package com;

import java.sql.Connection;
import java.sql.PreparedStatement;
import java.sql.ResultSet;
import java.sql.Statement;
import java.util.List;

public class creportsDao
{
  Connection connection = null;
  PreparedStatement ptmt = null;
  ResultSet rs = null;
  Statement stmt = null;
  String query = "";
  
  /* Error */
  public java.util.List<creportsBean> viewAllReports()
  {
	 return null;
	  
    // Byte code:
    //   0: ldc 40
    //   2: astore_1
    //   3: new 42	java/util/ArrayList
    //   6: dup
    //   7: invokespecial 44	java/util/ArrayList:<init>	()V
    //   10: astore_2
    //   11: aconst_null
    //   12: astore_3
    //   13: aload_0
    //   14: invokestatic 45	com/ConnectionProvider:getCon	()Ljava/sql/Connection;
    //   17: putfield 20	com/creportsDao:connection	Ljava/sql/Connection;
    //   20: aload_0
    //   21: aload_0
    //   22: getfield 20	com/creportsDao:connection	Ljava/sql/Connection;
    //   25: aload_1
    //   26: invokeinterface 51 2 0
    //   31: putfield 22	com/creportsDao:ptmt	Ljava/sql/PreparedStatement;
    //   34: aload_0
    //   35: aload_0
    //   36: getfield 22	com/creportsDao:ptmt	Ljava/sql/PreparedStatement;
    //   39: invokeinterface 57 1 0
    //   44: putfield 24	com/creportsDao:rs	Ljava/sql/ResultSet;
    //   47: goto +94 -> 141
    //   50: new 63	com/creportsBean
    //   53: dup
    //   54: invokespecial 65	com/creportsBean:<init>	()V
    //   57: astore_3
    //   58: aload_3
    //   59: aload_0
    //   60: getfield 24	com/creportsDao:rs	Ljava/sql/ResultSet;
    //   63: ldc 66
    //   65: invokeinterface 68 2 0
    //   70: invokevirtual 74	com/creportsBean:setRepid	(I)V
    //   73: aload_3
    //   74: aload_0
    //   75: getfield 24	com/creportsDao:rs	Ljava/sql/ResultSet;
    //   78: ldc 78
    //   80: invokeinterface 80 2 0
    //   85: invokevirtual 84	com/creportsBean:setName	(Ljava/lang/String;)V
    //   88: aload_3
    //   89: aload_0
    //   90: getfield 24	com/creportsDao:rs	Ljava/sql/ResultSet;
    //   93: ldc 88
    //   95: invokeinterface 80 2 0
    //   100: invokevirtual 90	com/creportsBean:setTitle	(Ljava/lang/String;)V
    //   103: aload_3
    //   104: aload_0
    //   105: getfield 24	com/creportsDao:rs	Ljava/sql/ResultSet;
    //   108: ldc 93
    //   110: invokeinterface 80 2 0
    //   115: invokevirtual 95	com/creportsBean:setQuery	(Ljava/lang/String;)V
    //   118: aload_3
    //   119: aload_0
    //   120: getfield 24	com/creportsDao:rs	Ljava/sql/ResultSet;
    //   123: ldc 98
    //   125: invokeinterface 80 2 0
    //   130: invokevirtual 100	com/creportsBean:setTemplate	(Ljava/lang/String;)V
    //   133: aload_2
    //   134: aload_3
    //   135: invokeinterface 103 2 0
    //   140: pop
    //   141: aload_0
    //   142: getfield 24	com/creportsDao:rs	Ljava/sql/ResultSet;
    //   145: invokeinterface 109 1 0
    //   150: ifne -100 -> 50
    //   153: aload_0
    //   154: getfield 24	com/creportsDao:rs	Ljava/sql/ResultSet;
    //   157: invokeinterface 113 1 0
    //   162: goto +70 -> 232
    //   165: astore 4
    //   167: aload 4
    //   169: invokevirtual 116	java/sql/SQLException:printStackTrace	()V
    //   172: aload_0
    //   173: getfield 26	com/creportsDao:stmt	Ljava/sql/Statement;
    //   176: ifnull +82 -> 258
    //   179: aload_0
    //   180: getfield 26	com/creportsDao:stmt	Ljava/sql/Statement;
    //   183: invokeinterface 121 1 0
    //   188: goto +70 -> 258
    //   191: astore 6
    //   193: aload 6
    //   195: invokevirtual 116	java/sql/SQLException:printStackTrace	()V
    //   198: goto +60 -> 258
    //   201: astore 5
    //   203: aload_0
    //   204: getfield 26	com/creportsDao:stmt	Ljava/sql/Statement;
    //   207: ifnull +22 -> 229
    //   210: aload_0
    //   211: getfield 26	com/creportsDao:stmt	Ljava/sql/Statement;
    //   214: invokeinterface 121 1 0
    //   219: goto +10 -> 229
    //   222: astore 6
    //   224: aload 6
    //   226: invokevirtual 116	java/sql/SQLException:printStackTrace	()V
    //   229: aload 5
    //   231: athrow
    //   232: aload_0
    //   233: getfield 26	com/creportsDao:stmt	Ljava/sql/Statement;
    //   236: ifnull +22 -> 258
    //   239: aload_0
    //   240: getfield 26	com/creportsDao:stmt	Ljava/sql/Statement;
    //   243: invokeinterface 121 1 0
    //   248: goto +10 -> 258
    //   251: astore 6
    //   253: aload 6
    //   255: invokevirtual 116	java/sql/SQLException:printStackTrace	()V
    //   258: aload_2
    //   259: areturn
    // Line number table:
    //   Java source line #24	-> byte code offset #0
    //   Java source line #25	-> byte code offset #3
    //   Java source line #26	-> byte code offset #11
    //   Java source line #28	-> byte code offset #13
    //   Java source line #29	-> byte code offset #20
    //   Java source line #30	-> byte code offset #34
    //   Java source line #31	-> byte code offset #47
    //   Java source line #32	-> byte code offset #50
    //   Java source line #33	-> byte code offset #58
    //   Java source line #34	-> byte code offset #73
    //   Java source line #35	-> byte code offset #88
    //   Java source line #36	-> byte code offset #103
    //   Java source line #37	-> byte code offset #118
    //   Java source line #38	-> byte code offset #133
    //   Java source line #31	-> byte code offset #141
    //   Java source line #40	-> byte code offset #153
    //   Java source line #42	-> byte code offset #162
    //   Java source line #46	-> byte code offset #172
    //   Java source line #47	-> byte code offset #179
    //   Java source line #48	-> byte code offset #188
    //   Java source line #49	-> byte code offset #193
    //   Java source line #44	-> byte code offset #201
    //   Java source line #46	-> byte code offset #203
    //   Java source line #47	-> byte code offset #210
    //   Java source line #48	-> byte code offset #219
    //   Java source line #49	-> byte code offset #224
    //   Java source line #51	-> byte code offset #229
    //   Java source line #46	-> byte code offset #232
    //   Java source line #47	-> byte code offset #239
    //   Java source line #48	-> byte code offset #248
    //   Java source line #49	-> byte code offset #253
    //   Java source line #52	-> byte code offset #258
    // Local variable table:
    //   start	length	slot	name	signature
    //   0	260	0	this	creportsDao
    //   2	24	1	query	String
    //   10	249	2	list	java.util.List<creportsBean>
    //   12	123	3	rep	creportsBean
    //   165	3	4	e	java.sql.SQLException
    //   201	29	5	localObject	Object
    //   191	3	6	e	java.sql.SQLException
    //   222	3	6	e	java.sql.SQLException
    //   251	3	6	e	java.sql.SQLException
    // Exception table:
    //   from	to	target	type
    //   13	162	165	java/sql/SQLException
    //   172	188	191	java/sql/SQLException
    //   13	172	201	finally
    //   203	219	222	java/sql/SQLException
    //   232	248	251	java/sql/SQLException
  }
  
  /* Error */
  public void getReport(creportsBean rep)
  {
    // Byte code:
    //   0: aload_0
    //   1: ldc -117
    //   3: putfield 30	com/creportsDao:query	Ljava/lang/String;
    //   6: aload_0
    //   7: invokestatic 45	com/ConnectionProvider:getCon	()Ljava/sql/Connection;
    //   10: putfield 20	com/creportsDao:connection	Ljava/sql/Connection;
    //   13: aload_0
    //   14: aload_0
    //   15: getfield 20	com/creportsDao:connection	Ljava/sql/Connection;
    //   18: aload_0
    //   19: getfield 30	com/creportsDao:query	Ljava/lang/String;
    //   22: invokeinterface 51 2 0
    //   27: putfield 22	com/creportsDao:ptmt	Ljava/sql/PreparedStatement;
    //   30: aload_0
    //   31: getfield 22	com/creportsDao:ptmt	Ljava/sql/PreparedStatement;
    //   34: iconst_1
    //   35: aload_1
    //   36: invokevirtual 141	com/creportsBean:getRepid	()I
    //   39: invokeinterface 145 3 0
    //   44: aload_0
    //   45: aload_0
    //   46: getfield 22	com/creportsDao:ptmt	Ljava/sql/PreparedStatement;
    //   49: invokeinterface 57 1 0
    //   54: putfield 24	com/creportsDao:rs	Ljava/sql/ResultSet;
    //   57: aload_0
    //   58: getfield 24	com/creportsDao:rs	Ljava/sql/ResultSet;
    //   61: invokeinterface 109 1 0
    //   66: pop
    //   67: aload_1
    //   68: aload_0
    //   69: getfield 24	com/creportsDao:rs	Ljava/sql/ResultSet;
    //   72: ldc 66
    //   74: invokeinterface 68 2 0
    //   79: invokevirtual 74	com/creportsBean:setRepid	(I)V
    //   82: aload_1
    //   83: aload_0
    //   84: getfield 24	com/creportsDao:rs	Ljava/sql/ResultSet;
    //   87: ldc 78
    //   89: invokeinterface 80 2 0
    //   94: invokevirtual 84	com/creportsBean:setName	(Ljava/lang/String;)V
    //   97: aload_1
    //   98: aload_0
    //   99: getfield 24	com/creportsDao:rs	Ljava/sql/ResultSet;
    //   102: ldc 88
    //   104: invokeinterface 80 2 0
    //   109: invokevirtual 90	com/creportsBean:setTitle	(Ljava/lang/String;)V
    //   112: aload_1
    //   113: aload_0
    //   114: getfield 24	com/creportsDao:rs	Ljava/sql/ResultSet;
    //   117: ldc 93
    //   119: invokeinterface 80 2 0
    //   124: invokevirtual 95	com/creportsBean:setQuery	(Ljava/lang/String;)V
    //   127: aload_1
    //   128: aload_0
    //   129: getfield 24	com/creportsDao:rs	Ljava/sql/ResultSet;
    //   132: ldc 98
    //   134: invokeinterface 80 2 0
    //   139: invokevirtual 100	com/creportsBean:setTemplate	(Ljava/lang/String;)V
    //   142: goto +118 -> 260
    //   145: astore_2
    //   146: aload_2
    //   147: invokevirtual 116	java/sql/SQLException:printStackTrace	()V
    //   150: aload_0
    //   151: getfield 24	com/creportsDao:rs	Ljava/sql/ResultSet;
    //   154: ifnull +12 -> 166
    //   157: aload_0
    //   158: getfield 24	com/creportsDao:rs	Ljava/sql/ResultSet;
    //   161: invokeinterface 113 1 0
    //   166: aload_0
    //   167: getfield 22	com/creportsDao:ptmt	Ljava/sql/PreparedStatement;
    //   170: ifnull +142 -> 312
    //   173: aload_0
    //   174: getfield 22	com/creportsDao:ptmt	Ljava/sql/PreparedStatement;
    //   177: invokeinterface 149 1 0
    //   182: goto +130 -> 312
    //   185: astore 4
    //   187: aload 4
    //   189: invokevirtual 116	java/sql/SQLException:printStackTrace	()V
    //   192: goto +120 -> 312
    //   195: astore 4
    //   197: aload 4
    //   199: invokevirtual 150	java/lang/Exception:printStackTrace	()V
    //   202: goto +110 -> 312
    //   205: astore_3
    //   206: aload_0
    //   207: getfield 24	com/creportsDao:rs	Ljava/sql/ResultSet;
    //   210: ifnull +12 -> 222
    //   213: aload_0
    //   214: getfield 24	com/creportsDao:rs	Ljava/sql/ResultSet;
    //   217: invokeinterface 113 1 0
    //   222: aload_0
    //   223: getfield 22	com/creportsDao:ptmt	Ljava/sql/PreparedStatement;
    //   226: ifnull +32 -> 258
    //   229: aload_0
    //   230: getfield 22	com/creportsDao:ptmt	Ljava/sql/PreparedStatement;
    //   233: invokeinterface 149 1 0
    //   238: goto +20 -> 258
    //   241: astore 4
    //   243: aload 4
    //   245: invokevirtual 116	java/sql/SQLException:printStackTrace	()V
    //   248: goto +10 -> 258
    //   251: astore 4
    //   253: aload 4
    //   255: invokevirtual 150	java/lang/Exception:printStackTrace	()V
    //   258: aload_3
    //   259: athrow
    //   260: aload_0
    //   261: getfield 24	com/creportsDao:rs	Ljava/sql/ResultSet;
    //   264: ifnull +12 -> 276
    //   267: aload_0
    //   268: getfield 24	com/creportsDao:rs	Ljava/sql/ResultSet;
    //   271: invokeinterface 113 1 0
    //   276: aload_0
    //   277: getfield 22	com/creportsDao:ptmt	Ljava/sql/PreparedStatement;
    //   280: ifnull +32 -> 312
    //   283: aload_0
    //   284: getfield 22	com/creportsDao:ptmt	Ljava/sql/PreparedStatement;
    //   287: invokeinterface 149 1 0
    //   292: goto +20 -> 312
    //   295: astore 4
    //   297: aload 4
    //   299: invokevirtual 116	java/sql/SQLException:printStackTrace	()V
    //   302: goto +10 -> 312
    //   305: astore 4
    //   307: aload 4
    //   309: invokevirtual 150	java/lang/Exception:printStackTrace	()V
    //   312: return
    // Line number table:
    //   Java source line #58	-> byte code offset #0
    //   Java source line #59	-> byte code offset #6
    //   Java source line #60	-> byte code offset #13
    //   Java source line #61	-> byte code offset #30
    //   Java source line #62	-> byte code offset #44
    //   Java source line #63	-> byte code offset #57
    //   Java source line #65	-> byte code offset #67
    //   Java source line #66	-> byte code offset #82
    //   Java source line #67	-> byte code offset #97
    //   Java source line #68	-> byte code offset #112
    //   Java source line #69	-> byte code offset #127
    //   Java source line #70	-> byte code offset #142
    //   Java source line #71	-> byte code offset #146
    //   Java source line #74	-> byte code offset #150
    //   Java source line #75	-> byte code offset #157
    //   Java source line #76	-> byte code offset #166
    //   Java source line #77	-> byte code offset #173
    //   Java source line #78	-> byte code offset #182
    //   Java source line #79	-> byte code offset #187
    //   Java source line #80	-> byte code offset #195
    //   Java source line #81	-> byte code offset #197
    //   Java source line #72	-> byte code offset #205
    //   Java source line #74	-> byte code offset #206
    //   Java source line #75	-> byte code offset #213
    //   Java source line #76	-> byte code offset #222
    //   Java source line #77	-> byte code offset #229
    //   Java source line #78	-> byte code offset #238
    //   Java source line #79	-> byte code offset #243
    //   Java source line #80	-> byte code offset #251
    //   Java source line #81	-> byte code offset #253
    //   Java source line #84	-> byte code offset #258
    //   Java source line #74	-> byte code offset #260
    //   Java source line #75	-> byte code offset #267
    //   Java source line #76	-> byte code offset #276
    //   Java source line #77	-> byte code offset #283
    //   Java source line #78	-> byte code offset #292
    //   Java source line #79	-> byte code offset #297
    //   Java source line #80	-> byte code offset #305
    //   Java source line #81	-> byte code offset #307
    //   Java source line #85	-> byte code offset #312
    // Local variable table:
    //   start	length	slot	name	signature
    //   0	313	0	this	creportsDao
    //   0	313	1	rep	creportsBean
    //   145	2	2	e	java.sql.SQLException
    //   205	54	3	localObject	Object
    //   185	3	4	e	java.sql.SQLException
    //   195	3	4	e	Exception
    //   241	3	4	e	java.sql.SQLException
    //   251	3	4	e	Exception
    //   295	3	4	e	java.sql.SQLException
    //   305	3	4	e	Exception
    // Exception table:
    //   from	to	target	type
    //   0	142	145	java/sql/SQLException
    //   150	182	185	java/sql/SQLException
    //   150	182	195	java/lang/Exception
    //   0	150	205	finally
    //   206	238	241	java/sql/SQLException
    //   206	238	251	java/lang/Exception
    //   260	292	295	java/sql/SQLException
    //   260	292	305	java/lang/Exception
  }
  
  /* Error */
  public void addReport(creportsBean rep)
  {
    // Byte code:
    //   0: aload_0
    //   1: ldc -101
    //   3: putfield 30	com/creportsDao:query	Ljava/lang/String;
    //   6: aload_0
    //   7: invokestatic 45	com/ConnectionProvider:getCon	()Ljava/sql/Connection;
    //   10: putfield 20	com/creportsDao:connection	Ljava/sql/Connection;
    //   13: aload_0
    //   14: aload_0
    //   15: getfield 20	com/creportsDao:connection	Ljava/sql/Connection;
    //   18: aload_0
    //   19: getfield 30	com/creportsDao:query	Ljava/lang/String;
    //   22: invokeinterface 51 2 0
    //   27: putfield 22	com/creportsDao:ptmt	Ljava/sql/PreparedStatement;
    //   30: aload_0
    //   31: getfield 22	com/creportsDao:ptmt	Ljava/sql/PreparedStatement;
    //   34: iconst_1
    //   35: aload_1
    //   36: invokevirtual 157	com/creportsBean:getName	()Ljava/lang/String;
    //   39: invokeinterface 161 3 0
    //   44: aload_0
    //   45: getfield 22	com/creportsDao:ptmt	Ljava/sql/PreparedStatement;
    //   48: iconst_2
    //   49: aload_1
    //   50: invokevirtual 165	com/creportsBean:getTitle	()Ljava/lang/String;
    //   53: invokeinterface 161 3 0
    //   58: aload_0
    //   59: getfield 22	com/creportsDao:ptmt	Ljava/sql/PreparedStatement;
    //   62: iconst_3
    //   63: aload_1
    //   64: invokevirtual 168	com/creportsBean:getQuery	()Ljava/lang/String;
    //   67: invokeinterface 161 3 0
    //   72: aload_0
    //   73: getfield 22	com/creportsDao:ptmt	Ljava/sql/PreparedStatement;
    //   76: iconst_4
    //   77: aload_1
    //   78: invokevirtual 171	com/creportsBean:getTemplate	()Ljava/lang/String;
    //   81: invokeinterface 161 3 0
    //   86: aload_0
    //   87: getfield 22	com/creportsDao:ptmt	Ljava/sql/PreparedStatement;
    //   90: invokeinterface 174 1 0
    //   95: pop
    //   96: goto +86 -> 182
    //   99: astore_2
    //   100: aload_2
    //   101: invokevirtual 116	java/sql/SQLException:printStackTrace	()V
    //   104: aload_0
    //   105: getfield 22	com/creportsDao:ptmt	Ljava/sql/PreparedStatement;
    //   108: ifnull +110 -> 218
    //   111: aload_0
    //   112: getfield 22	com/creportsDao:ptmt	Ljava/sql/PreparedStatement;
    //   115: invokeinterface 149 1 0
    //   120: goto +98 -> 218
    //   123: astore 4
    //   125: aload 4
    //   127: invokevirtual 116	java/sql/SQLException:printStackTrace	()V
    //   130: goto +88 -> 218
    //   133: astore 4
    //   135: aload 4
    //   137: invokevirtual 150	java/lang/Exception:printStackTrace	()V
    //   140: goto +78 -> 218
    //   143: astore_3
    //   144: aload_0
    //   145: getfield 22	com/creportsDao:ptmt	Ljava/sql/PreparedStatement;
    //   148: ifnull +32 -> 180
    //   151: aload_0
    //   152: getfield 22	com/creportsDao:ptmt	Ljava/sql/PreparedStatement;
    //   155: invokeinterface 149 1 0
    //   160: goto +20 -> 180
    //   163: astore 4
    //   165: aload 4
    //   167: invokevirtual 116	java/sql/SQLException:printStackTrace	()V
    //   170: goto +10 -> 180
    //   173: astore 4
    //   175: aload 4
    //   177: invokevirtual 150	java/lang/Exception:printStackTrace	()V
    //   180: aload_3
    //   181: athrow
    //   182: aload_0
    //   183: getfield 22	com/creportsDao:ptmt	Ljava/sql/PreparedStatement;
    //   186: ifnull +32 -> 218
    //   189: aload_0
    //   190: getfield 22	com/creportsDao:ptmt	Ljava/sql/PreparedStatement;
    //   193: invokeinterface 149 1 0
    //   198: goto +20 -> 218
    //   201: astore 4
    //   203: aload 4
    //   205: invokevirtual 116	java/sql/SQLException:printStackTrace	()V
    //   208: goto +10 -> 218
    //   211: astore 4
    //   213: aload 4
    //   215: invokevirtual 150	java/lang/Exception:printStackTrace	()V
    //   218: return
    // Line number table:
    //   Java source line #91	-> byte code offset #0
    //   Java source line #93	-> byte code offset #6
    //   Java source line #94	-> byte code offset #13
    //   Java source line #95	-> byte code offset #30
    //   Java source line #96	-> byte code offset #44
    //   Java source line #97	-> byte code offset #58
    //   Java source line #98	-> byte code offset #72
    //   Java source line #99	-> byte code offset #86
    //   Java source line #100	-> byte code offset #96
    //   Java source line #101	-> byte code offset #100
    //   Java source line #104	-> byte code offset #104
    //   Java source line #105	-> byte code offset #111
    //   Java source line #106	-> byte code offset #120
    //   Java source line #107	-> byte code offset #125
    //   Java source line #108	-> byte code offset #133
    //   Java source line #109	-> byte code offset #135
    //   Java source line #102	-> byte code offset #143
    //   Java source line #104	-> byte code offset #144
    //   Java source line #105	-> byte code offset #151
    //   Java source line #106	-> byte code offset #160
    //   Java source line #107	-> byte code offset #165
    //   Java source line #108	-> byte code offset #173
    //   Java source line #109	-> byte code offset #175
    //   Java source line #112	-> byte code offset #180
    //   Java source line #104	-> byte code offset #182
    //   Java source line #105	-> byte code offset #189
    //   Java source line #106	-> byte code offset #198
    //   Java source line #107	-> byte code offset #203
    //   Java source line #108	-> byte code offset #211
    //   Java source line #109	-> byte code offset #213
    //   Java source line #114	-> byte code offset #218
    // Local variable table:
    //   start	length	slot	name	signature
    //   0	219	0	this	creportsDao
    //   0	219	1	rep	creportsBean
    //   99	2	2	e	java.sql.SQLException
    //   143	38	3	localObject	Object
    //   123	3	4	e	java.sql.SQLException
    //   133	3	4	e	Exception
    //   163	3	4	e	java.sql.SQLException
    //   173	3	4	e	Exception
    //   201	3	4	e	java.sql.SQLException
    //   211	3	4	e	Exception
    // Exception table:
    //   from	to	target	type
    //   0	96	99	java/sql/SQLException
    //   104	120	123	java/sql/SQLException
    //   104	120	133	java/lang/Exception
    //   0	104	143	finally
    //   144	160	163	java/sql/SQLException
    //   144	160	173	java/lang/Exception
    //   182	198	201	java/sql/SQLException
    //   182	198	211	java/lang/Exception
  }
  
  /* Error */
  public void updateReport(creportsBean rep)
  {
    // Byte code:
    //   0: aload_0
    //   1: ldc -78
    //   3: putfield 30	com/creportsDao:query	Ljava/lang/String;
    //   6: aload_0
    //   7: invokestatic 45	com/ConnectionProvider:getCon	()Ljava/sql/Connection;
    //   10: putfield 20	com/creportsDao:connection	Ljava/sql/Connection;
    //   13: aload_0
    //   14: aload_0
    //   15: getfield 20	com/creportsDao:connection	Ljava/sql/Connection;
    //   18: aload_0
    //   19: getfield 30	com/creportsDao:query	Ljava/lang/String;
    //   22: invokeinterface 51 2 0
    //   27: putfield 22	com/creportsDao:ptmt	Ljava/sql/PreparedStatement;
    //   30: aload_0
    //   31: getfield 22	com/creportsDao:ptmt	Ljava/sql/PreparedStatement;
    //   34: iconst_1
    //   35: aload_1
    //   36: invokevirtual 157	com/creportsBean:getName	()Ljava/lang/String;
    //   39: invokeinterface 161 3 0
    //   44: aload_0
    //   45: getfield 22	com/creportsDao:ptmt	Ljava/sql/PreparedStatement;
    //   48: iconst_2
    //   49: aload_1
    //   50: invokevirtual 165	com/creportsBean:getTitle	()Ljava/lang/String;
    //   53: invokeinterface 161 3 0
    //   58: aload_0
    //   59: getfield 22	com/creportsDao:ptmt	Ljava/sql/PreparedStatement;
    //   62: iconst_3
    //   63: aload_1
    //   64: invokevirtual 168	com/creportsBean:getQuery	()Ljava/lang/String;
    //   67: invokeinterface 161 3 0
    //   72: aload_0
    //   73: getfield 22	com/creportsDao:ptmt	Ljava/sql/PreparedStatement;
    //   76: iconst_4
    //   77: aload_1
    //   78: invokevirtual 171	com/creportsBean:getTemplate	()Ljava/lang/String;
    //   81: invokeinterface 161 3 0
    //   86: aload_0
    //   87: getfield 22	com/creportsDao:ptmt	Ljava/sql/PreparedStatement;
    //   90: iconst_5
    //   91: aload_1
    //   92: invokevirtual 141	com/creportsBean:getRepid	()I
    //   95: invokeinterface 145 3 0
    //   100: aload_0
    //   101: getfield 22	com/creportsDao:ptmt	Ljava/sql/PreparedStatement;
    //   104: invokeinterface 174 1 0
    //   109: pop
    //   110: goto +86 -> 196
    //   113: astore_2
    //   114: aload_2
    //   115: invokevirtual 116	java/sql/SQLException:printStackTrace	()V
    //   118: aload_0
    //   119: getfield 22	com/creportsDao:ptmt	Ljava/sql/PreparedStatement;
    //   122: ifnull +110 -> 232
    //   125: aload_0
    //   126: getfield 22	com/creportsDao:ptmt	Ljava/sql/PreparedStatement;
    //   129: invokeinterface 149 1 0
    //   134: goto +98 -> 232
    //   137: astore 4
    //   139: aload 4
    //   141: invokevirtual 116	java/sql/SQLException:printStackTrace	()V
    //   144: goto +88 -> 232
    //   147: astore 4
    //   149: aload 4
    //   151: invokevirtual 150	java/lang/Exception:printStackTrace	()V
    //   154: goto +78 -> 232
    //   157: astore_3
    //   158: aload_0
    //   159: getfield 22	com/creportsDao:ptmt	Ljava/sql/PreparedStatement;
    //   162: ifnull +32 -> 194
    //   165: aload_0
    //   166: getfield 22	com/creportsDao:ptmt	Ljava/sql/PreparedStatement;
    //   169: invokeinterface 149 1 0
    //   174: goto +20 -> 194
    //   177: astore 4
    //   179: aload 4
    //   181: invokevirtual 116	java/sql/SQLException:printStackTrace	()V
    //   184: goto +10 -> 194
    //   187: astore 4
    //   189: aload 4
    //   191: invokevirtual 150	java/lang/Exception:printStackTrace	()V
    //   194: aload_3
    //   195: athrow
    //   196: aload_0
    //   197: getfield 22	com/creportsDao:ptmt	Ljava/sql/PreparedStatement;
    //   200: ifnull +32 -> 232
    //   203: aload_0
    //   204: getfield 22	com/creportsDao:ptmt	Ljava/sql/PreparedStatement;
    //   207: invokeinterface 149 1 0
    //   212: goto +20 -> 232
    //   215: astore 4
    //   217: aload 4
    //   219: invokevirtual 116	java/sql/SQLException:printStackTrace	()V
    //   222: goto +10 -> 232
    //   225: astore 4
    //   227: aload 4
    //   229: invokevirtual 150	java/lang/Exception:printStackTrace	()V
    //   232: return
    // Line number table:
    //   Java source line #119	-> byte code offset #0
    //   Java source line #120	-> byte code offset #6
    //   Java source line #121	-> byte code offset #13
    //   Java source line #122	-> byte code offset #30
    //   Java source line #123	-> byte code offset #44
    //   Java source line #124	-> byte code offset #58
    //   Java source line #125	-> byte code offset #72
    //   Java source line #126	-> byte code offset #86
    //   Java source line #127	-> byte code offset #100
    //   Java source line #128	-> byte code offset #110
    //   Java source line #129	-> byte code offset #114
    //   Java source line #132	-> byte code offset #118
    //   Java source line #133	-> byte code offset #125
    //   Java source line #134	-> byte code offset #134
    //   Java source line #135	-> byte code offset #139
    //   Java source line #136	-> byte code offset #147
    //   Java source line #137	-> byte code offset #149
    //   Java source line #130	-> byte code offset #157
    //   Java source line #132	-> byte code offset #158
    //   Java source line #133	-> byte code offset #165
    //   Java source line #134	-> byte code offset #174
    //   Java source line #135	-> byte code offset #179
    //   Java source line #136	-> byte code offset #187
    //   Java source line #137	-> byte code offset #189
    //   Java source line #140	-> byte code offset #194
    //   Java source line #132	-> byte code offset #196
    //   Java source line #133	-> byte code offset #203
    //   Java source line #134	-> byte code offset #212
    //   Java source line #135	-> byte code offset #217
    //   Java source line #136	-> byte code offset #225
    //   Java source line #137	-> byte code offset #227
    //   Java source line #142	-> byte code offset #232
    // Local variable table:
    //   start	length	slot	name	signature
    //   0	233	0	this	creportsDao
    //   0	233	1	rep	creportsBean
    //   113	2	2	e	java.sql.SQLException
    //   157	38	3	localObject	Object
    //   137	3	4	e	java.sql.SQLException
    //   147	3	4	e	Exception
    //   177	3	4	e	java.sql.SQLException
    //   187	3	4	e	Exception
    //   215	3	4	e	java.sql.SQLException
    //   225	3	4	e	Exception
    // Exception table:
    //   from	to	target	type
    //   0	110	113	java/sql/SQLException
    //   118	134	137	java/sql/SQLException
    //   118	134	147	java/lang/Exception
    //   0	118	157	finally
    //   158	174	177	java/sql/SQLException
    //   158	174	187	java/lang/Exception
    //   196	212	215	java/sql/SQLException
    //   196	212	225	java/lang/Exception
  }
  
  /* Error */
  public void delete(int repid)
  {
    // Byte code:
    //   0: aload_0
    //   1: invokestatic 45	com/ConnectionProvider:getCon	()Ljava/sql/Connection;
    //   4: putfield 20	com/creportsDao:connection	Ljava/sql/Connection;
    //   7: aload_0
    //   8: ldc -75
    //   10: putfield 30	com/creportsDao:query	Ljava/lang/String;
    //   13: aload_0
    //   14: aload_0
    //   15: getfield 20	com/creportsDao:connection	Ljava/sql/Connection;
    //   18: aload_0
    //   19: getfield 30	com/creportsDao:query	Ljava/lang/String;
    //   22: invokeinterface 51 2 0
    //   27: putfield 22	com/creportsDao:ptmt	Ljava/sql/PreparedStatement;
    //   30: aload_0
    //   31: getfield 22	com/creportsDao:ptmt	Ljava/sql/PreparedStatement;
    //   34: iconst_1
    //   35: iload_1
    //   36: invokeinterface 145 3 0
    //   41: aload_0
    //   42: getfield 22	com/creportsDao:ptmt	Ljava/sql/PreparedStatement;
    //   45: invokeinterface 174 1 0
    //   50: pop
    //   51: goto +86 -> 137
    //   54: astore_2
    //   55: aload_2
    //   56: invokevirtual 116	java/sql/SQLException:printStackTrace	()V
    //   59: aload_0
    //   60: getfield 22	com/creportsDao:ptmt	Ljava/sql/PreparedStatement;
    //   63: ifnull +110 -> 173
    //   66: aload_0
    //   67: getfield 22	com/creportsDao:ptmt	Ljava/sql/PreparedStatement;
    //   70: invokeinterface 149 1 0
    //   75: goto +98 -> 173
    //   78: astore 4
    //   80: aload 4
    //   82: invokevirtual 116	java/sql/SQLException:printStackTrace	()V
    //   85: goto +88 -> 173
    //   88: astore 4
    //   90: aload 4
    //   92: invokevirtual 150	java/lang/Exception:printStackTrace	()V
    //   95: goto +78 -> 173
    //   98: astore_3
    //   99: aload_0
    //   100: getfield 22	com/creportsDao:ptmt	Ljava/sql/PreparedStatement;
    //   103: ifnull +32 -> 135
    //   106: aload_0
    //   107: getfield 22	com/creportsDao:ptmt	Ljava/sql/PreparedStatement;
    //   110: invokeinterface 149 1 0
    //   115: goto +20 -> 135
    //   118: astore 4
    //   120: aload 4
    //   122: invokevirtual 116	java/sql/SQLException:printStackTrace	()V
    //   125: goto +10 -> 135
    //   128: astore 4
    //   130: aload 4
    //   132: invokevirtual 150	java/lang/Exception:printStackTrace	()V
    //   135: aload_3
    //   136: athrow
    //   137: aload_0
    //   138: getfield 22	com/creportsDao:ptmt	Ljava/sql/PreparedStatement;
    //   141: ifnull +32 -> 173
    //   144: aload_0
    //   145: getfield 22	com/creportsDao:ptmt	Ljava/sql/PreparedStatement;
    //   148: invokeinterface 149 1 0
    //   153: goto +20 -> 173
    //   156: astore 4
    //   158: aload 4
    //   160: invokevirtual 116	java/sql/SQLException:printStackTrace	()V
    //   163: goto +10 -> 173
    //   166: astore 4
    //   168: aload 4
    //   170: invokevirtual 150	java/lang/Exception:printStackTrace	()V
    //   173: return
    // Line number table:
    //   Java source line #147	-> byte code offset #0
    //   Java source line #148	-> byte code offset #7
    //   Java source line #149	-> byte code offset #13
    //   Java source line #150	-> byte code offset #30
    //   Java source line #151	-> byte code offset #41
    //   Java source line #152	-> byte code offset #51
    //   Java source line #153	-> byte code offset #55
    //   Java source line #156	-> byte code offset #59
    //   Java source line #157	-> byte code offset #66
    //   Java source line #158	-> byte code offset #75
    //   Java source line #159	-> byte code offset #88
    //   Java source line #154	-> byte code offset #98
    //   Java source line #156	-> byte code offset #99
    //   Java source line #157	-> byte code offset #106
    //   Java source line #158	-> byte code offset #115
    //   Java source line #159	-> byte code offset #128
    //   Java source line #161	-> byte code offset #135
    //   Java source line #156	-> byte code offset #137
    //   Java source line #157	-> byte code offset #144
    //   Java source line #158	-> byte code offset #153
    //   Java source line #159	-> byte code offset #166
    //   Java source line #162	-> byte code offset #173
    // Local variable table:
    //   start	length	slot	name	signature
    //   0	174	0	this	creportsDao
    //   0	174	1	repid	int
    //   54	2	2	e	java.sql.SQLException
    //   98	38	3	localObject	Object
    //   78	3	4	e	java.sql.SQLException
    //   88	3	4	e	Exception
    //   118	3	4	e	java.sql.SQLException
    //   128	3	4	e	Exception
    //   156	3	4	e	java.sql.SQLException
    //   166	3	4	e	Exception
    // Exception table:
    //   from	to	target	type
    //   0	51	54	java/sql/SQLException
    //   59	75	78	java/sql/SQLException
    //   59	75	88	java/lang/Exception
    //   0	59	98	finally
    //   99	115	118	java/sql/SQLException
    //   99	115	128	java/lang/Exception
    //   137	153	156	java/sql/SQLException
    //   137	153	166	java/lang/Exception
  }
}
