package com;

import java.sql.Connection;
import java.sql.PreparedStatement;
import java.sql.ResultSet;
import java.sql.Statement;

public class jobsDao
{
  Connection connection = null;
  PreparedStatement ptmt = null;
  ResultSet rs = null;
  Statement stmt = null;
  String query = "";
  
  /* Error */
  public java.util.List<jobsBean> viewAlljobs()
  {
	  return null;
    // Byte code:
    //   0: ldc 40
    //   2: astore_1
    //   3: new 42	java/util/ArrayList
    //   6: dup
    //   7: invokespecial 44	java/util/ArrayList:<init>	()V
    //   10: astore_2
    //   11: aconst_null
    //   12: astore_3
    //   13: aload_0
    //   14: invokestatic 45	com/ConnectionProvider:getCon	()Ljava/sql/Connection;
    //   17: putfield 20	com/jobsDao:connection	Ljava/sql/Connection;
    //   20: aload_0
    //   21: aload_0
    //   22: getfield 20	com/jobsDao:connection	Ljava/sql/Connection;
    //   25: aload_1
    //   26: invokeinterface 51 2 0
    //   31: putfield 22	com/jobsDao:ptmt	Ljava/sql/PreparedStatement;
    //   34: aload_0
    //   35: aload_0
    //   36: getfield 22	com/jobsDao:ptmt	Ljava/sql/PreparedStatement;
    //   39: invokeinterface 57 1 0
    //   44: putfield 24	com/jobsDao:rs	Ljava/sql/ResultSet;
    //   47: goto +139 -> 186
    //   50: new 63	com/jobsBean
    //   53: dup
    //   54: invokespecial 65	com/jobsBean:<init>	()V
    //   57: astore_3
    //   58: aload_3
    //   59: aload_0
    //   60: getfield 24	com/jobsDao:rs	Ljava/sql/ResultSet;
    //   63: ldc 66
    //   65: invokeinterface 68 2 0
    //   70: invokevirtual 74	com/jobsBean:setJobid	(I)V
    //   73: aload_3
    //   74: aload_0
    //   75: getfield 24	com/jobsDao:rs	Ljava/sql/ResultSet;
    //   78: ldc 78
    //   80: invokeinterface 80 2 0
    //   85: invokevirtual 84	com/jobsBean:setName	(Ljava/lang/String;)V
    //   88: aload_3
    //   89: aload_0
    //   90: getfield 24	com/jobsDao:rs	Ljava/sql/ResultSet;
    //   93: ldc 88
    //   95: invokeinterface 80 2 0
    //   100: invokevirtual 90	com/jobsBean:setLdate	(Ljava/lang/String;)V
    //   103: aload_3
    //   104: aload_0
    //   105: getfield 24	com/jobsDao:rs	Ljava/sql/ResultSet;
    //   108: ldc 93
    //   110: invokeinterface 80 2 0
    //   115: invokevirtual 95	com/jobsBean:setNdate	(Ljava/lang/String;)V
    //   118: aload_3
    //   119: aload_0
    //   120: getfield 24	com/jobsDao:rs	Ljava/sql/ResultSet;
    //   123: ldc 98
    //   125: invokeinterface 80 2 0
    //   130: invokevirtual 100	com/jobsBean:setBroken	(Ljava/lang/String;)V
    //   133: aload_3
    //   134: aload_0
    //   135: getfield 24	com/jobsDao:rs	Ljava/sql/ResultSet;
    //   138: ldc 103
    //   140: invokeinterface 68 2 0
    //   145: invokevirtual 105	com/jobsBean:setInterval	(I)V
    //   148: aload_3
    //   149: aload_0
    //   150: getfield 24	com/jobsDao:rs	Ljava/sql/ResultSet;
    //   153: ldc 108
    //   155: invokeinterface 80 2 0
    //   160: invokevirtual 110	com/jobsBean:setWhat	(Ljava/lang/String;)V
    //   163: aload_3
    //   164: aload_0
    //   165: getfield 24	com/jobsDao:rs	Ljava/sql/ResultSet;
    //   168: ldc 113
    //   170: invokeinterface 80 2 0
    //   175: invokevirtual 115	com/jobsBean:setIdate	(Ljava/lang/String;)V
    //   178: aload_2
    //   179: aload_3
    //   180: invokeinterface 118 2 0
    //   185: pop
    //   186: aload_0
    //   187: getfield 24	com/jobsDao:rs	Ljava/sql/ResultSet;
    //   190: invokeinterface 124 1 0
    //   195: ifne -145 -> 50
    //   198: aload_0
    //   199: getfield 24	com/jobsDao:rs	Ljava/sql/ResultSet;
    //   202: invokeinterface 128 1 0
    //   207: goto +70 -> 277
    //   210: astore 4
    //   212: aload 4
    //   214: invokevirtual 131	java/sql/SQLException:printStackTrace	()V
    //   217: aload_0
    //   218: getfield 26	com/jobsDao:stmt	Ljava/sql/Statement;
    //   221: ifnull +82 -> 303
    //   224: aload_0
    //   225: getfield 26	com/jobsDao:stmt	Ljava/sql/Statement;
    //   228: invokeinterface 136 1 0
    //   233: goto +70 -> 303
    //   236: astore 6
    //   238: aload 6
    //   240: invokevirtual 131	java/sql/SQLException:printStackTrace	()V
    //   243: goto +60 -> 303
    //   246: astore 5
    //   248: aload_0
    //   249: getfield 26	com/jobsDao:stmt	Ljava/sql/Statement;
    //   252: ifnull +22 -> 274
    //   255: aload_0
    //   256: getfield 26	com/jobsDao:stmt	Ljava/sql/Statement;
    //   259: invokeinterface 136 1 0
    //   264: goto +10 -> 274
    //   267: astore 6
    //   269: aload 6
    //   271: invokevirtual 131	java/sql/SQLException:printStackTrace	()V
    //   274: aload 5
    //   276: athrow
    //   277: aload_0
    //   278: getfield 26	com/jobsDao:stmt	Ljava/sql/Statement;
    //   281: ifnull +22 -> 303
    //   284: aload_0
    //   285: getfield 26	com/jobsDao:stmt	Ljava/sql/Statement;
    //   288: invokeinterface 136 1 0
    //   293: goto +10 -> 303
    //   296: astore 6
    //   298: aload 6
    //   300: invokevirtual 131	java/sql/SQLException:printStackTrace	()V
    //   303: aload_2
    //   304: areturn
    // Line number table:
    //   Java source line #25	-> byte code offset #0
    //   Java source line #27	-> byte code offset #3
    //   Java source line #28	-> byte code offset #11
    //   Java source line #30	-> byte code offset #13
    //   Java source line #31	-> byte code offset #20
    //   Java source line #32	-> byte code offset #34
    //   Java source line #33	-> byte code offset #47
    //   Java source line #34	-> byte code offset #50
    //   Java source line #35	-> byte code offset #58
    //   Java source line #36	-> byte code offset #73
    //   Java source line #37	-> byte code offset #88
    //   Java source line #38	-> byte code offset #103
    //   Java source line #39	-> byte code offset #118
    //   Java source line #40	-> byte code offset #133
    //   Java source line #41	-> byte code offset #148
    //   Java source line #42	-> byte code offset #163
    //   Java source line #43	-> byte code offset #178
    //   Java source line #33	-> byte code offset #186
    //   Java source line #45	-> byte code offset #198
    //   Java source line #47	-> byte code offset #207
    //   Java source line #51	-> byte code offset #217
    //   Java source line #52	-> byte code offset #224
    //   Java source line #53	-> byte code offset #233
    //   Java source line #54	-> byte code offset #238
    //   Java source line #49	-> byte code offset #246
    //   Java source line #51	-> byte code offset #248
    //   Java source line #52	-> byte code offset #255
    //   Java source line #53	-> byte code offset #264
    //   Java source line #54	-> byte code offset #269
    //   Java source line #56	-> byte code offset #274
    //   Java source line #51	-> byte code offset #277
    //   Java source line #52	-> byte code offset #284
    //   Java source line #53	-> byte code offset #293
    //   Java source line #54	-> byte code offset #298
    //   Java source line #57	-> byte code offset #303
    // Local variable table:
    //   start	length	slot	name	signature
    //   0	305	0	this	jobsDao
    //   2	24	1	query	String
    //   10	294	2	list	java.util.List<jobsBean>
    //   12	168	3	job	jobsBean
    //   210	3	4	e	java.sql.SQLException
    //   246	29	5	localObject	Object
    //   236	3	6	e	java.sql.SQLException
    //   267	3	6	e	java.sql.SQLException
    //   296	3	6	e	java.sql.SQLException
    // Exception table:
    //   from	to	target	type
    //   13	207	210	java/sql/SQLException
    //   217	233	236	java/sql/SQLException
    //   13	217	246	finally
    //   248	264	267	java/sql/SQLException
    //   277	293	296	java/sql/SQLException
  }
  
  /* Error */
  public void getJob(jobsBean job)
  {
    // Byte code:
    //   0: aload_0
    //   1: ldc -102
    //   3: putfield 30	com/jobsDao:query	Ljava/lang/String;
    //   6: aload_0
    //   7: invokestatic 45	com/ConnectionProvider:getCon	()Ljava/sql/Connection;
    //   10: putfield 20	com/jobsDao:connection	Ljava/sql/Connection;
    //   13: aload_0
    //   14: aload_0
    //   15: getfield 20	com/jobsDao:connection	Ljava/sql/Connection;
    //   18: aload_0
    //   19: getfield 30	com/jobsDao:query	Ljava/lang/String;
    //   22: invokeinterface 51 2 0
    //   27: putfield 22	com/jobsDao:ptmt	Ljava/sql/PreparedStatement;
    //   30: aload_0
    //   31: getfield 22	com/jobsDao:ptmt	Ljava/sql/PreparedStatement;
    //   34: iconst_1
    //   35: aload_1
    //   36: invokevirtual 156	com/jobsBean:getJobid	()I
    //   39: invokeinterface 160 3 0
    //   44: aload_0
    //   45: aload_0
    //   46: getfield 22	com/jobsDao:ptmt	Ljava/sql/PreparedStatement;
    //   49: invokeinterface 57 1 0
    //   54: putfield 24	com/jobsDao:rs	Ljava/sql/ResultSet;
    //   57: aload_0
    //   58: getfield 24	com/jobsDao:rs	Ljava/sql/ResultSet;
    //   61: invokeinterface 124 1 0
    //   66: pop
    //   67: aload_1
    //   68: aload_0
    //   69: getfield 24	com/jobsDao:rs	Ljava/sql/ResultSet;
    //   72: ldc 66
    //   74: invokeinterface 68 2 0
    //   79: invokevirtual 74	com/jobsBean:setJobid	(I)V
    //   82: aload_1
    //   83: aload_0
    //   84: getfield 24	com/jobsDao:rs	Ljava/sql/ResultSet;
    //   87: ldc 78
    //   89: invokeinterface 80 2 0
    //   94: invokevirtual 84	com/jobsBean:setName	(Ljava/lang/String;)V
    //   97: aload_1
    //   98: aload_0
    //   99: getfield 24	com/jobsDao:rs	Ljava/sql/ResultSet;
    //   102: ldc 88
    //   104: invokeinterface 80 2 0
    //   109: invokevirtual 90	com/jobsBean:setLdate	(Ljava/lang/String;)V
    //   112: aload_1
    //   113: aload_0
    //   114: getfield 24	com/jobsDao:rs	Ljava/sql/ResultSet;
    //   117: ldc 93
    //   119: invokeinterface 80 2 0
    //   124: invokevirtual 95	com/jobsBean:setNdate	(Ljava/lang/String;)V
    //   127: aload_1
    //   128: aload_0
    //   129: getfield 24	com/jobsDao:rs	Ljava/sql/ResultSet;
    //   132: ldc -92
    //   134: invokeinterface 80 2 0
    //   139: invokevirtual 166	com/jobsBean:setNhour	(Ljava/lang/String;)V
    //   142: aload_1
    //   143: aload_0
    //   144: getfield 24	com/jobsDao:rs	Ljava/sql/ResultSet;
    //   147: ldc -87
    //   149: invokeinterface 80 2 0
    //   154: invokevirtual 171	com/jobsBean:setNmin	(Ljava/lang/String;)V
    //   157: aload_1
    //   158: aload_0
    //   159: getfield 24	com/jobsDao:rs	Ljava/sql/ResultSet;
    //   162: ldc 98
    //   164: invokeinterface 80 2 0
    //   169: invokevirtual 100	com/jobsBean:setBroken	(Ljava/lang/String;)V
    //   172: aload_1
    //   173: aload_0
    //   174: getfield 24	com/jobsDao:rs	Ljava/sql/ResultSet;
    //   177: ldc 103
    //   179: invokeinterface 68 2 0
    //   184: invokevirtual 105	com/jobsBean:setInterval	(I)V
    //   187: aload_1
    //   188: aload_0
    //   189: getfield 24	com/jobsDao:rs	Ljava/sql/ResultSet;
    //   192: ldc 108
    //   194: invokeinterface 80 2 0
    //   199: invokevirtual 110	com/jobsBean:setWhat	(Ljava/lang/String;)V
    //   202: aload_1
    //   203: aload_0
    //   204: getfield 24	com/jobsDao:rs	Ljava/sql/ResultSet;
    //   207: ldc 113
    //   209: invokeinterface 80 2 0
    //   214: invokevirtual 115	com/jobsBean:setIdate	(Ljava/lang/String;)V
    //   217: goto +118 -> 335
    //   220: astore_2
    //   221: aload_2
    //   222: invokevirtual 131	java/sql/SQLException:printStackTrace	()V
    //   225: aload_0
    //   226: getfield 24	com/jobsDao:rs	Ljava/sql/ResultSet;
    //   229: ifnull +12 -> 241
    //   232: aload_0
    //   233: getfield 24	com/jobsDao:rs	Ljava/sql/ResultSet;
    //   236: invokeinterface 128 1 0
    //   241: aload_0
    //   242: getfield 22	com/jobsDao:ptmt	Ljava/sql/PreparedStatement;
    //   245: ifnull +142 -> 387
    //   248: aload_0
    //   249: getfield 22	com/jobsDao:ptmt	Ljava/sql/PreparedStatement;
    //   252: invokeinterface 174 1 0
    //   257: goto +130 -> 387
    //   260: astore 4
    //   262: aload 4
    //   264: invokevirtual 131	java/sql/SQLException:printStackTrace	()V
    //   267: goto +120 -> 387
    //   270: astore 4
    //   272: aload 4
    //   274: invokevirtual 175	java/lang/Exception:printStackTrace	()V
    //   277: goto +110 -> 387
    //   280: astore_3
    //   281: aload_0
    //   282: getfield 24	com/jobsDao:rs	Ljava/sql/ResultSet;
    //   285: ifnull +12 -> 297
    //   288: aload_0
    //   289: getfield 24	com/jobsDao:rs	Ljava/sql/ResultSet;
    //   292: invokeinterface 128 1 0
    //   297: aload_0
    //   298: getfield 22	com/jobsDao:ptmt	Ljava/sql/PreparedStatement;
    //   301: ifnull +32 -> 333
    //   304: aload_0
    //   305: getfield 22	com/jobsDao:ptmt	Ljava/sql/PreparedStatement;
    //   308: invokeinterface 174 1 0
    //   313: goto +20 -> 333
    //   316: astore 4
    //   318: aload 4
    //   320: invokevirtual 131	java/sql/SQLException:printStackTrace	()V
    //   323: goto +10 -> 333
    //   326: astore 4
    //   328: aload 4
    //   330: invokevirtual 175	java/lang/Exception:printStackTrace	()V
    //   333: aload_3
    //   334: athrow
    //   335: aload_0
    //   336: getfield 24	com/jobsDao:rs	Ljava/sql/ResultSet;
    //   339: ifnull +12 -> 351
    //   342: aload_0
    //   343: getfield 24	com/jobsDao:rs	Ljava/sql/ResultSet;
    //   346: invokeinterface 128 1 0
    //   351: aload_0
    //   352: getfield 22	com/jobsDao:ptmt	Ljava/sql/PreparedStatement;
    //   355: ifnull +32 -> 387
    //   358: aload_0
    //   359: getfield 22	com/jobsDao:ptmt	Ljava/sql/PreparedStatement;
    //   362: invokeinterface 174 1 0
    //   367: goto +20 -> 387
    //   370: astore 4
    //   372: aload 4
    //   374: invokevirtual 131	java/sql/SQLException:printStackTrace	()V
    //   377: goto +10 -> 387
    //   380: astore 4
    //   382: aload 4
    //   384: invokevirtual 175	java/lang/Exception:printStackTrace	()V
    //   387: return
    // Line number table:
    //   Java source line #63	-> byte code offset #0
    //   Java source line #65	-> byte code offset #6
    //   Java source line #66	-> byte code offset #13
    //   Java source line #67	-> byte code offset #30
    //   Java source line #69	-> byte code offset #44
    //   Java source line #70	-> byte code offset #57
    //   Java source line #71	-> byte code offset #67
    //   Java source line #72	-> byte code offset #82
    //   Java source line #73	-> byte code offset #97
    //   Java source line #74	-> byte code offset #112
    //   Java source line #75	-> byte code offset #127
    //   Java source line #76	-> byte code offset #142
    //   Java source line #77	-> byte code offset #157
    //   Java source line #78	-> byte code offset #172
    //   Java source line #79	-> byte code offset #187
    //   Java source line #80	-> byte code offset #202
    //   Java source line #81	-> byte code offset #217
    //   Java source line #82	-> byte code offset #221
    //   Java source line #85	-> byte code offset #225
    //   Java source line #86	-> byte code offset #232
    //   Java source line #87	-> byte code offset #241
    //   Java source line #88	-> byte code offset #248
    //   Java source line #89	-> byte code offset #257
    //   Java source line #90	-> byte code offset #262
    //   Java source line #91	-> byte code offset #270
    //   Java source line #92	-> byte code offset #272
    //   Java source line #83	-> byte code offset #280
    //   Java source line #85	-> byte code offset #281
    //   Java source line #86	-> byte code offset #288
    //   Java source line #87	-> byte code offset #297
    //   Java source line #88	-> byte code offset #304
    //   Java source line #89	-> byte code offset #313
    //   Java source line #90	-> byte code offset #318
    //   Java source line #91	-> byte code offset #326
    //   Java source line #92	-> byte code offset #328
    //   Java source line #95	-> byte code offset #333
    //   Java source line #85	-> byte code offset #335
    //   Java source line #86	-> byte code offset #342
    //   Java source line #87	-> byte code offset #351
    //   Java source line #88	-> byte code offset #358
    //   Java source line #89	-> byte code offset #367
    //   Java source line #90	-> byte code offset #372
    //   Java source line #91	-> byte code offset #380
    //   Java source line #92	-> byte code offset #382
    //   Java source line #96	-> byte code offset #387
    // Local variable table:
    //   start	length	slot	name	signature
    //   0	388	0	this	jobsDao
    //   0	388	1	job	jobsBean
    //   220	2	2	e	java.sql.SQLException
    //   280	54	3	localObject	Object
    //   260	3	4	e	java.sql.SQLException
    //   270	3	4	e	Exception
    //   316	3	4	e	java.sql.SQLException
    //   326	3	4	e	Exception
    //   370	3	4	e	java.sql.SQLException
    //   380	3	4	e	Exception
    // Exception table:
    //   from	to	target	type
    //   0	217	220	java/sql/SQLException
    //   225	257	260	java/sql/SQLException
    //   225	257	270	java/lang/Exception
    //   0	225	280	finally
    //   281	313	316	java/sql/SQLException
    //   281	313	326	java/lang/Exception
    //   335	367	370	java/sql/SQLException
    //   335	367	380	java/lang/Exception
  }
  
  /* Error */
  public void addjob(jobsBean job)
  {
    // Byte code:
    //   0: aload_0
    //   1: ldc -76
    //   3: putfield 30	com/jobsDao:query	Ljava/lang/String;
    //   6: aload_0
    //   7: invokestatic 45	com/ConnectionProvider:getCon	()Ljava/sql/Connection;
    //   10: putfield 20	com/jobsDao:connection	Ljava/sql/Connection;
    //   13: aload_1
    //   14: invokevirtual 182	com/jobsBean:getInterval	()I
    //   17: istore_2
    //   18: aload_1
    //   19: invokevirtual 185	com/jobsBean:getInterval_param	()Ljava/lang/String;
    //   22: ldc -67
    //   24: invokevirtual 191	java/lang/String:equalsIgnoreCase	(Ljava/lang/String;)Z
    //   27: ifeq +14 -> 41
    //   30: aload_1
    //   31: invokevirtual 182	com/jobsBean:getInterval	()I
    //   34: bipush 60
    //   36: imul
    //   37: istore_2
    //   38: goto +26 -> 64
    //   41: aload_1
    //   42: invokevirtual 185	com/jobsBean:getInterval_param	()Ljava/lang/String;
    //   45: ldc -61
    //   47: invokevirtual 191	java/lang/String:equalsIgnoreCase	(Ljava/lang/String;)Z
    //   50: ifeq +14 -> 64
    //   53: aload_1
    //   54: invokevirtual 182	com/jobsBean:getInterval	()I
    //   57: bipush 60
    //   59: imul
    //   60: bipush 24
    //   62: imul
    //   63: istore_2
    //   64: aload_0
    //   65: aload_0
    //   66: getfield 20	com/jobsDao:connection	Ljava/sql/Connection;
    //   69: aload_0
    //   70: getfield 30	com/jobsDao:query	Ljava/lang/String;
    //   73: invokeinterface 51 2 0
    //   78: putfield 22	com/jobsDao:ptmt	Ljava/sql/PreparedStatement;
    //   81: aload_0
    //   82: getfield 22	com/jobsDao:ptmt	Ljava/sql/PreparedStatement;
    //   85: iconst_1
    //   86: aload_1
    //   87: invokevirtual 197	com/jobsBean:getName	()Ljava/lang/String;
    //   90: invokeinterface 200 3 0
    //   95: aload_0
    //   96: getfield 22	com/jobsDao:ptmt	Ljava/sql/PreparedStatement;
    //   99: iconst_2
    //   100: aload_1
    //   101: invokevirtual 204	com/jobsBean:getNdate	()Ljava/lang/String;
    //   104: invokeinterface 200 3 0
    //   109: aload_0
    //   110: getfield 22	com/jobsDao:ptmt	Ljava/sql/PreparedStatement;
    //   113: iconst_3
    //   114: iload_2
    //   115: invokeinterface 160 3 0
    //   120: aload_0
    //   121: getfield 22	com/jobsDao:ptmt	Ljava/sql/PreparedStatement;
    //   124: iconst_4
    //   125: aload_1
    //   126: invokevirtual 207	com/jobsBean:getWhat	()Ljava/lang/String;
    //   129: invokeinterface 200 3 0
    //   134: aload_0
    //   135: getfield 22	com/jobsDao:ptmt	Ljava/sql/PreparedStatement;
    //   138: invokeinterface 210 1 0
    //   143: pop
    //   144: goto +86 -> 230
    //   147: astore_2
    //   148: aload_2
    //   149: invokevirtual 131	java/sql/SQLException:printStackTrace	()V
    //   152: aload_0
    //   153: getfield 22	com/jobsDao:ptmt	Ljava/sql/PreparedStatement;
    //   156: ifnull +110 -> 266
    //   159: aload_0
    //   160: getfield 22	com/jobsDao:ptmt	Ljava/sql/PreparedStatement;
    //   163: invokeinterface 174 1 0
    //   168: goto +98 -> 266
    //   171: astore 4
    //   173: aload 4
    //   175: invokevirtual 131	java/sql/SQLException:printStackTrace	()V
    //   178: goto +88 -> 266
    //   181: astore 4
    //   183: aload 4
    //   185: invokevirtual 175	java/lang/Exception:printStackTrace	()V
    //   188: goto +78 -> 266
    //   191: astore_3
    //   192: aload_0
    //   193: getfield 22	com/jobsDao:ptmt	Ljava/sql/PreparedStatement;
    //   196: ifnull +32 -> 228
    //   199: aload_0
    //   200: getfield 22	com/jobsDao:ptmt	Ljava/sql/PreparedStatement;
    //   203: invokeinterface 174 1 0
    //   208: goto +20 -> 228
    //   211: astore 4
    //   213: aload 4
    //   215: invokevirtual 131	java/sql/SQLException:printStackTrace	()V
    //   218: goto +10 -> 228
    //   221: astore 4
    //   223: aload 4
    //   225: invokevirtual 175	java/lang/Exception:printStackTrace	()V
    //   228: aload_3
    //   229: athrow
    //   230: aload_0
    //   231: getfield 22	com/jobsDao:ptmt	Ljava/sql/PreparedStatement;
    //   234: ifnull +32 -> 266
    //   237: aload_0
    //   238: getfield 22	com/jobsDao:ptmt	Ljava/sql/PreparedStatement;
    //   241: invokeinterface 174 1 0
    //   246: goto +20 -> 266
    //   249: astore 4
    //   251: aload 4
    //   253: invokevirtual 131	java/sql/SQLException:printStackTrace	()V
    //   256: goto +10 -> 266
    //   259: astore 4
    //   261: aload 4
    //   263: invokevirtual 175	java/lang/Exception:printStackTrace	()V
    //   266: return
    // Line number table:
    //   Java source line #103	-> byte code offset #0
    //   Java source line #105	-> byte code offset #6
    //   Java source line #106	-> byte code offset #13
    //   Java source line #107	-> byte code offset #18
    //   Java source line #108	-> byte code offset #30
    //   Java source line #109	-> byte code offset #38
    //   Java source line #110	-> byte code offset #53
    //   Java source line #113	-> byte code offset #64
    //   Java source line #114	-> byte code offset #81
    //   Java source line #115	-> byte code offset #95
    //   Java source line #116	-> byte code offset #109
    //   Java source line #117	-> byte code offset #120
    //   Java source line #119	-> byte code offset #134
    //   Java source line #120	-> byte code offset #144
    //   Java source line #121	-> byte code offset #148
    //   Java source line #124	-> byte code offset #152
    //   Java source line #125	-> byte code offset #159
    //   Java source line #126	-> byte code offset #168
    //   Java source line #127	-> byte code offset #173
    //   Java source line #128	-> byte code offset #181
    //   Java source line #129	-> byte code offset #183
    //   Java source line #122	-> byte code offset #191
    //   Java source line #124	-> byte code offset #192
    //   Java source line #125	-> byte code offset #199
    //   Java source line #126	-> byte code offset #208
    //   Java source line #127	-> byte code offset #213
    //   Java source line #128	-> byte code offset #221
    //   Java source line #129	-> byte code offset #223
    //   Java source line #132	-> byte code offset #228
    //   Java source line #124	-> byte code offset #230
    //   Java source line #125	-> byte code offset #237
    //   Java source line #126	-> byte code offset #246
    //   Java source line #127	-> byte code offset #251
    //   Java source line #128	-> byte code offset #259
    //   Java source line #129	-> byte code offset #261
    //   Java source line #134	-> byte code offset #266
    // Local variable table:
    //   start	length	slot	name	signature
    //   0	267	0	this	jobsDao
    //   0	267	1	job	jobsBean
    //   17	98	2	vinterval	int
    //   147	2	2	e	java.sql.SQLException
    //   191	38	3	localObject	Object
    //   171	3	4	e	java.sql.SQLException
    //   181	3	4	e	Exception
    //   211	3	4	e	java.sql.SQLException
    //   221	3	4	e	Exception
    //   249	3	4	e	java.sql.SQLException
    //   259	3	4	e	Exception
    // Exception table:
    //   from	to	target	type
    //   0	144	147	java/sql/SQLException
    //   152	168	171	java/sql/SQLException
    //   152	168	181	java/lang/Exception
    //   0	152	191	finally
    //   192	208	211	java/sql/SQLException
    //   192	208	221	java/lang/Exception
    //   230	246	249	java/sql/SQLException
    //   230	246	259	java/lang/Exception
  }
  
  /* Error */
  public void updateJob(jobsBean job)
  {
    // Byte code:
    //   0: aload_0
    //   1: ldc -40
    //   3: putfield 30	com/jobsDao:query	Ljava/lang/String;
    //   6: aload_0
    //   7: invokestatic 45	com/ConnectionProvider:getCon	()Ljava/sql/Connection;
    //   10: putfield 20	com/jobsDao:connection	Ljava/sql/Connection;
    //   13: aload_0
    //   14: aload_0
    //   15: getfield 20	com/jobsDao:connection	Ljava/sql/Connection;
    //   18: aload_0
    //   19: getfield 30	com/jobsDao:query	Ljava/lang/String;
    //   22: invokeinterface 51 2 0
    //   27: putfield 22	com/jobsDao:ptmt	Ljava/sql/PreparedStatement;
    //   30: aload_0
    //   31: getfield 22	com/jobsDao:ptmt	Ljava/sql/PreparedStatement;
    //   34: iconst_1
    //   35: aload_1
    //   36: invokevirtual 197	com/jobsBean:getName	()Ljava/lang/String;
    //   39: invokeinterface 200 3 0
    //   44: aload_0
    //   45: getfield 22	com/jobsDao:ptmt	Ljava/sql/PreparedStatement;
    //   48: iconst_2
    //   49: aload_1
    //   50: invokevirtual 204	com/jobsBean:getNdate	()Ljava/lang/String;
    //   53: invokeinterface 200 3 0
    //   58: aload_0
    //   59: getfield 22	com/jobsDao:ptmt	Ljava/sql/PreparedStatement;
    //   62: iconst_3
    //   63: aload_1
    //   64: invokevirtual 218	com/jobsBean:getBroken	()Ljava/lang/String;
    //   67: invokeinterface 200 3 0
    //   72: aload_0
    //   73: getfield 22	com/jobsDao:ptmt	Ljava/sql/PreparedStatement;
    //   76: iconst_4
    //   77: aload_1
    //   78: invokevirtual 182	com/jobsBean:getInterval	()I
    //   81: invokeinterface 160 3 0
    //   86: aload_0
    //   87: getfield 22	com/jobsDao:ptmt	Ljava/sql/PreparedStatement;
    //   90: iconst_5
    //   91: aload_1
    //   92: invokevirtual 207	com/jobsBean:getWhat	()Ljava/lang/String;
    //   95: invokeinterface 200 3 0
    //   100: aload_0
    //   101: getfield 22	com/jobsDao:ptmt	Ljava/sql/PreparedStatement;
    //   104: bipush 6
    //   106: aload_1
    //   107: invokevirtual 156	com/jobsBean:getJobid	()I
    //   110: invokeinterface 160 3 0
    //   115: aload_0
    //   116: getfield 22	com/jobsDao:ptmt	Ljava/sql/PreparedStatement;
    //   119: invokeinterface 210 1 0
    //   124: pop
    //   125: goto +86 -> 211
    //   128: astore_2
    //   129: aload_2
    //   130: invokevirtual 131	java/sql/SQLException:printStackTrace	()V
    //   133: aload_0
    //   134: getfield 22	com/jobsDao:ptmt	Ljava/sql/PreparedStatement;
    //   137: ifnull +110 -> 247
    //   140: aload_0
    //   141: getfield 22	com/jobsDao:ptmt	Ljava/sql/PreparedStatement;
    //   144: invokeinterface 174 1 0
    //   149: goto +98 -> 247
    //   152: astore 4
    //   154: aload 4
    //   156: invokevirtual 131	java/sql/SQLException:printStackTrace	()V
    //   159: goto +88 -> 247
    //   162: astore 4
    //   164: aload 4
    //   166: invokevirtual 175	java/lang/Exception:printStackTrace	()V
    //   169: goto +78 -> 247
    //   172: astore_3
    //   173: aload_0
    //   174: getfield 22	com/jobsDao:ptmt	Ljava/sql/PreparedStatement;
    //   177: ifnull +32 -> 209
    //   180: aload_0
    //   181: getfield 22	com/jobsDao:ptmt	Ljava/sql/PreparedStatement;
    //   184: invokeinterface 174 1 0
    //   189: goto +20 -> 209
    //   192: astore 4
    //   194: aload 4
    //   196: invokevirtual 131	java/sql/SQLException:printStackTrace	()V
    //   199: goto +10 -> 209
    //   202: astore 4
    //   204: aload 4
    //   206: invokevirtual 175	java/lang/Exception:printStackTrace	()V
    //   209: aload_3
    //   210: athrow
    //   211: aload_0
    //   212: getfield 22	com/jobsDao:ptmt	Ljava/sql/PreparedStatement;
    //   215: ifnull +32 -> 247
    //   218: aload_0
    //   219: getfield 22	com/jobsDao:ptmt	Ljava/sql/PreparedStatement;
    //   222: invokeinterface 174 1 0
    //   227: goto +20 -> 247
    //   230: astore 4
    //   232: aload 4
    //   234: invokevirtual 131	java/sql/SQLException:printStackTrace	()V
    //   237: goto +10 -> 247
    //   240: astore 4
    //   242: aload 4
    //   244: invokevirtual 175	java/lang/Exception:printStackTrace	()V
    //   247: return
    // Line number table:
    //   Java source line #139	-> byte code offset #0
    //   Java source line #140	-> byte code offset #6
    //   Java source line #141	-> byte code offset #13
    //   Java source line #142	-> byte code offset #30
    //   Java source line #143	-> byte code offset #44
    //   Java source line #144	-> byte code offset #58
    //   Java source line #145	-> byte code offset #72
    //   Java source line #146	-> byte code offset #86
    //   Java source line #147	-> byte code offset #100
    //   Java source line #149	-> byte code offset #115
    //   Java source line #150	-> byte code offset #125
    //   Java source line #151	-> byte code offset #129
    //   Java source line #154	-> byte code offset #133
    //   Java source line #155	-> byte code offset #140
    //   Java source line #156	-> byte code offset #149
    //   Java source line #157	-> byte code offset #154
    //   Java source line #158	-> byte code offset #162
    //   Java source line #159	-> byte code offset #164
    //   Java source line #152	-> byte code offset #172
    //   Java source line #154	-> byte code offset #173
    //   Java source line #155	-> byte code offset #180
    //   Java source line #156	-> byte code offset #189
    //   Java source line #157	-> byte code offset #194
    //   Java source line #158	-> byte code offset #202
    //   Java source line #159	-> byte code offset #204
    //   Java source line #162	-> byte code offset #209
    //   Java source line #154	-> byte code offset #211
    //   Java source line #155	-> byte code offset #218
    //   Java source line #156	-> byte code offset #227
    //   Java source line #157	-> byte code offset #232
    //   Java source line #158	-> byte code offset #240
    //   Java source line #159	-> byte code offset #242
    //   Java source line #164	-> byte code offset #247
    // Local variable table:
    //   start	length	slot	name	signature
    //   0	248	0	this	jobsDao
    //   0	248	1	job	jobsBean
    //   128	2	2	e	java.sql.SQLException
    //   172	38	3	localObject	Object
    //   152	3	4	e	java.sql.SQLException
    //   162	3	4	e	Exception
    //   192	3	4	e	java.sql.SQLException
    //   202	3	4	e	Exception
    //   230	3	4	e	java.sql.SQLException
    //   240	3	4	e	Exception
    // Exception table:
    //   from	to	target	type
    //   0	125	128	java/sql/SQLException
    //   133	149	152	java/sql/SQLException
    //   133	149	162	java/lang/Exception
    //   0	133	172	finally
    //   173	189	192	java/sql/SQLException
    //   173	189	202	java/lang/Exception
    //   211	227	230	java/sql/SQLException
    //   211	227	240	java/lang/Exception
  }
  
  /* Error */
  public void delete(int jobid)
  {
    // Byte code:
    //   0: aload_0
    //   1: invokestatic 45	com/ConnectionProvider:getCon	()Ljava/sql/Connection;
    //   4: putfield 20	com/jobsDao:connection	Ljava/sql/Connection;
    //   7: aload_0
    //   8: ldc -34
    //   10: putfield 30	com/jobsDao:query	Ljava/lang/String;
    //   13: aload_0
    //   14: aload_0
    //   15: getfield 20	com/jobsDao:connection	Ljava/sql/Connection;
    //   18: aload_0
    //   19: getfield 30	com/jobsDao:query	Ljava/lang/String;
    //   22: invokeinterface 51 2 0
    //   27: putfield 22	com/jobsDao:ptmt	Ljava/sql/PreparedStatement;
    //   30: aload_0
    //   31: getfield 22	com/jobsDao:ptmt	Ljava/sql/PreparedStatement;
    //   34: iconst_1
    //   35: iload_1
    //   36: invokeinterface 160 3 0
    //   41: aload_0
    //   42: getfield 22	com/jobsDao:ptmt	Ljava/sql/PreparedStatement;
    //   45: invokeinterface 210 1 0
    //   50: pop
    //   51: goto +86 -> 137
    //   54: astore_2
    //   55: aload_2
    //   56: invokevirtual 131	java/sql/SQLException:printStackTrace	()V
    //   59: aload_0
    //   60: getfield 22	com/jobsDao:ptmt	Ljava/sql/PreparedStatement;
    //   63: ifnull +110 -> 173
    //   66: aload_0
    //   67: getfield 22	com/jobsDao:ptmt	Ljava/sql/PreparedStatement;
    //   70: invokeinterface 174 1 0
    //   75: goto +98 -> 173
    //   78: astore 4
    //   80: aload 4
    //   82: invokevirtual 131	java/sql/SQLException:printStackTrace	()V
    //   85: goto +88 -> 173
    //   88: astore 4
    //   90: aload 4
    //   92: invokevirtual 175	java/lang/Exception:printStackTrace	()V
    //   95: goto +78 -> 173
    //   98: astore_3
    //   99: aload_0
    //   100: getfield 22	com/jobsDao:ptmt	Ljava/sql/PreparedStatement;
    //   103: ifnull +32 -> 135
    //   106: aload_0
    //   107: getfield 22	com/jobsDao:ptmt	Ljava/sql/PreparedStatement;
    //   110: invokeinterface 174 1 0
    //   115: goto +20 -> 135
    //   118: astore 4
    //   120: aload 4
    //   122: invokevirtual 131	java/sql/SQLException:printStackTrace	()V
    //   125: goto +10 -> 135
    //   128: astore 4
    //   130: aload 4
    //   132: invokevirtual 175	java/lang/Exception:printStackTrace	()V
    //   135: aload_3
    //   136: athrow
    //   137: aload_0
    //   138: getfield 22	com/jobsDao:ptmt	Ljava/sql/PreparedStatement;
    //   141: ifnull +32 -> 173
    //   144: aload_0
    //   145: getfield 22	com/jobsDao:ptmt	Ljava/sql/PreparedStatement;
    //   148: invokeinterface 174 1 0
    //   153: goto +20 -> 173
    //   156: astore 4
    //   158: aload 4
    //   160: invokevirtual 131	java/sql/SQLException:printStackTrace	()V
    //   163: goto +10 -> 173
    //   166: astore 4
    //   168: aload 4
    //   170: invokevirtual 175	java/lang/Exception:printStackTrace	()V
    //   173: return
    // Line number table:
    //   Java source line #169	-> byte code offset #0
    //   Java source line #170	-> byte code offset #7
    //   Java source line #171	-> byte code offset #13
    //   Java source line #172	-> byte code offset #30
    //   Java source line #173	-> byte code offset #41
    //   Java source line #174	-> byte code offset #51
    //   Java source line #175	-> byte code offset #55
    //   Java source line #178	-> byte code offset #59
    //   Java source line #179	-> byte code offset #66
    //   Java source line #180	-> byte code offset #75
    //   Java source line #181	-> byte code offset #88
    //   Java source line #176	-> byte code offset #98
    //   Java source line #178	-> byte code offset #99
    //   Java source line #179	-> byte code offset #106
    //   Java source line #180	-> byte code offset #115
    //   Java source line #181	-> byte code offset #128
    //   Java source line #183	-> byte code offset #135
    //   Java source line #178	-> byte code offset #137
    //   Java source line #179	-> byte code offset #144
    //   Java source line #180	-> byte code offset #153
    //   Java source line #181	-> byte code offset #166
    //   Java source line #184	-> byte code offset #173
    // Local variable table:
    //   start	length	slot	name	signature
    //   0	174	0	this	jobsDao
    //   0	174	1	jobid	int
    //   54	2	2	e	java.sql.SQLException
    //   98	38	3	localObject	Object
    //   78	3	4	e	java.sql.SQLException
    //   88	3	4	e	Exception
    //   118	3	4	e	java.sql.SQLException
    //   128	3	4	e	Exception
    //   156	3	4	e	java.sql.SQLException
    //   166	3	4	e	Exception
    // Exception table:
    //   from	to	target	type
    //   0	51	54	java/sql/SQLException
    //   59	75	78	java/sql/SQLException
    //   59	75	88	java/lang/Exception
    //   0	59	98	finally
    //   99	115	118	java/sql/SQLException
    //   99	115	128	java/lang/Exception
    //   137	153	156	java/sql/SQLException
    //   137	153	166	java/lang/Exception
  }
}
