package com;

import java.io.PrintStream;
import java.sql.Connection;
import java.sql.PreparedStatement;
import java.sql.ResultSet;
import java.sql.Statement;

public class orgDao
{
  Connection connection = null;
  PreparedStatement ptmt = null;
  ResultSet rs = null;
  boolean status = false;
  Statement stmt = null;
  String query = "";
  
  public void findOrg(orgBean oBean)
  {
    try
    {
      this.query = "select * from  organization where id=? ";
      this.connection = ConnectionProvider.getCon();
      this.ptmt = this.connection.prepareStatement(this.query);
      this.ptmt.setInt(1, oBean.getOid());
      this.rs = this.ptmt.executeQuery();
      this.status = this.rs.next();
      if (!this.status)
      {
        System.out.println("No organization found");
      }
      else if (this.status)
      {
        oBean.setName(this.rs.getString("name"));
        oBean.setAddress1(this.rs.getString("address1"));
        oBean.setAddress2(this.rs.getString("address2"));
        oBean.setCity(this.rs.getString("city"));
        oBean.setEmail(this.rs.getString("email_id"));
        oBean.setDstateid(this.rs.getInt("default_state_id"));
        oBean.setTmin(this.rs.getDouble("temp_min"));
        oBean.setTmax(this.rs.getDouble("temp_max"));
        oBean.setWmax(this.rs.getDouble("wind_max"));
        oBean.setHrain(this.rs.getDouble("hrain_max"));
      }
    }
    catch (Exception e)
    {
      System.out.println("Org Details not found: An Exception has occurred! " + e);
    }
  }
  
  /* Error */
  public void add(orgBean oBean)
  {
    // Byte code:
    //   0: aload_0
    //   1: ldc -78
    //   3: putfield 34	com/orgDao:query	Ljava/lang/String;
    //   6: aload_0
    //   7: invokestatic 44	com/ConnectionProvider:getCon	()Ljava/sql/Connection;
    //   10: putfield 22	com/orgDao:connection	Ljava/sql/Connection;
    //   13: aload_0
    //   14: aload_0
    //   15: getfield 22	com/orgDao:connection	Ljava/sql/Connection;
    //   18: aload_0
    //   19: getfield 34	com/orgDao:query	Ljava/lang/String;
    //   22: invokeinterface 50 2 0
    //   27: putfield 24	com/orgDao:ptmt	Ljava/sql/PreparedStatement;
    //   30: aload_0
    //   31: getfield 24	com/orgDao:ptmt	Ljava/sql/PreparedStatement;
    //   34: iconst_1
    //   35: aload_1
    //   36: invokevirtual 180	com/orgBean:getName	()Ljava/lang/String;
    //   39: invokeinterface 183 3 0
    //   44: aload_0
    //   45: getfield 24	com/orgDao:ptmt	Ljava/sql/PreparedStatement;
    //   48: iconst_2
    //   49: aload_1
    //   50: invokevirtual 187	com/orgBean:getAddress1	()Ljava/lang/String;
    //   53: invokeinterface 183 3 0
    //   58: aload_0
    //   59: getfield 24	com/orgDao:ptmt	Ljava/sql/PreparedStatement;
    //   62: iconst_3
    //   63: aload_1
    //   64: invokevirtual 190	com/orgBean:getAddress2	()Ljava/lang/String;
    //   67: invokeinterface 183 3 0
    //   72: aload_0
    //   73: getfield 24	com/orgDao:ptmt	Ljava/sql/PreparedStatement;
    //   76: iconst_4
    //   77: aload_1
    //   78: invokevirtual 193	com/orgBean:getCity	()Ljava/lang/String;
    //   81: invokeinterface 183 3 0
    //   86: aload_0
    //   87: getfield 24	com/orgDao:ptmt	Ljava/sql/PreparedStatement;
    //   90: iconst_5
    //   91: aload_1
    //   92: invokevirtual 196	com/orgBean:getEmail	()Ljava/lang/String;
    //   95: invokeinterface 183 3 0
    //   100: aload_0
    //   101: getfield 24	com/orgDao:ptmt	Ljava/sql/PreparedStatement;
    //   104: bipush 6
    //   106: aload_1
    //   107: invokevirtual 199	com/orgBean:getDstateid	()I
    //   110: invokeinterface 62 3 0
    //   115: aload_0
    //   116: getfield 24	com/orgDao:ptmt	Ljava/sql/PreparedStatement;
    //   119: invokeinterface 202 1 0
    //   124: pop
    //   125: goto +86 -> 211
    //   128: astore_2
    //   129: aload_2
    //   130: invokevirtual 205	java/sql/SQLException:printStackTrace	()V
    //   133: aload_0
    //   134: getfield 24	com/orgDao:ptmt	Ljava/sql/PreparedStatement;
    //   137: ifnull +110 -> 247
    //   140: aload_0
    //   141: getfield 24	com/orgDao:ptmt	Ljava/sql/PreparedStatement;
    //   144: invokeinterface 210 1 0
    //   149: goto +98 -> 247
    //   152: astore 4
    //   154: aload 4
    //   156: invokevirtual 205	java/sql/SQLException:printStackTrace	()V
    //   159: goto +88 -> 247
    //   162: astore 4
    //   164: aload 4
    //   166: invokevirtual 213	java/lang/Exception:printStackTrace	()V
    //   169: goto +78 -> 247
    //   172: astore_3
    //   173: aload_0
    //   174: getfield 24	com/orgDao:ptmt	Ljava/sql/PreparedStatement;
    //   177: ifnull +32 -> 209
    //   180: aload_0
    //   181: getfield 24	com/orgDao:ptmt	Ljava/sql/PreparedStatement;
    //   184: invokeinterface 210 1 0
    //   189: goto +20 -> 209
    //   192: astore 4
    //   194: aload 4
    //   196: invokevirtual 205	java/sql/SQLException:printStackTrace	()V
    //   199: goto +10 -> 209
    //   202: astore 4
    //   204: aload 4
    //   206: invokevirtual 213	java/lang/Exception:printStackTrace	()V
    //   209: aload_3
    //   210: athrow
    //   211: aload_0
    //   212: getfield 24	com/orgDao:ptmt	Ljava/sql/PreparedStatement;
    //   215: ifnull +32 -> 247
    //   218: aload_0
    //   219: getfield 24	com/orgDao:ptmt	Ljava/sql/PreparedStatement;
    //   222: invokeinterface 210 1 0
    //   227: goto +20 -> 247
    //   230: astore 4
    //   232: aload 4
    //   234: invokevirtual 205	java/sql/SQLException:printStackTrace	()V
    //   237: goto +10 -> 247
    //   240: astore 4
    //   242: aload 4
    //   244: invokevirtual 213	java/lang/Exception:printStackTrace	()V
    //   247: return
    // Line number table:
    //   Java source line #54	-> byte code offset #0
    //   Java source line #56	-> byte code offset #6
    //   Java source line #57	-> byte code offset #13
    //   Java source line #58	-> byte code offset #30
    //   Java source line #59	-> byte code offset #44
    //   Java source line #60	-> byte code offset #58
    //   Java source line #61	-> byte code offset #72
    //   Java source line #62	-> byte code offset #86
    //   Java source line #63	-> byte code offset #100
    //   Java source line #64	-> byte code offset #115
    //   Java source line #65	-> byte code offset #125
    //   Java source line #66	-> byte code offset #129
    //   Java source line #69	-> byte code offset #133
    //   Java source line #70	-> byte code offset #140
    //   Java source line #71	-> byte code offset #149
    //   Java source line #72	-> byte code offset #154
    //   Java source line #73	-> byte code offset #162
    //   Java source line #74	-> byte code offset #164
    //   Java source line #67	-> byte code offset #172
    //   Java source line #69	-> byte code offset #173
    //   Java source line #70	-> byte code offset #180
    //   Java source line #71	-> byte code offset #189
    //   Java source line #72	-> byte code offset #194
    //   Java source line #73	-> byte code offset #202
    //   Java source line #74	-> byte code offset #204
    //   Java source line #77	-> byte code offset #209
    //   Java source line #69	-> byte code offset #211
    //   Java source line #70	-> byte code offset #218
    //   Java source line #71	-> byte code offset #227
    //   Java source line #72	-> byte code offset #232
    //   Java source line #73	-> byte code offset #240
    //   Java source line #74	-> byte code offset #242
    //   Java source line #79	-> byte code offset #247
    // Local variable table:
    //   start	length	slot	name	signature
    //   0	248	0	this	orgDao
    //   0	248	1	oBean	orgBean
    //   128	2	2	e	java.sql.SQLException
    //   172	38	3	localObject	Object
    //   152	3	4	e	java.sql.SQLException
    //   162	3	4	e	Exception
    //   192	3	4	e	java.sql.SQLException
    //   202	3	4	e	Exception
    //   230	3	4	e	java.sql.SQLException
    //   240	3	4	e	Exception
    // Exception table:
    //   from	to	target	type
    //   0	125	128	java/sql/SQLException
    //   133	149	152	java/sql/SQLException
    //   133	149	162	java/lang/Exception
    //   0	133	172	finally
    //   173	189	192	java/sql/SQLException
    //   173	189	202	java/lang/Exception
    //   211	227	230	java/sql/SQLException
    //   211	227	240	java/lang/Exception
  }
  
  /* Error */
  public void update(orgBean oBean)
  {
    // Byte code:
    //   0: aload_0
    //   1: ldc -38
    //   3: putfield 34	com/orgDao:query	Ljava/lang/String;
    //   6: aload_0
    //   7: invokestatic 44	com/ConnectionProvider:getCon	()Ljava/sql/Connection;
    //   10: putfield 22	com/orgDao:connection	Ljava/sql/Connection;
    //   13: aload_0
    //   14: aload_0
    //   15: getfield 22	com/orgDao:connection	Ljava/sql/Connection;
    //   18: aload_0
    //   19: getfield 34	com/orgDao:query	Ljava/lang/String;
    //   22: invokeinterface 50 2 0
    //   27: putfield 24	com/orgDao:ptmt	Ljava/sql/PreparedStatement;
    //   30: aload_0
    //   31: getfield 24	com/orgDao:ptmt	Ljava/sql/PreparedStatement;
    //   34: iconst_1
    //   35: aload_1
    //   36: invokevirtual 180	com/orgBean:getName	()Ljava/lang/String;
    //   39: invokeinterface 183 3 0
    //   44: aload_0
    //   45: getfield 24	com/orgDao:ptmt	Ljava/sql/PreparedStatement;
    //   48: iconst_2
    //   49: aload_1
    //   50: invokevirtual 187	com/orgBean:getAddress1	()Ljava/lang/String;
    //   53: invokeinterface 183 3 0
    //   58: aload_0
    //   59: getfield 24	com/orgDao:ptmt	Ljava/sql/PreparedStatement;
    //   62: iconst_3
    //   63: aload_1
    //   64: invokevirtual 190	com/orgBean:getAddress2	()Ljava/lang/String;
    //   67: invokeinterface 183 3 0
    //   72: aload_0
    //   73: getfield 24	com/orgDao:ptmt	Ljava/sql/PreparedStatement;
    //   76: iconst_4
    //   77: aload_1
    //   78: invokevirtual 193	com/orgBean:getCity	()Ljava/lang/String;
    //   81: invokeinterface 183 3 0
    //   86: aload_0
    //   87: getfield 24	com/orgDao:ptmt	Ljava/sql/PreparedStatement;
    //   90: iconst_5
    //   91: aload_1
    //   92: invokevirtual 196	com/orgBean:getEmail	()Ljava/lang/String;
    //   95: invokeinterface 183 3 0
    //   100: aload_0
    //   101: getfield 24	com/orgDao:ptmt	Ljava/sql/PreparedStatement;
    //   104: bipush 6
    //   106: aload_1
    //   107: invokevirtual 199	com/orgBean:getDstateid	()I
    //   110: invokeinterface 62 3 0
    //   115: aload_0
    //   116: getfield 24	com/orgDao:ptmt	Ljava/sql/PreparedStatement;
    //   119: bipush 7
    //   121: aload_1
    //   122: invokevirtual 56	com/orgBean:getOid	()I
    //   125: invokeinterface 62 3 0
    //   130: aload_0
    //   131: getfield 24	com/orgDao:ptmt	Ljava/sql/PreparedStatement;
    //   134: invokeinterface 202 1 0
    //   139: pop
    //   140: goto +86 -> 226
    //   143: astore_2
    //   144: aload_2
    //   145: invokevirtual 205	java/sql/SQLException:printStackTrace	()V
    //   148: aload_0
    //   149: getfield 24	com/orgDao:ptmt	Ljava/sql/PreparedStatement;
    //   152: ifnull +110 -> 262
    //   155: aload_0
    //   156: getfield 24	com/orgDao:ptmt	Ljava/sql/PreparedStatement;
    //   159: invokeinterface 210 1 0
    //   164: goto +98 -> 262
    //   167: astore 4
    //   169: aload 4
    //   171: invokevirtual 205	java/sql/SQLException:printStackTrace	()V
    //   174: goto +88 -> 262
    //   177: astore 4
    //   179: aload 4
    //   181: invokevirtual 213	java/lang/Exception:printStackTrace	()V
    //   184: goto +78 -> 262
    //   187: astore_3
    //   188: aload_0
    //   189: getfield 24	com/orgDao:ptmt	Ljava/sql/PreparedStatement;
    //   192: ifnull +32 -> 224
    //   195: aload_0
    //   196: getfield 24	com/orgDao:ptmt	Ljava/sql/PreparedStatement;
    //   199: invokeinterface 210 1 0
    //   204: goto +20 -> 224
    //   207: astore 4
    //   209: aload 4
    //   211: invokevirtual 205	java/sql/SQLException:printStackTrace	()V
    //   214: goto +10 -> 224
    //   217: astore 4
    //   219: aload 4
    //   221: invokevirtual 213	java/lang/Exception:printStackTrace	()V
    //   224: aload_3
    //   225: athrow
    //   226: aload_0
    //   227: getfield 24	com/orgDao:ptmt	Ljava/sql/PreparedStatement;
    //   230: ifnull +32 -> 262
    //   233: aload_0
    //   234: getfield 24	com/orgDao:ptmt	Ljava/sql/PreparedStatement;
    //   237: invokeinterface 210 1 0
    //   242: goto +20 -> 262
    //   245: astore 4
    //   247: aload 4
    //   249: invokevirtual 205	java/sql/SQLException:printStackTrace	()V
    //   252: goto +10 -> 262
    //   255: astore 4
    //   257: aload 4
    //   259: invokevirtual 213	java/lang/Exception:printStackTrace	()V
    //   262: return
    // Line number table:
    //   Java source line #83	-> byte code offset #0
    //   Java source line #85	-> byte code offset #6
    //   Java source line #86	-> byte code offset #13
    //   Java source line #87	-> byte code offset #30
    //   Java source line #88	-> byte code offset #44
    //   Java source line #89	-> byte code offset #58
    //   Java source line #90	-> byte code offset #72
    //   Java source line #91	-> byte code offset #86
    //   Java source line #92	-> byte code offset #100
    //   Java source line #93	-> byte code offset #115
    //   Java source line #95	-> byte code offset #130
    //   Java source line #96	-> byte code offset #140
    //   Java source line #97	-> byte code offset #144
    //   Java source line #100	-> byte code offset #148
    //   Java source line #101	-> byte code offset #155
    //   Java source line #102	-> byte code offset #164
    //   Java source line #103	-> byte code offset #169
    //   Java source line #104	-> byte code offset #177
    //   Java source line #105	-> byte code offset #179
    //   Java source line #98	-> byte code offset #187
    //   Java source line #100	-> byte code offset #188
    //   Java source line #101	-> byte code offset #195
    //   Java source line #102	-> byte code offset #204
    //   Java source line #103	-> byte code offset #209
    //   Java source line #104	-> byte code offset #217
    //   Java source line #105	-> byte code offset #219
    //   Java source line #108	-> byte code offset #224
    //   Java source line #100	-> byte code offset #226
    //   Java source line #101	-> byte code offset #233
    //   Java source line #102	-> byte code offset #242
    //   Java source line #103	-> byte code offset #247
    //   Java source line #104	-> byte code offset #255
    //   Java source line #105	-> byte code offset #257
    //   Java source line #110	-> byte code offset #262
    // Local variable table:
    //   start	length	slot	name	signature
    //   0	263	0	this	orgDao
    //   0	263	1	oBean	orgBean
    //   143	2	2	e	java.sql.SQLException
    //   187	38	3	localObject	Object
    //   167	3	4	e	java.sql.SQLException
    //   177	3	4	e	Exception
    //   207	3	4	e	java.sql.SQLException
    //   217	3	4	e	Exception
    //   245	3	4	e	java.sql.SQLException
    //   255	3	4	e	Exception
    // Exception table:
    //   from	to	target	type
    //   0	140	143	java/sql/SQLException
    //   148	164	167	java/sql/SQLException
    //   148	164	177	java/lang/Exception
    //   0	148	187	finally
    //   188	204	207	java/sql/SQLException
    //   188	204	217	java/lang/Exception
    //   226	242	245	java/sql/SQLException
    //   226	242	255	java/lang/Exception
  }
  
  /* Error */
  public void updateParams(orgBean oBean)
  {
    // Byte code:
    //   0: aload_0
    //   1: ldc -35
    //   3: putfield 34	com/orgDao:query	Ljava/lang/String;
    //   6: aload_0
    //   7: invokestatic 44	com/ConnectionProvider:getCon	()Ljava/sql/Connection;
    //   10: putfield 22	com/orgDao:connection	Ljava/sql/Connection;
    //   13: aload_0
    //   14: aload_0
    //   15: getfield 22	com/orgDao:connection	Ljava/sql/Connection;
    //   18: aload_0
    //   19: getfield 34	com/orgDao:query	Ljava/lang/String;
    //   22: invokeinterface 50 2 0
    //   27: putfield 24	com/orgDao:ptmt	Ljava/sql/PreparedStatement;
    //   30: aload_0
    //   31: getfield 24	com/orgDao:ptmt	Ljava/sql/PreparedStatement;
    //   34: iconst_1
    //   35: aload_1
    //   36: invokevirtual 223	com/orgBean:getTmin	()D
    //   39: invokeinterface 227 4 0
    //   44: aload_0
    //   45: getfield 24	com/orgDao:ptmt	Ljava/sql/PreparedStatement;
    //   48: iconst_2
    //   49: aload_1
    //   50: invokevirtual 231	com/orgBean:getTmax	()D
    //   53: invokeinterface 227 4 0
    //   58: aload_0
    //   59: getfield 24	com/orgDao:ptmt	Ljava/sql/PreparedStatement;
    //   62: iconst_3
    //   63: aload_1
    //   64: invokevirtual 234	com/orgBean:getWmax	()D
    //   67: invokeinterface 227 4 0
    //   72: aload_0
    //   73: getfield 24	com/orgDao:ptmt	Ljava/sql/PreparedStatement;
    //   76: iconst_4
    //   77: aload_1
    //   78: invokevirtual 237	com/orgBean:getHrain	()D
    //   81: invokeinterface 227 4 0
    //   86: aload_0
    //   87: getfield 24	com/orgDao:ptmt	Ljava/sql/PreparedStatement;
    //   90: iconst_5
    //   91: aload_1
    //   92: invokevirtual 240	com/orgBean:getPmin	()D
    //   95: invokeinterface 227 4 0
    //   100: aload_0
    //   101: getfield 24	com/orgDao:ptmt	Ljava/sql/PreparedStatement;
    //   104: bipush 6
    //   106: aload_1
    //   107: invokevirtual 243	com/orgBean:getPmax	()D
    //   110: invokeinterface 227 4 0
    //   115: aload_0
    //   116: getfield 24	com/orgDao:ptmt	Ljava/sql/PreparedStatement;
    //   119: invokeinterface 202 1 0
    //   124: pop
    //   125: goto +86 -> 211
    //   128: astore_2
    //   129: aload_2
    //   130: invokevirtual 205	java/sql/SQLException:printStackTrace	()V
    //   133: aload_0
    //   134: getfield 24	com/orgDao:ptmt	Ljava/sql/PreparedStatement;
    //   137: ifnull +110 -> 247
    //   140: aload_0
    //   141: getfield 24	com/orgDao:ptmt	Ljava/sql/PreparedStatement;
    //   144: invokeinterface 210 1 0
    //   149: goto +98 -> 247
    //   152: astore 4
    //   154: aload 4
    //   156: invokevirtual 205	java/sql/SQLException:printStackTrace	()V
    //   159: goto +88 -> 247
    //   162: astore 4
    //   164: aload 4
    //   166: invokevirtual 213	java/lang/Exception:printStackTrace	()V
    //   169: goto +78 -> 247
    //   172: astore_3
    //   173: aload_0
    //   174: getfield 24	com/orgDao:ptmt	Ljava/sql/PreparedStatement;
    //   177: ifnull +32 -> 209
    //   180: aload_0
    //   181: getfield 24	com/orgDao:ptmt	Ljava/sql/PreparedStatement;
    //   184: invokeinterface 210 1 0
    //   189: goto +20 -> 209
    //   192: astore 4
    //   194: aload 4
    //   196: invokevirtual 205	java/sql/SQLException:printStackTrace	()V
    //   199: goto +10 -> 209
    //   202: astore 4
    //   204: aload 4
    //   206: invokevirtual 213	java/lang/Exception:printStackTrace	()V
    //   209: aload_3
    //   210: athrow
    //   211: aload_0
    //   212: getfield 24	com/orgDao:ptmt	Ljava/sql/PreparedStatement;
    //   215: ifnull +32 -> 247
    //   218: aload_0
    //   219: getfield 24	com/orgDao:ptmt	Ljava/sql/PreparedStatement;
    //   222: invokeinterface 210 1 0
    //   227: goto +20 -> 247
    //   230: astore 4
    //   232: aload 4
    //   234: invokevirtual 205	java/sql/SQLException:printStackTrace	()V
    //   237: goto +10 -> 247
    //   240: astore 4
    //   242: aload 4
    //   244: invokevirtual 213	java/lang/Exception:printStackTrace	()V
    //   247: return
    // Line number table:
    //   Java source line #114	-> byte code offset #0
    //   Java source line #116	-> byte code offset #6
    //   Java source line #117	-> byte code offset #13
    //   Java source line #118	-> byte code offset #30
    //   Java source line #119	-> byte code offset #44
    //   Java source line #120	-> byte code offset #58
    //   Java source line #121	-> byte code offset #72
    //   Java source line #122	-> byte code offset #86
    //   Java source line #123	-> byte code offset #100
    //   Java source line #125	-> byte code offset #115
    //   Java source line #126	-> byte code offset #125
    //   Java source line #127	-> byte code offset #129
    //   Java source line #130	-> byte code offset #133
    //   Java source line #131	-> byte code offset #140
    //   Java source line #132	-> byte code offset #149
    //   Java source line #133	-> byte code offset #154
    //   Java source line #134	-> byte code offset #162
    //   Java source line #135	-> byte code offset #164
    //   Java source line #128	-> byte code offset #172
    //   Java source line #130	-> byte code offset #173
    //   Java source line #131	-> byte code offset #180
    //   Java source line #132	-> byte code offset #189
    //   Java source line #133	-> byte code offset #194
    //   Java source line #134	-> byte code offset #202
    //   Java source line #135	-> byte code offset #204
    //   Java source line #138	-> byte code offset #209
    //   Java source line #130	-> byte code offset #211
    //   Java source line #131	-> byte code offset #218
    //   Java source line #132	-> byte code offset #227
    //   Java source line #133	-> byte code offset #232
    //   Java source line #134	-> byte code offset #240
    //   Java source line #135	-> byte code offset #242
    //   Java source line #140	-> byte code offset #247
    // Local variable table:
    //   start	length	slot	name	signature
    //   0	248	0	this	orgDao
    //   0	248	1	oBean	orgBean
    //   128	2	2	e	java.sql.SQLException
    //   172	38	3	localObject	Object
    //   152	3	4	e	java.sql.SQLException
    //   162	3	4	e	Exception
    //   192	3	4	e	java.sql.SQLException
    //   202	3	4	e	Exception
    //   230	3	4	e	java.sql.SQLException
    //   240	3	4	e	Exception
    // Exception table:
    //   from	to	target	type
    //   0	125	128	java/sql/SQLException
    //   133	149	152	java/sql/SQLException
    //   133	149	162	java/lang/Exception
    //   0	133	172	finally
    //   173	189	192	java/sql/SQLException
    //   173	189	202	java/lang/Exception
    //   211	227	230	java/sql/SQLException
    //   211	227	240	java/lang/Exception
  }
}
