package com;

import java.sql.Connection;
import java.sql.PreparedStatement;
import java.sql.ResultSet;
import java.sql.Statement;

public class datapacketsDao
{
  Connection connection = null;
  PreparedStatement ptmt = null;
  ResultSet rs = null;
  boolean status = false;
  Statement stmt = null;
  String query = "";
  
  /* Error */
  public java.util.List<datapacketsBean> viewPackets(int stationid, String fdate, String tdate)
  {
    // Byte code:
    //   0: new 44	java/util/ArrayList
    //   3: dup
    //   4: invokespecial 46	java/util/ArrayList:<init>	()V
    //   7: astore 4
    //   9: aconst_null
    //   10: astore 5
    //   12: aload_0
    //   13: ldc 47
    //   15: putfield 34	com/datapacketsDao:query	Ljava/lang/String;
    //   18: aload_0
    //   19: invokestatic 49	com/ConnectionProvider:getCon	()Ljava/sql/Connection;
    //   22: putfield 22	com/datapacketsDao:connection	Ljava/sql/Connection;
    //   25: aload_0
    //   26: aload_0
    //   27: getfield 22	com/datapacketsDao:connection	Ljava/sql/Connection;
    //   30: aload_0
    //   31: getfield 34	com/datapacketsDao:query	Ljava/lang/String;
    //   34: invokeinterface 55 2 0
    //   39: putfield 24	com/datapacketsDao:ptmt	Ljava/sql/PreparedStatement;
    //   42: aload_0
    //   43: getfield 24	com/datapacketsDao:ptmt	Ljava/sql/PreparedStatement;
    //   46: iconst_1
    //   47: iload_1
    //   48: invokeinterface 61 3 0
    //   53: aload_0
    //   54: getfield 24	com/datapacketsDao:ptmt	Ljava/sql/PreparedStatement;
    //   57: iconst_2
    //   58: aload_2
    //   59: invokeinterface 67 3 0
    //   64: aload_0
    //   65: getfield 24	com/datapacketsDao:ptmt	Ljava/sql/PreparedStatement;
    //   68: iconst_3
    //   69: aload_3
    //   70: invokeinterface 67 3 0
    //   75: aload_0
    //   76: aload_0
    //   77: getfield 24	com/datapacketsDao:ptmt	Ljava/sql/PreparedStatement;
    //   80: invokeinterface 71 1 0
    //   85: putfield 26	com/datapacketsDao:rs	Ljava/sql/ResultSet;
    //   88: goto +182 -> 270
    //   91: new 75	com/datapacketsBean
    //   94: dup
    //   95: invokespecial 77	com/datapacketsBean:<init>	()V
    //   98: astore 5
    //   100: aload 5
    //   102: aload_0
    //   103: getfield 26	com/datapacketsDao:rs	Ljava/sql/ResultSet;
    //   106: ldc 78
    //   108: invokeinterface 80 2 0
    //   113: invokevirtual 86	com/datapacketsBean:setDtime	(Ljava/lang/String;)V
    //   116: aload 5
    //   118: aload_0
    //   119: getfield 26	com/datapacketsDao:rs	Ljava/sql/ResultSet;
    //   122: ldc 90
    //   124: invokeinterface 92 2 0
    //   129: invokevirtual 96	com/datapacketsBean:setStation_id	(I)V
    //   132: aload 5
    //   134: aload_0
    //   135: getfield 26	com/datapacketsDao:rs	Ljava/sql/ResultSet;
    //   138: ldc 100
    //   140: invokeinterface 80 2 0
    //   145: invokevirtual 102	com/datapacketsBean:setPacketno	(Ljava/lang/String;)V
    //   148: aload 5
    //   150: aload_0
    //   151: getfield 26	com/datapacketsDao:rs	Ljava/sql/ResultSet;
    //   154: ldc 105
    //   156: invokeinterface 107 2 0
    //   161: invokevirtual 111	com/datapacketsBean:setRain	(F)V
    //   164: aload 5
    //   166: aload_0
    //   167: getfield 26	com/datapacketsDao:rs	Ljava/sql/ResultSet;
    //   170: ldc 115
    //   172: invokeinterface 107 2 0
    //   177: invokevirtual 117	com/datapacketsBean:setTemp	(F)V
    //   180: aload 5
    //   182: aload_0
    //   183: getfield 26	com/datapacketsDao:rs	Ljava/sql/ResultSet;
    //   186: ldc 120
    //   188: invokeinterface 107 2 0
    //   193: invokevirtual 122	com/datapacketsBean:setWind	(F)V
    //   196: aload 5
    //   198: aload_0
    //   199: getfield 26	com/datapacketsDao:rs	Ljava/sql/ResultSet;
    //   202: ldc 125
    //   204: invokeinterface 107 2 0
    //   209: invokevirtual 127	com/datapacketsBean:setWind_direction	(F)V
    //   212: aload 5
    //   214: aload_0
    //   215: getfield 26	com/datapacketsDao:rs	Ljava/sql/ResultSet;
    //   218: ldc -126
    //   220: invokeinterface 107 2 0
    //   225: invokevirtual 132	com/datapacketsBean:setMslp	(F)V
    //   228: aload 5
    //   230: aload_0
    //   231: getfield 26	com/datapacketsDao:rs	Ljava/sql/ResultSet;
    //   234: ldc -121
    //   236: invokeinterface 107 2 0
    //   241: invokevirtual 137	com/datapacketsBean:setHumidity	(F)V
    //   244: aload 5
    //   246: aload_0
    //   247: getfield 26	com/datapacketsDao:rs	Ljava/sql/ResultSet;
    //   250: ldc -116
    //   252: invokeinterface 107 2 0
    //   257: invokevirtual 142	com/datapacketsBean:setLocal_pressure	(F)V
    //   260: aload 4
    //   262: aload 5
    //   264: invokeinterface 145 2 0
    //   269: pop
    //   270: aload_0
    //   271: getfield 26	com/datapacketsDao:rs	Ljava/sql/ResultSet;
    //   274: invokeinterface 151 1 0
    //   279: ifne -188 -> 91
    //   282: goto +70 -> 352
    //   285: astore 6
    //   287: aload 6
    //   289: invokevirtual 155	java/sql/SQLException:printStackTrace	()V
    //   292: aload_0
    //   293: getfield 30	com/datapacketsDao:stmt	Ljava/sql/Statement;
    //   296: ifnull +82 -> 378
    //   299: aload_0
    //   300: getfield 30	com/datapacketsDao:stmt	Ljava/sql/Statement;
    //   303: invokeinterface 160 1 0
    //   308: goto +70 -> 378
    //   311: astore 8
    //   313: aload 8
    //   315: invokevirtual 155	java/sql/SQLException:printStackTrace	()V
    //   318: goto +60 -> 378
    //   321: astore 7
    //   323: aload_0
    //   324: getfield 30	com/datapacketsDao:stmt	Ljava/sql/Statement;
    //   327: ifnull +22 -> 349
    //   330: aload_0
    //   331: getfield 30	com/datapacketsDao:stmt	Ljava/sql/Statement;
    //   334: invokeinterface 160 1 0
    //   339: goto +10 -> 349
    //   342: astore 8
    //   344: aload 8
    //   346: invokevirtual 155	java/sql/SQLException:printStackTrace	()V
    //   349: aload 7
    //   351: athrow
    //   352: aload_0
    //   353: getfield 30	com/datapacketsDao:stmt	Ljava/sql/Statement;
    //   356: ifnull +22 -> 378
    //   359: aload_0
    //   360: getfield 30	com/datapacketsDao:stmt	Ljava/sql/Statement;
    //   363: invokeinterface 160 1 0
    //   368: goto +10 -> 378
    //   371: astore 8
    //   373: aload 8
    //   375: invokevirtual 155	java/sql/SQLException:printStackTrace	()V
    //   378: aload 4
    //   380: areturn
    // Line number table:
    //   Java source line #26	-> byte code offset #0
    //   Java source line #27	-> byte code offset #9
    //   Java source line #29	-> byte code offset #12
    //   Java source line #33	-> byte code offset #18
    //   Java source line #34	-> byte code offset #25
    //   Java source line #35	-> byte code offset #42
    //   Java source line #36	-> byte code offset #53
    //   Java source line #37	-> byte code offset #64
    //   Java source line #38	-> byte code offset #75
    //   Java source line #39	-> byte code offset #88
    //   Java source line #40	-> byte code offset #91
    //   Java source line #41	-> byte code offset #100
    //   Java source line #42	-> byte code offset #116
    //   Java source line #43	-> byte code offset #132
    //   Java source line #44	-> byte code offset #148
    //   Java source line #45	-> byte code offset #164
    //   Java source line #46	-> byte code offset #180
    //   Java source line #47	-> byte code offset #196
    //   Java source line #48	-> byte code offset #212
    //   Java source line #49	-> byte code offset #228
    //   Java source line #50	-> byte code offset #244
    //   Java source line #53	-> byte code offset #260
    //   Java source line #39	-> byte code offset #270
    //   Java source line #55	-> byte code offset #282
    //   Java source line #59	-> byte code offset #292
    //   Java source line #60	-> byte code offset #299
    //   Java source line #61	-> byte code offset #308
    //   Java source line #62	-> byte code offset #313
    //   Java source line #57	-> byte code offset #321
    //   Java source line #59	-> byte code offset #323
    //   Java source line #60	-> byte code offset #330
    //   Java source line #61	-> byte code offset #339
    //   Java source line #62	-> byte code offset #344
    //   Java source line #64	-> byte code offset #349
    //   Java source line #59	-> byte code offset #352
    //   Java source line #60	-> byte code offset #359
    //   Java source line #61	-> byte code offset #368
    //   Java source line #62	-> byte code offset #373
    //   Java source line #66	-> byte code offset #378
    // Local variable table:
    //   start	length	slot	name	signature
    //   0	381	0	this	datapacketsDao
    //   0	381	1	stationid	int
    //   0	381	2	fdate	String
    //   0	381	3	tdate	String
    //   7	372	4	list	java.util.List<datapacketsBean>
    //   10	253	5	dp	datapacketsBean
    //   285	3	6	e	java.sql.SQLException
    //   321	29	7	localObject	Object
    //   311	3	8	e	java.sql.SQLException
    //   342	3	8	e	java.sql.SQLException
    //   371	3	8	e	java.sql.SQLException
    // Exception table:
    //   from	to	target	type
    //   12	282	285	java/sql/SQLException
    //   292	308	311	java/sql/SQLException
    //   12	292	321	finally
    //   323	339	342	java/sql/SQLException
    //   352	368	371	java/sql/SQLException
  }
}
