package com;

import java.sql.Connection;
import java.sql.PreparedStatement;
import java.sql.ResultSet;
import java.sql.Statement;

public class locationDao
{
  Connection connection = null;
  PreparedStatement ptmt = null;
  ResultSet rs = null;
  boolean status = false;
  Statement stmt = null;
  String query = "";
  
  /* Error */
  public java.util.List<locationBean> viewStates()
  {
	  return null;
    // Byte code:
    //   0: aload_0
    //   1: ldc 44
    //   3: putfield 34	com/locationDao:query	Ljava/lang/String;
    //   6: new 46	java/util/ArrayList
    //   9: dup
    //   10: invokespecial 48	java/util/ArrayList:<init>	()V
    //   13: astore_1
    //   14: aconst_null
    //   15: astore_2
    //   16: aload_0
    //   17: invokestatic 49	com/ConnectionProvider:getCon	()Ljava/sql/Connection;
    //   20: putfield 22	com/locationDao:connection	Ljava/sql/Connection;
    //   23: aload_0
    //   24: aload_0
    //   25: getfield 22	com/locationDao:connection	Ljava/sql/Connection;
    //   28: invokeinterface 55 1 0
    //   33: putfield 30	com/locationDao:stmt	Ljava/sql/Statement;
    //   36: aload_0
    //   37: aload_0
    //   38: getfield 30	com/locationDao:stmt	Ljava/sql/Statement;
    //   41: aload_0
    //   42: getfield 34	com/locationDao:query	Ljava/lang/String;
    //   45: invokeinterface 61 2 0
    //   50: putfield 26	com/locationDao:rs	Ljava/sql/ResultSet;
    //   53: goto +49 -> 102
    //   56: new 67	com/locationBean
    //   59: dup
    //   60: invokespecial 69	com/locationBean:<init>	()V
    //   63: astore_2
    //   64: aload_2
    //   65: aload_0
    //   66: getfield 26	com/locationDao:rs	Ljava/sql/ResultSet;
    //   69: ldc 70
    //   71: invokeinterface 72 2 0
    //   76: invokevirtual 78	com/locationBean:setStateid	(I)V
    //   79: aload_2
    //   80: aload_0
    //   81: getfield 26	com/locationDao:rs	Ljava/sql/ResultSet;
    //   84: ldc 82
    //   86: invokeinterface 84 2 0
    //   91: invokevirtual 88	com/locationBean:setSname	(Ljava/lang/String;)V
    //   94: aload_1
    //   95: aload_2
    //   96: invokeinterface 92 2 0
    //   101: pop
    //   102: aload_0
    //   103: getfield 26	com/locationDao:rs	Ljava/sql/ResultSet;
    //   106: invokeinterface 98 1 0
    //   111: ifne -55 -> 56
    //   114: aload_0
    //   115: getfield 26	com/locationDao:rs	Ljava/sql/ResultSet;
    //   118: invokeinterface 102 1 0
    //   123: goto +68 -> 191
    //   126: astore_3
    //   127: aload_3
    //   128: invokevirtual 105	java/sql/SQLException:printStackTrace	()V
    //   131: aload_0
    //   132: getfield 30	com/locationDao:stmt	Ljava/sql/Statement;
    //   135: ifnull +82 -> 217
    //   138: aload_0
    //   139: getfield 30	com/locationDao:stmt	Ljava/sql/Statement;
    //   142: invokeinterface 110 1 0
    //   147: goto +70 -> 217
    //   150: astore 5
    //   152: aload 5
    //   154: invokevirtual 105	java/sql/SQLException:printStackTrace	()V
    //   157: goto +60 -> 217
    //   160: astore 4
    //   162: aload_0
    //   163: getfield 30	com/locationDao:stmt	Ljava/sql/Statement;
    //   166: ifnull +22 -> 188
    //   169: aload_0
    //   170: getfield 30	com/locationDao:stmt	Ljava/sql/Statement;
    //   173: invokeinterface 110 1 0
    //   178: goto +10 -> 188
    //   181: astore 5
    //   183: aload 5
    //   185: invokevirtual 105	java/sql/SQLException:printStackTrace	()V
    //   188: aload 4
    //   190: athrow
    //   191: aload_0
    //   192: getfield 30	com/locationDao:stmt	Ljava/sql/Statement;
    //   195: ifnull +22 -> 217
    //   198: aload_0
    //   199: getfield 30	com/locationDao:stmt	Ljava/sql/Statement;
    //   202: invokeinterface 110 1 0
    //   207: goto +10 -> 217
    //   210: astore 5
    //   212: aload 5
    //   214: invokevirtual 105	java/sql/SQLException:printStackTrace	()V
    //   217: aload_1
    //   218: areturn
    // Line number table:
    //   Java source line #31	-> byte code offset #0
    //   Java source line #32	-> byte code offset #6
    //   Java source line #33	-> byte code offset #14
    //   Java source line #35	-> byte code offset #16
    //   Java source line #36	-> byte code offset #23
    //   Java source line #37	-> byte code offset #36
    //   Java source line #38	-> byte code offset #53
    //   Java source line #39	-> byte code offset #56
    //   Java source line #40	-> byte code offset #64
    //   Java source line #41	-> byte code offset #79
    //   Java source line #42	-> byte code offset #94
    //   Java source line #38	-> byte code offset #102
    //   Java source line #44	-> byte code offset #114
    //   Java source line #46	-> byte code offset #123
    //   Java source line #48	-> byte code offset #131
    //   Java source line #49	-> byte code offset #138
    //   Java source line #47	-> byte code offset #160
    //   Java source line #48	-> byte code offset #162
    //   Java source line #49	-> byte code offset #169
    //   Java source line #50	-> byte code offset #188
    //   Java source line #48	-> byte code offset #191
    //   Java source line #49	-> byte code offset #198
    //   Java source line #51	-> byte code offset #217
    // Local variable table:
    //   start	length	slot	name	signature
    //   0	219	0	this	locationDao
    //   13	205	1	list	java.util.List<locationBean>
    //   15	81	2	location	locationBean
    //   126	2	3	e	java.sql.SQLException
    //   160	29	4	localObject	Object
    //   150	3	5	e	java.sql.SQLException
    //   181	3	5	e	java.sql.SQLException
    //   210	3	5	e	java.sql.SQLException
    // Exception table:
    //   from	to	target	type
    //   16	123	126	java/sql/SQLException
    //   131	147	150	java/sql/SQLException
    //   16	131	160	finally
    //   162	178	181	java/sql/SQLException
    //   191	207	210	java/sql/SQLException
  }
  
  /* Error */
  public java.util.List<locationBean> viewDistrict(int stateid)
  {
	   return null;
    // Byte code:
    //   0: aload_0
    //   1: ldc 125
    //   3: putfield 34	com/locationDao:query	Ljava/lang/String;
    //   6: new 46	java/util/ArrayList
    //   9: dup
    //   10: invokespecial 48	java/util/ArrayList:<init>	()V
    //   13: astore_2
    //   14: aconst_null
    //   15: astore_3
    //   16: aload_0
    //   17: invokestatic 49	com/ConnectionProvider:getCon	()Ljava/sql/Connection;
    //   20: putfield 22	com/locationDao:connection	Ljava/sql/Connection;
    //   23: aload_0
    //   24: aload_0
    //   25: getfield 22	com/locationDao:connection	Ljava/sql/Connection;
    //   28: aload_0
    //   29: getfield 34	com/locationDao:query	Ljava/lang/String;
    //   32: invokeinterface 127 2 0
    //   37: putfield 24	com/locationDao:ptmt	Ljava/sql/PreparedStatement;
    //   40: aload_0
    //   41: getfield 24	com/locationDao:ptmt	Ljava/sql/PreparedStatement;
    //   44: iconst_1
    //   45: iload_1
    //   46: invokeinterface 131 3 0
    //   51: aload_0
    //   52: aload_0
    //   53: getfield 24	com/locationDao:ptmt	Ljava/sql/PreparedStatement;
    //   56: invokeinterface 137 1 0
    //   61: putfield 26	com/locationDao:rs	Ljava/sql/ResultSet;
    //   64: goto +49 -> 113
    //   67: new 67	com/locationBean
    //   70: dup
    //   71: invokespecial 69	com/locationBean:<init>	()V
    //   74: astore_3
    //   75: aload_3
    //   76: aload_0
    //   77: getfield 26	com/locationDao:rs	Ljava/sql/ResultSet;
    //   80: ldc -116
    //   82: invokeinterface 72 2 0
    //   87: invokevirtual 142	com/locationBean:setDistrict_id	(I)V
    //   90: aload_3
    //   91: aload_0
    //   92: getfield 26	com/locationDao:rs	Ljava/sql/ResultSet;
    //   95: ldc -111
    //   97: invokeinterface 84 2 0
    //   102: invokevirtual 147	com/locationBean:setDname	(Ljava/lang/String;)V
    //   105: aload_2
    //   106: aload_3
    //   107: invokeinterface 92 2 0
    //   112: pop
    //   113: aload_0
    //   114: getfield 26	com/locationDao:rs	Ljava/sql/ResultSet;
    //   117: invokeinterface 98 1 0
    //   122: ifne -55 -> 67
    //   125: aload_0
    //   126: getfield 26	com/locationDao:rs	Ljava/sql/ResultSet;
    //   129: invokeinterface 102 1 0
    //   134: goto +70 -> 204
    //   137: astore 4
    //   139: aload 4
    //   141: invokevirtual 105	java/sql/SQLException:printStackTrace	()V
    //   144: aload_0
    //   145: getfield 30	com/locationDao:stmt	Ljava/sql/Statement;
    //   148: ifnull +82 -> 230
    //   151: aload_0
    //   152: getfield 30	com/locationDao:stmt	Ljava/sql/Statement;
    //   155: invokeinterface 110 1 0
    //   160: goto +70 -> 230
    //   163: astore 6
    //   165: aload 6
    //   167: invokevirtual 105	java/sql/SQLException:printStackTrace	()V
    //   170: goto +60 -> 230
    //   173: astore 5
    //   175: aload_0
    //   176: getfield 30	com/locationDao:stmt	Ljava/sql/Statement;
    //   179: ifnull +22 -> 201
    //   182: aload_0
    //   183: getfield 30	com/locationDao:stmt	Ljava/sql/Statement;
    //   186: invokeinterface 110 1 0
    //   191: goto +10 -> 201
    //   194: astore 6
    //   196: aload 6
    //   198: invokevirtual 105	java/sql/SQLException:printStackTrace	()V
    //   201: aload 5
    //   203: athrow
    //   204: aload_0
    //   205: getfield 30	com/locationDao:stmt	Ljava/sql/Statement;
    //   208: ifnull +22 -> 230
    //   211: aload_0
    //   212: getfield 30	com/locationDao:stmt	Ljava/sql/Statement;
    //   215: invokeinterface 110 1 0
    //   220: goto +10 -> 230
    //   223: astore 6
    //   225: aload 6
    //   227: invokevirtual 105	java/sql/SQLException:printStackTrace	()V
    //   230: aload_2
    //   231: areturn
    // Line number table:
    //   Java source line #57	-> byte code offset #0
    //   Java source line #58	-> byte code offset #6
    //   Java source line #59	-> byte code offset #14
    //   Java source line #61	-> byte code offset #16
    //   Java source line #62	-> byte code offset #23
    //   Java source line #63	-> byte code offset #40
    //   Java source line #64	-> byte code offset #51
    //   Java source line #65	-> byte code offset #64
    //   Java source line #66	-> byte code offset #67
    //   Java source line #67	-> byte code offset #75
    //   Java source line #68	-> byte code offset #90
    //   Java source line #69	-> byte code offset #105
    //   Java source line #65	-> byte code offset #113
    //   Java source line #71	-> byte code offset #125
    //   Java source line #73	-> byte code offset #134
    //   Java source line #77	-> byte code offset #144
    //   Java source line #78	-> byte code offset #151
    //   Java source line #79	-> byte code offset #160
    //   Java source line #80	-> byte code offset #165
    //   Java source line #75	-> byte code offset #173
    //   Java source line #77	-> byte code offset #175
    //   Java source line #78	-> byte code offset #182
    //   Java source line #79	-> byte code offset #191
    //   Java source line #80	-> byte code offset #196
    //   Java source line #82	-> byte code offset #201
    //   Java source line #77	-> byte code offset #204
    //   Java source line #78	-> byte code offset #211
    //   Java source line #79	-> byte code offset #220
    //   Java source line #80	-> byte code offset #225
    //   Java source line #83	-> byte code offset #230
    // Local variable table:
    //   start	length	slot	name	signature
    //   0	232	0	this	locationDao
    //   0	232	1	stateid	int
    //   13	218	2	list	java.util.List<locationBean>
    //   15	92	3	location	locationBean
    //   137	3	4	e	java.sql.SQLException
    //   173	29	5	localObject	Object
    //   163	3	6	e	java.sql.SQLException
    //   194	3	6	e	java.sql.SQLException
    //   223	3	6	e	java.sql.SQLException
    // Exception table:
    //   from	to	target	type
    //   16	134	137	java/sql/SQLException
    //   144	160	163	java/sql/SQLException
    //   16	144	173	finally
    //   175	191	194	java/sql/SQLException
    //   204	220	223	java/sql/SQLException
  }
  
  /* Error */
  public java.util.List<locationBean> viewCounty(int distid)
  {
	  return null;
    // Byte code:
    //   0: aload_0
    //   1: ldc -103
    //   3: putfield 34	com/locationDao:query	Ljava/lang/String;
    //   6: new 46	java/util/ArrayList
    //   9: dup
    //   10: invokespecial 48	java/util/ArrayList:<init>	()V
    //   13: astore_2
    //   14: aconst_null
    //   15: astore_3
    //   16: aload_0
    //   17: invokestatic 49	com/ConnectionProvider:getCon	()Ljava/sql/Connection;
    //   20: putfield 22	com/locationDao:connection	Ljava/sql/Connection;
    //   23: aload_0
    //   24: aload_0
    //   25: getfield 22	com/locationDao:connection	Ljava/sql/Connection;
    //   28: aload_0
    //   29: getfield 34	com/locationDao:query	Ljava/lang/String;
    //   32: invokeinterface 127 2 0
    //   37: putfield 24	com/locationDao:ptmt	Ljava/sql/PreparedStatement;
    //   40: aload_0
    //   41: getfield 24	com/locationDao:ptmt	Ljava/sql/PreparedStatement;
    //   44: iconst_1
    //   45: iload_1
    //   46: invokeinterface 131 3 0
    //   51: aload_0
    //   52: aload_0
    //   53: getfield 24	com/locationDao:ptmt	Ljava/sql/PreparedStatement;
    //   56: invokeinterface 137 1 0
    //   61: putfield 26	com/locationDao:rs	Ljava/sql/ResultSet;
    //   64: goto +49 -> 113
    //   67: new 67	com/locationBean
    //   70: dup
    //   71: invokespecial 69	com/locationBean:<init>	()V
    //   74: astore_3
    //   75: aload_3
    //   76: aload_0
    //   77: getfield 26	com/locationDao:rs	Ljava/sql/ResultSet;
    //   80: ldc -101
    //   82: invokeinterface 72 2 0
    //   87: invokevirtual 157	com/locationBean:setCounty_id	(I)V
    //   90: aload_3
    //   91: aload_0
    //   92: getfield 26	com/locationDao:rs	Ljava/sql/ResultSet;
    //   95: ldc -96
    //   97: invokeinterface 84 2 0
    //   102: invokevirtual 162	com/locationBean:setCname	(Ljava/lang/String;)V
    //   105: aload_2
    //   106: aload_3
    //   107: invokeinterface 92 2 0
    //   112: pop
    //   113: aload_0
    //   114: getfield 26	com/locationDao:rs	Ljava/sql/ResultSet;
    //   117: invokeinterface 98 1 0
    //   122: ifne -55 -> 67
    //   125: aload_0
    //   126: getfield 26	com/locationDao:rs	Ljava/sql/ResultSet;
    //   129: invokeinterface 102 1 0
    //   134: goto +70 -> 204
    //   137: astore 4
    //   139: aload 4
    //   141: invokevirtual 105	java/sql/SQLException:printStackTrace	()V
    //   144: aload_0
    //   145: getfield 30	com/locationDao:stmt	Ljava/sql/Statement;
    //   148: ifnull +82 -> 230
    //   151: aload_0
    //   152: getfield 30	com/locationDao:stmt	Ljava/sql/Statement;
    //   155: invokeinterface 110 1 0
    //   160: goto +70 -> 230
    //   163: astore 6
    //   165: aload 6
    //   167: invokevirtual 105	java/sql/SQLException:printStackTrace	()V
    //   170: goto +60 -> 230
    //   173: astore 5
    //   175: aload_0
    //   176: getfield 30	com/locationDao:stmt	Ljava/sql/Statement;
    //   179: ifnull +22 -> 201
    //   182: aload_0
    //   183: getfield 30	com/locationDao:stmt	Ljava/sql/Statement;
    //   186: invokeinterface 110 1 0
    //   191: goto +10 -> 201
    //   194: astore 6
    //   196: aload 6
    //   198: invokevirtual 105	java/sql/SQLException:printStackTrace	()V
    //   201: aload 5
    //   203: athrow
    //   204: aload_0
    //   205: getfield 30	com/locationDao:stmt	Ljava/sql/Statement;
    //   208: ifnull +22 -> 230
    //   211: aload_0
    //   212: getfield 30	com/locationDao:stmt	Ljava/sql/Statement;
    //   215: invokeinterface 110 1 0
    //   220: goto +10 -> 230
    //   223: astore 6
    //   225: aload 6
    //   227: invokevirtual 105	java/sql/SQLException:printStackTrace	()V
    //   230: aload_2
    //   231: areturn
    // Line number table:
    //   Java source line #88	-> byte code offset #0
    //   Java source line #89	-> byte code offset #6
    //   Java source line #90	-> byte code offset #14
    //   Java source line #92	-> byte code offset #16
    //   Java source line #93	-> byte code offset #23
    //   Java source line #94	-> byte code offset #40
    //   Java source line #95	-> byte code offset #51
    //   Java source line #96	-> byte code offset #64
    //   Java source line #97	-> byte code offset #67
    //   Java source line #98	-> byte code offset #75
    //   Java source line #99	-> byte code offset #90
    //   Java source line #100	-> byte code offset #105
    //   Java source line #96	-> byte code offset #113
    //   Java source line #102	-> byte code offset #125
    //   Java source line #104	-> byte code offset #134
    //   Java source line #108	-> byte code offset #144
    //   Java source line #109	-> byte code offset #151
    //   Java source line #110	-> byte code offset #160
    //   Java source line #111	-> byte code offset #165
    //   Java source line #106	-> byte code offset #173
    //   Java source line #108	-> byte code offset #175
    //   Java source line #109	-> byte code offset #182
    //   Java source line #110	-> byte code offset #191
    //   Java source line #111	-> byte code offset #196
    //   Java source line #113	-> byte code offset #201
    //   Java source line #108	-> byte code offset #204
    //   Java source line #109	-> byte code offset #211
    //   Java source line #110	-> byte code offset #220
    //   Java source line #111	-> byte code offset #225
    //   Java source line #114	-> byte code offset #230
    // Local variable table:
    //   start	length	slot	name	signature
    //   0	232	0	this	locationDao
    //   0	232	1	distid	int
    //   13	218	2	list	java.util.List<locationBean>
    //   15	92	3	location	locationBean
    //   137	3	4	e	java.sql.SQLException
    //   173	29	5	localObject	Object
    //   163	3	6	e	java.sql.SQLException
    //   194	3	6	e	java.sql.SQLException
    //   223	3	6	e	java.sql.SQLException
    // Exception table:
    //   from	to	target	type
    //   16	134	137	java/sql/SQLException
    //   144	160	163	java/sql/SQLException
    //   16	144	173	finally
    //   175	191	194	java/sql/SQLException
    //   204	220	223	java/sql/SQLException
  }
  
  /* Error */
  public java.util.List<locationBean> viewStations(int stateid, int distid, int countyid)
  {
	  return null;
    // Byte code:
    //   0: new 46	java/util/ArrayList
    //   3: dup
    //   4: invokespecial 48	java/util/ArrayList:<init>	()V
    //   7: astore 4
    //   9: aconst_null
    //   10: astore 5
    //   12: aload_0
    //   13: ldc -87
    //   15: putfield 34	com/locationDao:query	Ljava/lang/String;
    //   18: aload_0
    //   19: invokestatic 49	com/ConnectionProvider:getCon	()Ljava/sql/Connection;
    //   22: putfield 22	com/locationDao:connection	Ljava/sql/Connection;
    //   25: aload_0
    //   26: aload_0
    //   27: getfield 22	com/locationDao:connection	Ljava/sql/Connection;
    //   30: aload_0
    //   31: getfield 34	com/locationDao:query	Ljava/lang/String;
    //   34: invokeinterface 127 2 0
    //   39: putfield 24	com/locationDao:ptmt	Ljava/sql/PreparedStatement;
    //   42: aload_0
    //   43: getfield 24	com/locationDao:ptmt	Ljava/sql/PreparedStatement;
    //   46: iconst_1
    //   47: iload_1
    //   48: invokeinterface 131 3 0
    //   53: aload_0
    //   54: getfield 24	com/locationDao:ptmt	Ljava/sql/PreparedStatement;
    //   57: iconst_2
    //   58: iload_2
    //   59: invokeinterface 131 3 0
    //   64: aload_0
    //   65: getfield 24	com/locationDao:ptmt	Ljava/sql/PreparedStatement;
    //   68: iconst_3
    //   69: iload_3
    //   70: invokeinterface 131 3 0
    //   75: aload_0
    //   76: aload_0
    //   77: getfield 24	com/locationDao:ptmt	Ljava/sql/PreparedStatement;
    //   80: invokeinterface 137 1 0
    //   85: putfield 26	com/locationDao:rs	Ljava/sql/ResultSet;
    //   88: goto +134 -> 222
    //   91: new 67	com/locationBean
    //   94: dup
    //   95: invokespecial 69	com/locationBean:<init>	()V
    //   98: astore 5
    //   100: aload 5
    //   102: aload_0
    //   103: getfield 26	com/locationDao:rs	Ljava/sql/ResultSet;
    //   106: ldc -85
    //   108: invokeinterface 72 2 0
    //   113: invokevirtual 173	com/locationBean:setLocation_id	(I)V
    //   116: aload 5
    //   118: aload_0
    //   119: getfield 26	com/locationDao:rs	Ljava/sql/ResultSet;
    //   122: ldc -111
    //   124: invokeinterface 84 2 0
    //   129: invokevirtual 147	com/locationBean:setDname	(Ljava/lang/String;)V
    //   132: aload 5
    //   134: aload_0
    //   135: getfield 26	com/locationDao:rs	Ljava/sql/ResultSet;
    //   138: ldc -80
    //   140: invokeinterface 84 2 0
    //   145: invokevirtual 162	com/locationBean:setCname	(Ljava/lang/String;)V
    //   148: aload 5
    //   150: aload_0
    //   151: getfield 26	com/locationDao:rs	Ljava/sql/ResultSet;
    //   154: ldc -78
    //   156: invokeinterface 84 2 0
    //   161: invokevirtual 179	com/locationBean:setLname	(Ljava/lang/String;)V
    //   164: aload 5
    //   166: aload_0
    //   167: getfield 26	com/locationDao:rs	Ljava/sql/ResultSet;
    //   170: ldc -74
    //   172: invokeinterface 84 2 0
    //   177: invokevirtual 184	com/locationBean:setLat	(Ljava/lang/String;)V
    //   180: aload 5
    //   182: aload_0
    //   183: getfield 26	com/locationDao:rs	Ljava/sql/ResultSet;
    //   186: ldc -69
    //   188: invokeinterface 84 2 0
    //   193: invokevirtual 189	com/locationBean:setLon	(Ljava/lang/String;)V
    //   196: aload 5
    //   198: aload_0
    //   199: getfield 26	com/locationDao:rs	Ljava/sql/ResultSet;
    //   202: ldc -64
    //   204: invokeinterface 84 2 0
    //   209: invokevirtual 194	com/locationBean:setAlt	(Ljava/lang/String;)V
    //   212: aload 4
    //   214: aload 5
    //   216: invokeinterface 92 2 0
    //   221: pop
    //   222: aload_0
    //   223: getfield 26	com/locationDao:rs	Ljava/sql/ResultSet;
    //   226: invokeinterface 98 1 0
    //   231: ifne -140 -> 91
    //   234: goto +70 -> 304
    //   237: astore 6
    //   239: aload 6
    //   241: invokevirtual 105	java/sql/SQLException:printStackTrace	()V
    //   244: aload_0
    //   245: getfield 30	com/locationDao:stmt	Ljava/sql/Statement;
    //   248: ifnull +82 -> 330
    //   251: aload_0
    //   252: getfield 30	com/locationDao:stmt	Ljava/sql/Statement;
    //   255: invokeinterface 110 1 0
    //   260: goto +70 -> 330
    //   263: astore 8
    //   265: aload 8
    //   267: invokevirtual 105	java/sql/SQLException:printStackTrace	()V
    //   270: goto +60 -> 330
    //   273: astore 7
    //   275: aload_0
    //   276: getfield 30	com/locationDao:stmt	Ljava/sql/Statement;
    //   279: ifnull +22 -> 301
    //   282: aload_0
    //   283: getfield 30	com/locationDao:stmt	Ljava/sql/Statement;
    //   286: invokeinterface 110 1 0
    //   291: goto +10 -> 301
    //   294: astore 8
    //   296: aload 8
    //   298: invokevirtual 105	java/sql/SQLException:printStackTrace	()V
    //   301: aload 7
    //   303: athrow
    //   304: aload_0
    //   305: getfield 30	com/locationDao:stmt	Ljava/sql/Statement;
    //   308: ifnull +22 -> 330
    //   311: aload_0
    //   312: getfield 30	com/locationDao:stmt	Ljava/sql/Statement;
    //   315: invokeinterface 110 1 0
    //   320: goto +10 -> 330
    //   323: astore 8
    //   325: aload 8
    //   327: invokevirtual 105	java/sql/SQLException:printStackTrace	()V
    //   330: aload 4
    //   332: areturn
    // Line number table:
    //   Java source line #120	-> byte code offset #0
    //   Java source line #121	-> byte code offset #9
    //   Java source line #125	-> byte code offset #12
    //   Java source line #128	-> byte code offset #18
    //   Java source line #129	-> byte code offset #25
    //   Java source line #130	-> byte code offset #42
    //   Java source line #131	-> byte code offset #53
    //   Java source line #132	-> byte code offset #64
    //   Java source line #133	-> byte code offset #75
    //   Java source line #134	-> byte code offset #88
    //   Java source line #135	-> byte code offset #91
    //   Java source line #136	-> byte code offset #100
    //   Java source line #137	-> byte code offset #116
    //   Java source line #138	-> byte code offset #132
    //   Java source line #139	-> byte code offset #148
    //   Java source line #140	-> byte code offset #164
    //   Java source line #141	-> byte code offset #180
    //   Java source line #142	-> byte code offset #196
    //   Java source line #143	-> byte code offset #212
    //   Java source line #134	-> byte code offset #222
    //   Java source line #146	-> byte code offset #234
    //   Java source line #150	-> byte code offset #244
    //   Java source line #151	-> byte code offset #251
    //   Java source line #152	-> byte code offset #260
    //   Java source line #153	-> byte code offset #265
    //   Java source line #148	-> byte code offset #273
    //   Java source line #150	-> byte code offset #275
    //   Java source line #151	-> byte code offset #282
    //   Java source line #152	-> byte code offset #291
    //   Java source line #153	-> byte code offset #296
    //   Java source line #155	-> byte code offset #301
    //   Java source line #150	-> byte code offset #304
    //   Java source line #151	-> byte code offset #311
    //   Java source line #152	-> byte code offset #320
    //   Java source line #153	-> byte code offset #325
    //   Java source line #156	-> byte code offset #330
    // Local variable table:
    //   start	length	slot	name	signature
    //   0	333	0	this	locationDao
    //   0	333	1	stateid	int
    //   0	333	2	distid	int
    //   0	333	3	countyid	int
    //   7	324	4	list	java.util.List<locationBean>
    //   10	205	5	location	locationBean
    //   237	3	6	e	java.sql.SQLException
    //   273	29	7	localObject	Object
    //   263	3	8	e	java.sql.SQLException
    //   294	3	8	e	java.sql.SQLException
    //   323	3	8	e	java.sql.SQLException
    // Exception table:
    //   from	to	target	type
    //   12	234	237	java/sql/SQLException
    //   244	260	263	java/sql/SQLException
    //   12	244	273	finally
    //   275	291	294	java/sql/SQLException
    //   304	320	323	java/sql/SQLException
  }
  
  /* Error */
  public java.util.List<locationBean> viewStations(int stateid, int distid)
  {
	  return null;
    // Byte code:
    //   0: new 46	java/util/ArrayList
    //   3: dup
    //   4: invokespecial 48	java/util/ArrayList:<init>	()V
    //   7: astore_3
    //   8: aconst_null
    //   9: astore 4
    //   11: aload_0
    //   12: ldc -56
    //   14: putfield 34	com/locationDao:query	Ljava/lang/String;
    //   17: aload_0
    //   18: invokestatic 49	com/ConnectionProvider:getCon	()Ljava/sql/Connection;
    //   21: putfield 22	com/locationDao:connection	Ljava/sql/Connection;
    //   24: aload_0
    //   25: aload_0
    //   26: getfield 22	com/locationDao:connection	Ljava/sql/Connection;
    //   29: aload_0
    //   30: getfield 34	com/locationDao:query	Ljava/lang/String;
    //   33: invokeinterface 127 2 0
    //   38: putfield 24	com/locationDao:ptmt	Ljava/sql/PreparedStatement;
    //   41: aload_0
    //   42: getfield 24	com/locationDao:ptmt	Ljava/sql/PreparedStatement;
    //   45: iconst_1
    //   46: iload_1
    //   47: invokeinterface 131 3 0
    //   52: aload_0
    //   53: getfield 24	com/locationDao:ptmt	Ljava/sql/PreparedStatement;
    //   56: iconst_2
    //   57: iload_2
    //   58: invokeinterface 131 3 0
    //   63: aload_0
    //   64: aload_0
    //   65: getfield 24	com/locationDao:ptmt	Ljava/sql/PreparedStatement;
    //   68: invokeinterface 137 1 0
    //   73: putfield 26	com/locationDao:rs	Ljava/sql/ResultSet;
    //   76: goto +133 -> 209
    //   79: new 67	com/locationBean
    //   82: dup
    //   83: invokespecial 69	com/locationBean:<init>	()V
    //   86: astore 4
    //   88: aload 4
    //   90: aload_0
    //   91: getfield 26	com/locationDao:rs	Ljava/sql/ResultSet;
    //   94: ldc -85
    //   96: invokeinterface 72 2 0
    //   101: invokevirtual 173	com/locationBean:setLocation_id	(I)V
    //   104: aload 4
    //   106: aload_0
    //   107: getfield 26	com/locationDao:rs	Ljava/sql/ResultSet;
    //   110: ldc -111
    //   112: invokeinterface 84 2 0
    //   117: invokevirtual 147	com/locationBean:setDname	(Ljava/lang/String;)V
    //   120: aload 4
    //   122: aload_0
    //   123: getfield 26	com/locationDao:rs	Ljava/sql/ResultSet;
    //   126: ldc -80
    //   128: invokeinterface 84 2 0
    //   133: invokevirtual 162	com/locationBean:setCname	(Ljava/lang/String;)V
    //   136: aload 4
    //   138: aload_0
    //   139: getfield 26	com/locationDao:rs	Ljava/sql/ResultSet;
    //   142: ldc -78
    //   144: invokeinterface 84 2 0
    //   149: invokevirtual 179	com/locationBean:setLname	(Ljava/lang/String;)V
    //   152: aload 4
    //   154: aload_0
    //   155: getfield 26	com/locationDao:rs	Ljava/sql/ResultSet;
    //   158: ldc -74
    //   160: invokeinterface 84 2 0
    //   165: invokevirtual 184	com/locationBean:setLat	(Ljava/lang/String;)V
    //   168: aload 4
    //   170: aload_0
    //   171: getfield 26	com/locationDao:rs	Ljava/sql/ResultSet;
    //   174: ldc -69
    //   176: invokeinterface 84 2 0
    //   181: invokevirtual 189	com/locationBean:setLon	(Ljava/lang/String;)V
    //   184: aload 4
    //   186: aload_0
    //   187: getfield 26	com/locationDao:rs	Ljava/sql/ResultSet;
    //   190: ldc -64
    //   192: invokeinterface 84 2 0
    //   197: invokevirtual 194	com/locationBean:setAlt	(Ljava/lang/String;)V
    //   200: aload_3
    //   201: aload 4
    //   203: invokeinterface 92 2 0
    //   208: pop
    //   209: aload_0
    //   210: getfield 26	com/locationDao:rs	Ljava/sql/ResultSet;
    //   213: invokeinterface 98 1 0
    //   218: ifne -139 -> 79
    //   221: goto +70 -> 291
    //   224: astore 5
    //   226: aload 5
    //   228: invokevirtual 105	java/sql/SQLException:printStackTrace	()V
    //   231: aload_0
    //   232: getfield 30	com/locationDao:stmt	Ljava/sql/Statement;
    //   235: ifnull +82 -> 317
    //   238: aload_0
    //   239: getfield 30	com/locationDao:stmt	Ljava/sql/Statement;
    //   242: invokeinterface 110 1 0
    //   247: goto +70 -> 317
    //   250: astore 7
    //   252: aload 7
    //   254: invokevirtual 105	java/sql/SQLException:printStackTrace	()V
    //   257: goto +60 -> 317
    //   260: astore 6
    //   262: aload_0
    //   263: getfield 30	com/locationDao:stmt	Ljava/sql/Statement;
    //   266: ifnull +22 -> 288
    //   269: aload_0
    //   270: getfield 30	com/locationDao:stmt	Ljava/sql/Statement;
    //   273: invokeinterface 110 1 0
    //   278: goto +10 -> 288
    //   281: astore 7
    //   283: aload 7
    //   285: invokevirtual 105	java/sql/SQLException:printStackTrace	()V
    //   288: aload 6
    //   290: athrow
    //   291: aload_0
    //   292: getfield 30	com/locationDao:stmt	Ljava/sql/Statement;
    //   295: ifnull +22 -> 317
    //   298: aload_0
    //   299: getfield 30	com/locationDao:stmt	Ljava/sql/Statement;
    //   302: invokeinterface 110 1 0
    //   307: goto +10 -> 317
    //   310: astore 7
    //   312: aload 7
    //   314: invokevirtual 105	java/sql/SQLException:printStackTrace	()V
    //   317: aload_3
    //   318: areturn
    // Line number table:
    //   Java source line #161	-> byte code offset #0
    //   Java source line #162	-> byte code offset #8
    //   Java source line #164	-> byte code offset #11
    //   Java source line #168	-> byte code offset #17
    //   Java source line #169	-> byte code offset #24
    //   Java source line #170	-> byte code offset #41
    //   Java source line #171	-> byte code offset #52
    //   Java source line #173	-> byte code offset #63
    //   Java source line #174	-> byte code offset #76
    //   Java source line #175	-> byte code offset #79
    //   Java source line #176	-> byte code offset #88
    //   Java source line #177	-> byte code offset #104
    //   Java source line #178	-> byte code offset #120
    //   Java source line #179	-> byte code offset #136
    //   Java source line #180	-> byte code offset #152
    //   Java source line #181	-> byte code offset #168
    //   Java source line #182	-> byte code offset #184
    //   Java source line #183	-> byte code offset #200
    //   Java source line #174	-> byte code offset #209
    //   Java source line #185	-> byte code offset #221
    //   Java source line #189	-> byte code offset #231
    //   Java source line #190	-> byte code offset #238
    //   Java source line #191	-> byte code offset #247
    //   Java source line #192	-> byte code offset #252
    //   Java source line #187	-> byte code offset #260
    //   Java source line #189	-> byte code offset #262
    //   Java source line #190	-> byte code offset #269
    //   Java source line #191	-> byte code offset #278
    //   Java source line #192	-> byte code offset #283
    //   Java source line #194	-> byte code offset #288
    //   Java source line #189	-> byte code offset #291
    //   Java source line #190	-> byte code offset #298
    //   Java source line #191	-> byte code offset #307
    //   Java source line #192	-> byte code offset #312
    //   Java source line #196	-> byte code offset #317
    // Local variable table:
    //   start	length	slot	name	signature
    //   0	319	0	this	locationDao
    //   0	319	1	stateid	int
    //   0	319	2	distid	int
    //   7	311	3	list	java.util.List<locationBean>
    //   9	193	4	location	locationBean
    //   224	3	5	e	java.sql.SQLException
    //   260	29	6	localObject	Object
    //   250	3	7	e	java.sql.SQLException
    //   281	3	7	e	java.sql.SQLException
    //   310	3	7	e	java.sql.SQLException
    // Exception table:
    //   from	to	target	type
    //   11	221	224	java/sql/SQLException
    //   231	247	250	java/sql/SQLException
    //   11	231	260	finally
    //   262	278	281	java/sql/SQLException
    //   291	307	310	java/sql/SQLException
  }
  
  /* Error */
  public void delLocation(int locid)
  {
    // Byte code:
    //   0: aload_0
    //   1: ldc -53
    //   3: putfield 34	com/locationDao:query	Ljava/lang/String;
    //   6: aload_0
    //   7: invokestatic 49	com/ConnectionProvider:getCon	()Ljava/sql/Connection;
    //   10: putfield 22	com/locationDao:connection	Ljava/sql/Connection;
    //   13: aload_0
    //   14: aload_0
    //   15: getfield 22	com/locationDao:connection	Ljava/sql/Connection;
    //   18: aload_0
    //   19: getfield 34	com/locationDao:query	Ljava/lang/String;
    //   22: invokeinterface 127 2 0
    //   27: putfield 24	com/locationDao:ptmt	Ljava/sql/PreparedStatement;
    //   30: aload_0
    //   31: getfield 24	com/locationDao:ptmt	Ljava/sql/PreparedStatement;
    //   34: iconst_1
    //   35: iload_1
    //   36: invokeinterface 131 3 0
    //   41: aload_0
    //   42: getfield 24	com/locationDao:ptmt	Ljava/sql/PreparedStatement;
    //   45: invokeinterface 205 1 0
    //   50: pop
    //   51: goto +86 -> 137
    //   54: astore_2
    //   55: aload_2
    //   56: invokevirtual 105	java/sql/SQLException:printStackTrace	()V
    //   59: aload_0
    //   60: getfield 24	com/locationDao:ptmt	Ljava/sql/PreparedStatement;
    //   63: ifnull +110 -> 173
    //   66: aload_0
    //   67: getfield 24	com/locationDao:ptmt	Ljava/sql/PreparedStatement;
    //   70: invokeinterface 209 1 0
    //   75: goto +98 -> 173
    //   78: astore 4
    //   80: aload 4
    //   82: invokevirtual 105	java/sql/SQLException:printStackTrace	()V
    //   85: goto +88 -> 173
    //   88: astore 4
    //   90: aload 4
    //   92: invokevirtual 210	java/lang/Exception:printStackTrace	()V
    //   95: goto +78 -> 173
    //   98: astore_3
    //   99: aload_0
    //   100: getfield 24	com/locationDao:ptmt	Ljava/sql/PreparedStatement;
    //   103: ifnull +32 -> 135
    //   106: aload_0
    //   107: getfield 24	com/locationDao:ptmt	Ljava/sql/PreparedStatement;
    //   110: invokeinterface 209 1 0
    //   115: goto +20 -> 135
    //   118: astore 4
    //   120: aload 4
    //   122: invokevirtual 105	java/sql/SQLException:printStackTrace	()V
    //   125: goto +10 -> 135
    //   128: astore 4
    //   130: aload 4
    //   132: invokevirtual 210	java/lang/Exception:printStackTrace	()V
    //   135: aload_3
    //   136: athrow
    //   137: aload_0
    //   138: getfield 24	com/locationDao:ptmt	Ljava/sql/PreparedStatement;
    //   141: ifnull +32 -> 173
    //   144: aload_0
    //   145: getfield 24	com/locationDao:ptmt	Ljava/sql/PreparedStatement;
    //   148: invokeinterface 209 1 0
    //   153: goto +20 -> 173
    //   156: astore 4
    //   158: aload 4
    //   160: invokevirtual 105	java/sql/SQLException:printStackTrace	()V
    //   163: goto +10 -> 173
    //   166: astore 4
    //   168: aload 4
    //   170: invokevirtual 210	java/lang/Exception:printStackTrace	()V
    //   173: return
    // Line number table:
    //   Java source line #202	-> byte code offset #0
    //   Java source line #204	-> byte code offset #6
    //   Java source line #205	-> byte code offset #13
    //   Java source line #206	-> byte code offset #30
    //   Java source line #207	-> byte code offset #41
    //   Java source line #208	-> byte code offset #51
    //   Java source line #209	-> byte code offset #55
    //   Java source line #212	-> byte code offset #59
    //   Java source line #213	-> byte code offset #66
    //   Java source line #214	-> byte code offset #75
    //   Java source line #215	-> byte code offset #80
    //   Java source line #216	-> byte code offset #88
    //   Java source line #217	-> byte code offset #90
    //   Java source line #210	-> byte code offset #98
    //   Java source line #212	-> byte code offset #99
    //   Java source line #213	-> byte code offset #106
    //   Java source line #214	-> byte code offset #115
    //   Java source line #215	-> byte code offset #120
    //   Java source line #216	-> byte code offset #128
    //   Java source line #217	-> byte code offset #130
    //   Java source line #220	-> byte code offset #135
    //   Java source line #212	-> byte code offset #137
    //   Java source line #213	-> byte code offset #144
    //   Java source line #214	-> byte code offset #153
    //   Java source line #215	-> byte code offset #158
    //   Java source line #216	-> byte code offset #166
    //   Java source line #217	-> byte code offset #168
    //   Java source line #222	-> byte code offset #173
    // Local variable table:
    //   start	length	slot	name	signature
    //   0	174	0	this	locationDao
    //   0	174	1	locid	int
    //   54	2	2	e	java.sql.SQLException
    //   98	38	3	localObject	Object
    //   78	3	4	e	java.sql.SQLException
    //   88	3	4	e	Exception
    //   118	3	4	e	java.sql.SQLException
    //   128	3	4	e	Exception
    //   156	3	4	e	java.sql.SQLException
    //   166	3	4	e	Exception
    // Exception table:
    //   from	to	target	type
    //   0	51	54	java/sql/SQLException
    //   59	75	78	java/sql/SQLException
    //   59	75	88	java/lang/Exception
    //   0	59	98	finally
    //   99	115	118	java/sql/SQLException
    //   99	115	128	java/lang/Exception
    //   137	153	156	java/sql/SQLException
    //   137	153	166	java/lang/Exception
  }
  
  /* Error */
  public void searchLocation(locationBean station)
  {
    // Byte code:
    //   0: aload_0
    //   1: ldc -39
    //   3: putfield 34	com/locationDao:query	Ljava/lang/String;
    //   6: aload_0
    //   7: invokestatic 49	com/ConnectionProvider:getCon	()Ljava/sql/Connection;
    //   10: putfield 22	com/locationDao:connection	Ljava/sql/Connection;
    //   13: aload_0
    //   14: aload_0
    //   15: getfield 22	com/locationDao:connection	Ljava/sql/Connection;
    //   18: aload_0
    //   19: getfield 34	com/locationDao:query	Ljava/lang/String;
    //   22: invokeinterface 127 2 0
    //   27: putfield 24	com/locationDao:ptmt	Ljava/sql/PreparedStatement;
    //   30: aload_0
    //   31: getfield 24	com/locationDao:ptmt	Ljava/sql/PreparedStatement;
    //   34: iconst_1
    //   35: aload_1
    //   36: invokevirtual 219	com/locationBean:getLocation_id	()I
    //   39: invokeinterface 131 3 0
    //   44: aload_0
    //   45: aload_0
    //   46: getfield 24	com/locationDao:ptmt	Ljava/sql/PreparedStatement;
    //   49: invokeinterface 137 1 0
    //   54: putfield 26	com/locationDao:rs	Ljava/sql/ResultSet;
    //   57: aload_0
    //   58: getfield 26	com/locationDao:rs	Ljava/sql/ResultSet;
    //   61: invokeinterface 98 1 0
    //   66: pop
    //   67: aload_1
    //   68: aload_0
    //   69: getfield 26	com/locationDao:rs	Ljava/sql/ResultSet;
    //   72: ldc -34
    //   74: invokeinterface 72 2 0
    //   79: invokevirtual 173	com/locationBean:setLocation_id	(I)V
    //   82: aload_1
    //   83: aload_0
    //   84: getfield 26	com/locationDao:rs	Ljava/sql/ResultSet;
    //   87: ldc 82
    //   89: invokeinterface 72 2 0
    //   94: invokevirtual 78	com/locationBean:setStateid	(I)V
    //   97: aload_1
    //   98: aload_0
    //   99: getfield 26	com/locationDao:rs	Ljava/sql/ResultSet;
    //   102: ldc -111
    //   104: invokeinterface 72 2 0
    //   109: invokevirtual 142	com/locationBean:setDistrict_id	(I)V
    //   112: aload_1
    //   113: aload_0
    //   114: getfield 26	com/locationDao:rs	Ljava/sql/ResultSet;
    //   117: ldc -80
    //   119: invokeinterface 72 2 0
    //   124: invokevirtual 157	com/locationBean:setCounty_id	(I)V
    //   127: aload_1
    //   128: aload_0
    //   129: getfield 26	com/locationDao:rs	Ljava/sql/ResultSet;
    //   132: ldc -32
    //   134: invokeinterface 84 2 0
    //   139: invokevirtual 147	com/locationBean:setDname	(Ljava/lang/String;)V
    //   142: aload_1
    //   143: aload_0
    //   144: getfield 26	com/locationDao:rs	Ljava/sql/ResultSet;
    //   147: ldc -30
    //   149: invokeinterface 84 2 0
    //   154: invokevirtual 162	com/locationBean:setCname	(Ljava/lang/String;)V
    //   157: aload_1
    //   158: aload_0
    //   159: getfield 26	com/locationDao:rs	Ljava/sql/ResultSet;
    //   162: ldc -74
    //   164: invokeinterface 84 2 0
    //   169: invokevirtual 184	com/locationBean:setLat	(Ljava/lang/String;)V
    //   172: aload_1
    //   173: aload_0
    //   174: getfield 26	com/locationDao:rs	Ljava/sql/ResultSet;
    //   177: ldc -69
    //   179: invokeinterface 84 2 0
    //   184: invokevirtual 189	com/locationBean:setLon	(Ljava/lang/String;)V
    //   187: aload_1
    //   188: aload_0
    //   189: getfield 26	com/locationDao:rs	Ljava/sql/ResultSet;
    //   192: ldc -64
    //   194: invokeinterface 84 2 0
    //   199: invokevirtual 194	com/locationBean:setAlt	(Ljava/lang/String;)V
    //   202: aload_1
    //   203: aload_0
    //   204: getfield 26	com/locationDao:rs	Ljava/sql/ResultSet;
    //   207: ldc -78
    //   209: invokeinterface 84 2 0
    //   214: invokevirtual 179	com/locationBean:setLname	(Ljava/lang/String;)V
    //   217: aload_1
    //   218: aload_0
    //   219: getfield 26	com/locationDao:rs	Ljava/sql/ResultSet;
    //   222: ldc -28
    //   224: invokeinterface 84 2 0
    //   229: invokevirtual 230	com/locationBean:setAddress	(Ljava/lang/String;)V
    //   232: aload_1
    //   233: aload_0
    //   234: getfield 26	com/locationDao:rs	Ljava/sql/ResultSet;
    //   237: ldc -23
    //   239: invokeinterface 72 2 0
    //   244: invokevirtual 235	com/locationBean:setDatafreq	(I)V
    //   247: aload_1
    //   248: aload_0
    //   249: getfield 26	com/locationDao:rs	Ljava/sql/ResultSet;
    //   252: ldc -18
    //   254: invokeinterface 72 2 0
    //   259: invokevirtual 240	com/locationBean:setCommfreq	(I)V
    //   262: aload_1
    //   263: aload_0
    //   264: getfield 26	com/locationDao:rs	Ljava/sql/ResultSet;
    //   267: ldc -13
    //   269: invokeinterface 84 2 0
    //   274: invokevirtual 245	com/locationBean:setStn_sim	(Ljava/lang/String;)V
    //   277: aload_1
    //   278: aload_0
    //   279: getfield 26	com/locationDao:rs	Ljava/sql/ResultSet;
    //   282: ldc -8
    //   284: invokeinterface 84 2 0
    //   289: invokevirtual 250	com/locationBean:setSrv_sim	(Ljava/lang/String;)V
    //   292: aload_1
    //   293: aload_0
    //   294: getfield 26	com/locationDao:rs	Ljava/sql/ResultSet;
    //   297: ldc -3
    //   299: invokeinterface 84 2 0
    //   304: invokevirtual 255	com/locationBean:setSrv_sim_bkp1	(Ljava/lang/String;)V
    //   307: aload_1
    //   308: aload_0
    //   309: getfield 26	com/locationDao:rs	Ljava/sql/ResultSet;
    //   312: ldc_w 258
    //   315: invokeinterface 84 2 0
    //   320: invokevirtual 260	com/locationBean:setSrv_sim_bkp2	(Ljava/lang/String;)V
    //   323: aload_1
    //   324: aload_0
    //   325: getfield 26	com/locationDao:rs	Ljava/sql/ResultSet;
    //   328: ldc_w 263
    //   331: invokeinterface 84 2 0
    //   336: invokevirtual 265	com/locationBean:setWindavg	(Ljava/lang/String;)V
    //   339: aload_1
    //   340: aload_0
    //   341: getfield 26	com/locationDao:rs	Ljava/sql/ResultSet;
    //   344: ldc_w 268
    //   347: invokeinterface 84 2 0
    //   352: invokevirtual 270	com/locationBean:setCalibrationrain	(Ljava/lang/String;)V
    //   355: aload_1
    //   356: aload_0
    //   357: getfield 26	com/locationDao:rs	Ljava/sql/ResultSet;
    //   360: ldc_w 273
    //   363: invokeinterface 84 2 0
    //   368: invokevirtual 275	com/locationBean:setCalibrationwind	(Ljava/lang/String;)V
    //   371: aload_1
    //   372: aload_0
    //   373: getfield 26	com/locationDao:rs	Ljava/sql/ResultSet;
    //   376: ldc_w 278
    //   379: invokeinterface 84 2 0
    //   384: invokevirtual 280	com/locationBean:setCperson	(Ljava/lang/String;)V
    //   387: aload_1
    //   388: aload_0
    //   389: getfield 26	com/locationDao:rs	Ljava/sql/ResultSet;
    //   392: ldc_w 283
    //   395: invokeinterface 84 2 0
    //   400: invokevirtual 285	com/locationBean:setCphone	(Ljava/lang/String;)V
    //   403: aload_1
    //   404: aload_0
    //   405: getfield 26	com/locationDao:rs	Ljava/sql/ResultSet;
    //   408: ldc_w 288
    //   411: invokeinterface 84 2 0
    //   416: invokevirtual 290	com/locationBean:setCemail	(Ljava/lang/String;)V
    //   419: aload_1
    //   420: aload_0
    //   421: getfield 26	com/locationDao:rs	Ljava/sql/ResultSet;
    //   424: ldc_w 293
    //   427: invokeinterface 84 2 0
    //   432: invokevirtual 295	com/locationBean:setOperator	(Ljava/lang/String;)V
    //   435: aload_1
    //   436: aload_0
    //   437: getfield 26	com/locationDao:rs	Ljava/sql/ResultSet;
    //   440: ldc_w 298
    //   443: invokeinterface 84 2 0
    //   448: invokevirtual 300	com/locationBean:setLsignal	(Ljava/lang/String;)V
    //   451: goto +66 -> 517
    //   454: astore_2
    //   455: aload_2
    //   456: invokevirtual 105	java/sql/SQLException:printStackTrace	()V
    //   459: aload_0
    //   460: getfield 30	com/locationDao:stmt	Ljava/sql/Statement;
    //   463: ifnull +80 -> 543
    //   466: aload_0
    //   467: getfield 30	com/locationDao:stmt	Ljava/sql/Statement;
    //   470: invokeinterface 110 1 0
    //   475: goto +68 -> 543
    //   478: astore 4
    //   480: aload 4
    //   482: invokevirtual 105	java/sql/SQLException:printStackTrace	()V
    //   485: goto +58 -> 543
    //   488: astore_3
    //   489: aload_0
    //   490: getfield 30	com/locationDao:stmt	Ljava/sql/Statement;
    //   493: ifnull +22 -> 515
    //   496: aload_0
    //   497: getfield 30	com/locationDao:stmt	Ljava/sql/Statement;
    //   500: invokeinterface 110 1 0
    //   505: goto +10 -> 515
    //   508: astore 4
    //   510: aload 4
    //   512: invokevirtual 105	java/sql/SQLException:printStackTrace	()V
    //   515: aload_3
    //   516: athrow
    //   517: aload_0
    //   518: getfield 30	com/locationDao:stmt	Ljava/sql/Statement;
    //   521: ifnull +22 -> 543
    //   524: aload_0
    //   525: getfield 30	com/locationDao:stmt	Ljava/sql/Statement;
    //   528: invokeinterface 110 1 0
    //   533: goto +10 -> 543
    //   536: astore 4
    //   538: aload 4
    //   540: invokevirtual 105	java/sql/SQLException:printStackTrace	()V
    //   543: return
    // Line number table:
    //   Java source line #230	-> byte code offset #0
    //   Java source line #234	-> byte code offset #6
    //   Java source line #235	-> byte code offset #13
    //   Java source line #236	-> byte code offset #30
    //   Java source line #238	-> byte code offset #44
    //   Java source line #239	-> byte code offset #57
    //   Java source line #240	-> byte code offset #67
    //   Java source line #241	-> byte code offset #82
    //   Java source line #242	-> byte code offset #97
    //   Java source line #243	-> byte code offset #112
    //   Java source line #244	-> byte code offset #127
    //   Java source line #245	-> byte code offset #142
    //   Java source line #246	-> byte code offset #157
    //   Java source line #247	-> byte code offset #172
    //   Java source line #248	-> byte code offset #187
    //   Java source line #249	-> byte code offset #202
    //   Java source line #250	-> byte code offset #217
    //   Java source line #251	-> byte code offset #232
    //   Java source line #252	-> byte code offset #247
    //   Java source line #253	-> byte code offset #262
    //   Java source line #254	-> byte code offset #277
    //   Java source line #255	-> byte code offset #292
    //   Java source line #256	-> byte code offset #307
    //   Java source line #257	-> byte code offset #323
    //   Java source line #258	-> byte code offset #339
    //   Java source line #259	-> byte code offset #355
    //   Java source line #260	-> byte code offset #371
    //   Java source line #261	-> byte code offset #387
    //   Java source line #262	-> byte code offset #403
    //   Java source line #263	-> byte code offset #419
    //   Java source line #264	-> byte code offset #435
    //   Java source line #266	-> byte code offset #451
    //   Java source line #270	-> byte code offset #459
    //   Java source line #271	-> byte code offset #466
    //   Java source line #272	-> byte code offset #475
    //   Java source line #273	-> byte code offset #480
    //   Java source line #268	-> byte code offset #488
    //   Java source line #270	-> byte code offset #489
    //   Java source line #271	-> byte code offset #496
    //   Java source line #272	-> byte code offset #505
    //   Java source line #273	-> byte code offset #510
    //   Java source line #275	-> byte code offset #515
    //   Java source line #270	-> byte code offset #517
    //   Java source line #271	-> byte code offset #524
    //   Java source line #272	-> byte code offset #533
    //   Java source line #273	-> byte code offset #538
    //   Java source line #277	-> byte code offset #543
    // Local variable table:
    //   start	length	slot	name	signature
    //   0	544	0	this	locationDao
    //   0	544	1	station	locationBean
    //   454	2	2	e	java.sql.SQLException
    //   488	28	3	localObject	Object
    //   478	3	4	e	java.sql.SQLException
    //   508	3	4	e	java.sql.SQLException
    //   536	3	4	e	java.sql.SQLException
    // Exception table:
    //   from	to	target	type
    //   0	451	454	java/sql/SQLException
    //   459	475	478	java/sql/SQLException
    //   0	459	488	finally
    //   489	505	508	java/sql/SQLException
    //   517	533	536	java/sql/SQLException
  }
  
  /* Error */
  public void addstation(locationBean locBean)
  {
    // Byte code:
    //   0: aload_0
    //   1: ldc_w 305
    //   4: putfield 34	com/locationDao:query	Ljava/lang/String;
    //   7: aload_0
    //   8: invokestatic 49	com/ConnectionProvider:getCon	()Ljava/sql/Connection;
    //   11: putfield 22	com/locationDao:connection	Ljava/sql/Connection;
    //   14: aload_0
    //   15: aload_0
    //   16: getfield 22	com/locationDao:connection	Ljava/sql/Connection;
    //   19: aload_0
    //   20: getfield 34	com/locationDao:query	Ljava/lang/String;
    //   23: invokeinterface 127 2 0
    //   28: putfield 24	com/locationDao:ptmt	Ljava/sql/PreparedStatement;
    //   31: aload_0
    //   32: getfield 24	com/locationDao:ptmt	Ljava/sql/PreparedStatement;
    //   35: iconst_1
    //   36: aload_1
    //   37: invokevirtual 307	com/locationBean:getLname	()Ljava/lang/String;
    //   40: invokeinterface 311 3 0
    //   45: aload_0
    //   46: getfield 24	com/locationDao:ptmt	Ljava/sql/PreparedStatement;
    //   49: iconst_2
    //   50: aload_1
    //   51: invokevirtual 315	com/locationBean:getAddress	()Ljava/lang/String;
    //   54: invokeinterface 311 3 0
    //   59: aload_0
    //   60: getfield 24	com/locationDao:ptmt	Ljava/sql/PreparedStatement;
    //   63: iconst_3
    //   64: aload_1
    //   65: invokevirtual 318	com/locationBean:getLat	()Ljava/lang/String;
    //   68: invokestatic 321	java/lang/Double:parseDouble	(Ljava/lang/String;)D
    //   71: invokeinterface 327 4 0
    //   76: aload_0
    //   77: getfield 24	com/locationDao:ptmt	Ljava/sql/PreparedStatement;
    //   80: iconst_4
    //   81: aload_1
    //   82: invokevirtual 331	com/locationBean:getLon	()Ljava/lang/String;
    //   85: invokestatic 321	java/lang/Double:parseDouble	(Ljava/lang/String;)D
    //   88: invokeinterface 327 4 0
    //   93: aload_0
    //   94: getfield 24	com/locationDao:ptmt	Ljava/sql/PreparedStatement;
    //   97: iconst_5
    //   98: aload_1
    //   99: invokevirtual 334	com/locationBean:getAlt	()Ljava/lang/String;
    //   102: invokestatic 321	java/lang/Double:parseDouble	(Ljava/lang/String;)D
    //   105: invokeinterface 327 4 0
    //   110: aload_0
    //   111: getfield 24	com/locationDao:ptmt	Ljava/sql/PreparedStatement;
    //   114: bipush 6
    //   116: aload_1
    //   117: invokevirtual 337	com/locationBean:getStateid	()I
    //   120: invokeinterface 131 3 0
    //   125: aload_0
    //   126: getfield 24	com/locationDao:ptmt	Ljava/sql/PreparedStatement;
    //   129: bipush 7
    //   131: aload_1
    //   132: invokevirtual 340	com/locationBean:getDistrict_id	()I
    //   135: invokeinterface 131 3 0
    //   140: aload_0
    //   141: getfield 24	com/locationDao:ptmt	Ljava/sql/PreparedStatement;
    //   144: bipush 8
    //   146: aload_1
    //   147: invokevirtual 343	com/locationBean:getCounty_id	()I
    //   150: invokeinterface 131 3 0
    //   155: aload_0
    //   156: getfield 24	com/locationDao:ptmt	Ljava/sql/PreparedStatement;
    //   159: bipush 9
    //   161: aload_1
    //   162: invokevirtual 346	com/locationBean:getDatafreq	()I
    //   165: invokeinterface 131 3 0
    //   170: aload_0
    //   171: getfield 24	com/locationDao:ptmt	Ljava/sql/PreparedStatement;
    //   174: bipush 10
    //   176: aload_1
    //   177: invokevirtual 349	com/locationBean:getCommfreq	()I
    //   180: invokeinterface 131 3 0
    //   185: aload_0
    //   186: getfield 24	com/locationDao:ptmt	Ljava/sql/PreparedStatement;
    //   189: bipush 11
    //   191: aload_1
    //   192: invokevirtual 352	com/locationBean:getStn_sim	()Ljava/lang/String;
    //   195: invokeinterface 311 3 0
    //   200: aload_0
    //   201: getfield 24	com/locationDao:ptmt	Ljava/sql/PreparedStatement;
    //   204: bipush 12
    //   206: aload_1
    //   207: invokevirtual 355	com/locationBean:getSrv_sim	()Ljava/lang/String;
    //   210: invokeinterface 311 3 0
    //   215: aload_0
    //   216: getfield 24	com/locationDao:ptmt	Ljava/sql/PreparedStatement;
    //   219: bipush 13
    //   221: aload_1
    //   222: invokevirtual 358	com/locationBean:getSrv_sim_bkp1	()Ljava/lang/String;
    //   225: invokeinterface 311 3 0
    //   230: aload_0
    //   231: getfield 24	com/locationDao:ptmt	Ljava/sql/PreparedStatement;
    //   234: bipush 14
    //   236: aload_1
    //   237: invokevirtual 361	com/locationBean:getSrv_sim_bkp2	()Ljava/lang/String;
    //   240: invokeinterface 311 3 0
    //   245: aload_0
    //   246: getfield 24	com/locationDao:ptmt	Ljava/sql/PreparedStatement;
    //   249: bipush 15
    //   251: aload_1
    //   252: invokevirtual 364	com/locationBean:getCalibrationrain	()Ljava/lang/String;
    //   255: invokeinterface 311 3 0
    //   260: aload_0
    //   261: getfield 24	com/locationDao:ptmt	Ljava/sql/PreparedStatement;
    //   264: bipush 16
    //   266: aload_1
    //   267: invokevirtual 367	com/locationBean:getCalibrationwind	()Ljava/lang/String;
    //   270: invokeinterface 311 3 0
    //   275: aload_0
    //   276: getfield 24	com/locationDao:ptmt	Ljava/sql/PreparedStatement;
    //   279: bipush 17
    //   281: aload_1
    //   282: invokevirtual 370	com/locationBean:getCalibrationwinddirection	()Ljava/lang/String;
    //   285: invokeinterface 311 3 0
    //   290: aload_0
    //   291: getfield 24	com/locationDao:ptmt	Ljava/sql/PreparedStatement;
    //   294: bipush 18
    //   296: aload_1
    //   297: invokevirtual 219	com/locationBean:getLocation_id	()I
    //   300: invokeinterface 131 3 0
    //   305: aload_0
    //   306: getfield 24	com/locationDao:ptmt	Ljava/sql/PreparedStatement;
    //   309: invokeinterface 205 1 0
    //   314: pop
    //   315: goto +86 -> 401
    //   318: astore_2
    //   319: aload_2
    //   320: invokevirtual 105	java/sql/SQLException:printStackTrace	()V
    //   323: aload_0
    //   324: getfield 24	com/locationDao:ptmt	Ljava/sql/PreparedStatement;
    //   327: ifnull +110 -> 437
    //   330: aload_0
    //   331: getfield 24	com/locationDao:ptmt	Ljava/sql/PreparedStatement;
    //   334: invokeinterface 209 1 0
    //   339: goto +98 -> 437
    //   342: astore 4
    //   344: aload 4
    //   346: invokevirtual 105	java/sql/SQLException:printStackTrace	()V
    //   349: goto +88 -> 437
    //   352: astore 4
    //   354: aload 4
    //   356: invokevirtual 210	java/lang/Exception:printStackTrace	()V
    //   359: goto +78 -> 437
    //   362: astore_3
    //   363: aload_0
    //   364: getfield 24	com/locationDao:ptmt	Ljava/sql/PreparedStatement;
    //   367: ifnull +32 -> 399
    //   370: aload_0
    //   371: getfield 24	com/locationDao:ptmt	Ljava/sql/PreparedStatement;
    //   374: invokeinterface 209 1 0
    //   379: goto +20 -> 399
    //   382: astore 4
    //   384: aload 4
    //   386: invokevirtual 105	java/sql/SQLException:printStackTrace	()V
    //   389: goto +10 -> 399
    //   392: astore 4
    //   394: aload 4
    //   396: invokevirtual 210	java/lang/Exception:printStackTrace	()V
    //   399: aload_3
    //   400: athrow
    //   401: aload_0
    //   402: getfield 24	com/locationDao:ptmt	Ljava/sql/PreparedStatement;
    //   405: ifnull +32 -> 437
    //   408: aload_0
    //   409: getfield 24	com/locationDao:ptmt	Ljava/sql/PreparedStatement;
    //   412: invokeinterface 209 1 0
    //   417: goto +20 -> 437
    //   420: astore 4
    //   422: aload 4
    //   424: invokevirtual 105	java/sql/SQLException:printStackTrace	()V
    //   427: goto +10 -> 437
    //   430: astore 4
    //   432: aload 4
    //   434: invokevirtual 210	java/lang/Exception:printStackTrace	()V
    //   437: return
    // Line number table:
    //   Java source line #284	-> byte code offset #0
    //   Java source line #287	-> byte code offset #7
    //   Java source line #288	-> byte code offset #14
    //   Java source line #289	-> byte code offset #31
    //   Java source line #290	-> byte code offset #45
    //   Java source line #291	-> byte code offset #59
    //   Java source line #292	-> byte code offset #76
    //   Java source line #293	-> byte code offset #93
    //   Java source line #294	-> byte code offset #110
    //   Java source line #295	-> byte code offset #125
    //   Java source line #296	-> byte code offset #140
    //   Java source line #298	-> byte code offset #155
    //   Java source line #299	-> byte code offset #170
    //   Java source line #300	-> byte code offset #185
    //   Java source line #301	-> byte code offset #200
    //   Java source line #302	-> byte code offset #215
    //   Java source line #303	-> byte code offset #230
    //   Java source line #304	-> byte code offset #245
    //   Java source line #305	-> byte code offset #260
    //   Java source line #306	-> byte code offset #275
    //   Java source line #307	-> byte code offset #290
    //   Java source line #309	-> byte code offset #305
    //   Java source line #310	-> byte code offset #315
    //   Java source line #311	-> byte code offset #319
    //   Java source line #314	-> byte code offset #323
    //   Java source line #315	-> byte code offset #330
    //   Java source line #316	-> byte code offset #339
    //   Java source line #317	-> byte code offset #344
    //   Java source line #318	-> byte code offset #352
    //   Java source line #319	-> byte code offset #354
    //   Java source line #312	-> byte code offset #362
    //   Java source line #314	-> byte code offset #363
    //   Java source line #315	-> byte code offset #370
    //   Java source line #316	-> byte code offset #379
    //   Java source line #317	-> byte code offset #384
    //   Java source line #318	-> byte code offset #392
    //   Java source line #319	-> byte code offset #394
    //   Java source line #322	-> byte code offset #399
    //   Java source line #314	-> byte code offset #401
    //   Java source line #315	-> byte code offset #408
    //   Java source line #316	-> byte code offset #417
    //   Java source line #317	-> byte code offset #422
    //   Java source line #318	-> byte code offset #430
    //   Java source line #319	-> byte code offset #432
    //   Java source line #324	-> byte code offset #437
    // Local variable table:
    //   start	length	slot	name	signature
    //   0	438	0	this	locationDao
    //   0	438	1	locBean	locationBean
    //   318	2	2	e	java.sql.SQLException
    //   362	38	3	localObject	Object
    //   342	3	4	e	java.sql.SQLException
    //   352	3	4	e	Exception
    //   382	3	4	e	java.sql.SQLException
    //   392	3	4	e	Exception
    //   420	3	4	e	java.sql.SQLException
    //   430	3	4	e	Exception
    // Exception table:
    //   from	to	target	type
    //   0	315	318	java/sql/SQLException
    //   323	339	342	java/sql/SQLException
    //   323	339	352	java/lang/Exception
    //   0	323	362	finally
    //   363	379	382	java/sql/SQLException
    //   363	379	392	java/lang/Exception
    //   401	417	420	java/sql/SQLException
    //   401	417	430	java/lang/Exception
  }
  
  /* Error */
  public void updatestation(locationBean locBean)
  {
    // Byte code:
    //   0: aload_0
    //   1: ldc_w 375
    //   4: putfield 34	com/locationDao:query	Ljava/lang/String;
    //   7: aload_0
    //   8: invokestatic 49	com/ConnectionProvider:getCon	()Ljava/sql/Connection;
    //   11: putfield 22	com/locationDao:connection	Ljava/sql/Connection;
    //   14: aload_0
    //   15: aload_0
    //   16: getfield 22	com/locationDao:connection	Ljava/sql/Connection;
    //   19: aload_0
    //   20: getfield 34	com/locationDao:query	Ljava/lang/String;
    //   23: invokeinterface 127 2 0
    //   28: putfield 24	com/locationDao:ptmt	Ljava/sql/PreparedStatement;
    //   31: aload_0
    //   32: getfield 24	com/locationDao:ptmt	Ljava/sql/PreparedStatement;
    //   35: iconst_1
    //   36: aload_1
    //   37: invokevirtual 307	com/locationBean:getLname	()Ljava/lang/String;
    //   40: invokeinterface 311 3 0
    //   45: aload_0
    //   46: getfield 24	com/locationDao:ptmt	Ljava/sql/PreparedStatement;
    //   49: iconst_2
    //   50: aload_1
    //   51: invokevirtual 315	com/locationBean:getAddress	()Ljava/lang/String;
    //   54: invokeinterface 311 3 0
    //   59: aload_0
    //   60: getfield 24	com/locationDao:ptmt	Ljava/sql/PreparedStatement;
    //   63: iconst_3
    //   64: aload_1
    //   65: invokevirtual 318	com/locationBean:getLat	()Ljava/lang/String;
    //   68: invokestatic 321	java/lang/Double:parseDouble	(Ljava/lang/String;)D
    //   71: invokeinterface 327 4 0
    //   76: aload_0
    //   77: getfield 24	com/locationDao:ptmt	Ljava/sql/PreparedStatement;
    //   80: iconst_4
    //   81: aload_1
    //   82: invokevirtual 331	com/locationBean:getLon	()Ljava/lang/String;
    //   85: invokestatic 321	java/lang/Double:parseDouble	(Ljava/lang/String;)D
    //   88: invokeinterface 327 4 0
    //   93: aload_0
    //   94: getfield 24	com/locationDao:ptmt	Ljava/sql/PreparedStatement;
    //   97: iconst_5
    //   98: aload_1
    //   99: invokevirtual 334	com/locationBean:getAlt	()Ljava/lang/String;
    //   102: invokestatic 321	java/lang/Double:parseDouble	(Ljava/lang/String;)D
    //   105: invokeinterface 327 4 0
    //   110: aload_0
    //   111: getfield 24	com/locationDao:ptmt	Ljava/sql/PreparedStatement;
    //   114: bipush 6
    //   116: aload_1
    //   117: invokevirtual 337	com/locationBean:getStateid	()I
    //   120: invokeinterface 131 3 0
    //   125: aload_0
    //   126: getfield 24	com/locationDao:ptmt	Ljava/sql/PreparedStatement;
    //   129: bipush 7
    //   131: aload_1
    //   132: invokevirtual 340	com/locationBean:getDistrict_id	()I
    //   135: invokeinterface 131 3 0
    //   140: aload_0
    //   141: getfield 24	com/locationDao:ptmt	Ljava/sql/PreparedStatement;
    //   144: bipush 8
    //   146: aload_1
    //   147: invokevirtual 343	com/locationBean:getCounty_id	()I
    //   150: invokeinterface 131 3 0
    //   155: aload_0
    //   156: getfield 24	com/locationDao:ptmt	Ljava/sql/PreparedStatement;
    //   159: bipush 9
    //   161: aload_1
    //   162: invokevirtual 346	com/locationBean:getDatafreq	()I
    //   165: invokeinterface 131 3 0
    //   170: aload_0
    //   171: getfield 24	com/locationDao:ptmt	Ljava/sql/PreparedStatement;
    //   174: bipush 10
    //   176: aload_1
    //   177: invokevirtual 349	com/locationBean:getCommfreq	()I
    //   180: invokeinterface 131 3 0
    //   185: aload_0
    //   186: getfield 24	com/locationDao:ptmt	Ljava/sql/PreparedStatement;
    //   189: bipush 11
    //   191: aload_1
    //   192: invokevirtual 352	com/locationBean:getStn_sim	()Ljava/lang/String;
    //   195: invokeinterface 311 3 0
    //   200: aload_0
    //   201: getfield 24	com/locationDao:ptmt	Ljava/sql/PreparedStatement;
    //   204: bipush 12
    //   206: aload_1
    //   207: invokevirtual 355	com/locationBean:getSrv_sim	()Ljava/lang/String;
    //   210: invokeinterface 311 3 0
    //   215: aload_0
    //   216: getfield 24	com/locationDao:ptmt	Ljava/sql/PreparedStatement;
    //   219: bipush 13
    //   221: aload_1
    //   222: invokevirtual 358	com/locationBean:getSrv_sim_bkp1	()Ljava/lang/String;
    //   225: invokeinterface 311 3 0
    //   230: aload_0
    //   231: getfield 24	com/locationDao:ptmt	Ljava/sql/PreparedStatement;
    //   234: bipush 14
    //   236: aload_1
    //   237: invokevirtual 361	com/locationBean:getSrv_sim_bkp2	()Ljava/lang/String;
    //   240: invokeinterface 311 3 0
    //   245: aload_0
    //   246: getfield 24	com/locationDao:ptmt	Ljava/sql/PreparedStatement;
    //   249: bipush 15
    //   251: aload_1
    //   252: invokevirtual 364	com/locationBean:getCalibrationrain	()Ljava/lang/String;
    //   255: invokeinterface 311 3 0
    //   260: aload_0
    //   261: getfield 24	com/locationDao:ptmt	Ljava/sql/PreparedStatement;
    //   264: bipush 16
    //   266: aload_1
    //   267: invokevirtual 367	com/locationBean:getCalibrationwind	()Ljava/lang/String;
    //   270: invokeinterface 311 3 0
    //   275: aload_0
    //   276: getfield 24	com/locationDao:ptmt	Ljava/sql/PreparedStatement;
    //   279: bipush 17
    //   281: aload_1
    //   282: invokevirtual 370	com/locationBean:getCalibrationwinddirection	()Ljava/lang/String;
    //   285: invokeinterface 311 3 0
    //   290: aload_0
    //   291: getfield 24	com/locationDao:ptmt	Ljava/sql/PreparedStatement;
    //   294: bipush 18
    //   296: aload_1
    //   297: invokevirtual 219	com/locationBean:getLocation_id	()I
    //   300: invokeinterface 131 3 0
    //   305: aload_0
    //   306: getfield 24	com/locationDao:ptmt	Ljava/sql/PreparedStatement;
    //   309: invokeinterface 205 1 0
    //   314: pop
    //   315: goto +86 -> 401
    //   318: astore_2
    //   319: aload_2
    //   320: invokevirtual 105	java/sql/SQLException:printStackTrace	()V
    //   323: aload_0
    //   324: getfield 24	com/locationDao:ptmt	Ljava/sql/PreparedStatement;
    //   327: ifnull +110 -> 437
    //   330: aload_0
    //   331: getfield 24	com/locationDao:ptmt	Ljava/sql/PreparedStatement;
    //   334: invokeinterface 209 1 0
    //   339: goto +98 -> 437
    //   342: astore 4
    //   344: aload 4
    //   346: invokevirtual 105	java/sql/SQLException:printStackTrace	()V
    //   349: goto +88 -> 437
    //   352: astore 4
    //   354: aload 4
    //   356: invokevirtual 210	java/lang/Exception:printStackTrace	()V
    //   359: goto +78 -> 437
    //   362: astore_3
    //   363: aload_0
    //   364: getfield 24	com/locationDao:ptmt	Ljava/sql/PreparedStatement;
    //   367: ifnull +32 -> 399
    //   370: aload_0
    //   371: getfield 24	com/locationDao:ptmt	Ljava/sql/PreparedStatement;
    //   374: invokeinterface 209 1 0
    //   379: goto +20 -> 399
    //   382: astore 4
    //   384: aload 4
    //   386: invokevirtual 105	java/sql/SQLException:printStackTrace	()V
    //   389: goto +10 -> 399
    //   392: astore 4
    //   394: aload 4
    //   396: invokevirtual 210	java/lang/Exception:printStackTrace	()V
    //   399: aload_3
    //   400: athrow
    //   401: aload_0
    //   402: getfield 24	com/locationDao:ptmt	Ljava/sql/PreparedStatement;
    //   405: ifnull +32 -> 437
    //   408: aload_0
    //   409: getfield 24	com/locationDao:ptmt	Ljava/sql/PreparedStatement;
    //   412: invokeinterface 209 1 0
    //   417: goto +20 -> 437
    //   420: astore 4
    //   422: aload 4
    //   424: invokevirtual 105	java/sql/SQLException:printStackTrace	()V
    //   427: goto +10 -> 437
    //   430: astore 4
    //   432: aload 4
    //   434: invokevirtual 210	java/lang/Exception:printStackTrace	()V
    //   437: return
    // Line number table:
    //   Java source line #329	-> byte code offset #0
    //   Java source line #333	-> byte code offset #7
    //   Java source line #334	-> byte code offset #14
    //   Java source line #336	-> byte code offset #31
    //   Java source line #337	-> byte code offset #45
    //   Java source line #338	-> byte code offset #59
    //   Java source line #339	-> byte code offset #76
    //   Java source line #340	-> byte code offset #93
    //   Java source line #341	-> byte code offset #110
    //   Java source line #342	-> byte code offset #125
    //   Java source line #343	-> byte code offset #140
    //   Java source line #345	-> byte code offset #155
    //   Java source line #346	-> byte code offset #170
    //   Java source line #347	-> byte code offset #185
    //   Java source line #348	-> byte code offset #200
    //   Java source line #349	-> byte code offset #215
    //   Java source line #350	-> byte code offset #230
    //   Java source line #351	-> byte code offset #245
    //   Java source line #352	-> byte code offset #260
    //   Java source line #353	-> byte code offset #275
    //   Java source line #354	-> byte code offset #290
    //   Java source line #357	-> byte code offset #305
    //   Java source line #358	-> byte code offset #315
    //   Java source line #359	-> byte code offset #319
    //   Java source line #362	-> byte code offset #323
    //   Java source line #363	-> byte code offset #330
    //   Java source line #364	-> byte code offset #339
    //   Java source line #365	-> byte code offset #344
    //   Java source line #366	-> byte code offset #352
    //   Java source line #367	-> byte code offset #354
    //   Java source line #360	-> byte code offset #362
    //   Java source line #362	-> byte code offset #363
    //   Java source line #363	-> byte code offset #370
    //   Java source line #364	-> byte code offset #379
    //   Java source line #365	-> byte code offset #384
    //   Java source line #366	-> byte code offset #392
    //   Java source line #367	-> byte code offset #394
    //   Java source line #370	-> byte code offset #399
    //   Java source line #362	-> byte code offset #401
    //   Java source line #363	-> byte code offset #408
    //   Java source line #364	-> byte code offset #417
    //   Java source line #365	-> byte code offset #422
    //   Java source line #366	-> byte code offset #430
    //   Java source line #367	-> byte code offset #432
    //   Java source line #372	-> byte code offset #437
    // Local variable table:
    //   start	length	slot	name	signature
    //   0	438	0	this	locationDao
    //   0	438	1	locBean	locationBean
    //   318	2	2	e	java.sql.SQLException
    //   362	38	3	localObject	Object
    //   342	3	4	e	java.sql.SQLException
    //   352	3	4	e	Exception
    //   382	3	4	e	java.sql.SQLException
    //   392	3	4	e	Exception
    //   420	3	4	e	java.sql.SQLException
    //   430	3	4	e	Exception
    // Exception table:
    //   from	to	target	type
    //   0	315	318	java/sql/SQLException
    //   323	339	342	java/sql/SQLException
    //   323	339	352	java/lang/Exception
    //   0	323	362	finally
    //   363	379	382	java/sql/SQLException
    //   363	379	392	java/lang/Exception
    //   401	417	420	java/sql/SQLException
    //   401	417	430	java/lang/Exception
  }
  
  /* Error */
  public void addCounty(String name, int Did)
  {
    // Byte code:
    //   0: aload_0
    //   1: ldc_w 379
    //   4: putfield 34	com/locationDao:query	Ljava/lang/String;
    //   7: aload_0
    //   8: invokestatic 49	com/ConnectionProvider:getCon	()Ljava/sql/Connection;
    //   11: putfield 22	com/locationDao:connection	Ljava/sql/Connection;
    //   14: aload_0
    //   15: aload_0
    //   16: getfield 22	com/locationDao:connection	Ljava/sql/Connection;
    //   19: aload_0
    //   20: getfield 34	com/locationDao:query	Ljava/lang/String;
    //   23: invokeinterface 127 2 0
    //   28: putfield 24	com/locationDao:ptmt	Ljava/sql/PreparedStatement;
    //   31: aload_0
    //   32: getfield 24	com/locationDao:ptmt	Ljava/sql/PreparedStatement;
    //   35: iconst_1
    //   36: aload_1
    //   37: invokeinterface 311 3 0
    //   42: aload_0
    //   43: getfield 24	com/locationDao:ptmt	Ljava/sql/PreparedStatement;
    //   46: iconst_2
    //   47: iload_2
    //   48: invokeinterface 131 3 0
    //   53: aload_0
    //   54: getfield 24	com/locationDao:ptmt	Ljava/sql/PreparedStatement;
    //   57: invokeinterface 205 1 0
    //   62: pop
    //   63: goto +88 -> 151
    //   66: astore_3
    //   67: aload_3
    //   68: invokevirtual 105	java/sql/SQLException:printStackTrace	()V
    //   71: aload_0
    //   72: getfield 24	com/locationDao:ptmt	Ljava/sql/PreparedStatement;
    //   75: ifnull +112 -> 187
    //   78: aload_0
    //   79: getfield 24	com/locationDao:ptmt	Ljava/sql/PreparedStatement;
    //   82: invokeinterface 209 1 0
    //   87: goto +100 -> 187
    //   90: astore 5
    //   92: aload 5
    //   94: invokevirtual 105	java/sql/SQLException:printStackTrace	()V
    //   97: goto +90 -> 187
    //   100: astore 5
    //   102: aload 5
    //   104: invokevirtual 210	java/lang/Exception:printStackTrace	()V
    //   107: goto +80 -> 187
    //   110: astore 4
    //   112: aload_0
    //   113: getfield 24	com/locationDao:ptmt	Ljava/sql/PreparedStatement;
    //   116: ifnull +32 -> 148
    //   119: aload_0
    //   120: getfield 24	com/locationDao:ptmt	Ljava/sql/PreparedStatement;
    //   123: invokeinterface 209 1 0
    //   128: goto +20 -> 148
    //   131: astore 5
    //   133: aload 5
    //   135: invokevirtual 105	java/sql/SQLException:printStackTrace	()V
    //   138: goto +10 -> 148
    //   141: astore 5
    //   143: aload 5
    //   145: invokevirtual 210	java/lang/Exception:printStackTrace	()V
    //   148: aload 4
    //   150: athrow
    //   151: aload_0
    //   152: getfield 24	com/locationDao:ptmt	Ljava/sql/PreparedStatement;
    //   155: ifnull +32 -> 187
    //   158: aload_0
    //   159: getfield 24	com/locationDao:ptmt	Ljava/sql/PreparedStatement;
    //   162: invokeinterface 209 1 0
    //   167: goto +20 -> 187
    //   170: astore 5
    //   172: aload 5
    //   174: invokevirtual 105	java/sql/SQLException:printStackTrace	()V
    //   177: goto +10 -> 187
    //   180: astore 5
    //   182: aload 5
    //   184: invokevirtual 210	java/lang/Exception:printStackTrace	()V
    //   187: return
    // Line number table:
    //   Java source line #379	-> byte code offset #0
    //   Java source line #380	-> byte code offset #7
    //   Java source line #381	-> byte code offset #14
    //   Java source line #383	-> byte code offset #31
    //   Java source line #384	-> byte code offset #42
    //   Java source line #385	-> byte code offset #53
    //   Java source line #386	-> byte code offset #63
    //   Java source line #387	-> byte code offset #67
    //   Java source line #390	-> byte code offset #71
    //   Java source line #391	-> byte code offset #78
    //   Java source line #392	-> byte code offset #87
    //   Java source line #393	-> byte code offset #92
    //   Java source line #394	-> byte code offset #100
    //   Java source line #395	-> byte code offset #102
    //   Java source line #388	-> byte code offset #110
    //   Java source line #390	-> byte code offset #112
    //   Java source line #391	-> byte code offset #119
    //   Java source line #392	-> byte code offset #128
    //   Java source line #393	-> byte code offset #133
    //   Java source line #394	-> byte code offset #141
    //   Java source line #395	-> byte code offset #143
    //   Java source line #398	-> byte code offset #148
    //   Java source line #390	-> byte code offset #151
    //   Java source line #391	-> byte code offset #158
    //   Java source line #392	-> byte code offset #167
    //   Java source line #393	-> byte code offset #172
    //   Java source line #394	-> byte code offset #180
    //   Java source line #395	-> byte code offset #182
    //   Java source line #400	-> byte code offset #187
    // Local variable table:
    //   start	length	slot	name	signature
    //   0	188	0	this	locationDao
    //   0	188	1	name	String
    //   0	188	2	Did	int
    //   66	2	3	e	java.sql.SQLException
    //   110	39	4	localObject	Object
    //   90	3	5	e	java.sql.SQLException
    //   100	3	5	e	Exception
    //   131	3	5	e	java.sql.SQLException
    //   141	3	5	e	Exception
    //   170	3	5	e	java.sql.SQLException
    //   180	3	5	e	Exception
    // Exception table:
    //   from	to	target	type
    //   0	63	66	java/sql/SQLException
    //   71	87	90	java/sql/SQLException
    //   71	87	100	java/lang/Exception
    //   0	71	110	finally
    //   112	128	131	java/sql/SQLException
    //   112	128	141	java/lang/Exception
    //   151	167	170	java/sql/SQLException
    //   151	167	180	java/lang/Exception
  }
  
  /* Error */
  public java.util.List<locationBean> getMaintCmd()
  {
	  return null;

    // Byte code:
    //   0: aload_0
    //   1: ldc_w 386
    //   4: putfield 34	com/locationDao:query	Ljava/lang/String;
    //   7: new 46	java/util/ArrayList
    //   10: dup
    //   11: invokespecial 48	java/util/ArrayList:<init>	()V
    //   14: astore_1
    //   15: aconst_null
    //   16: astore_2
    //   17: aload_0
    //   18: invokestatic 49	com/ConnectionProvider:getCon	()Ljava/sql/Connection;
    //   21: putfield 22	com/locationDao:connection	Ljava/sql/Connection;
    //   24: aload_0
    //   25: aload_0
    //   26: getfield 22	com/locationDao:connection	Ljava/sql/Connection;
    //   29: invokeinterface 55 1 0
    //   34: putfield 30	com/locationDao:stmt	Ljava/sql/Statement;
    //   37: aload_0
    //   38: aload_0
    //   39: getfield 30	com/locationDao:stmt	Ljava/sql/Statement;
    //   42: aload_0
    //   43: getfield 34	com/locationDao:query	Ljava/lang/String;
    //   46: invokeinterface 61 2 0
    //   51: putfield 26	com/locationDao:rs	Ljava/sql/ResultSet;
    //   54: goto +67 -> 121
    //   57: new 67	com/locationBean
    //   60: dup
    //   61: invokespecial 69	com/locationBean:<init>	()V
    //   64: astore_2
    //   65: aload_2
    //   66: aload_0
    //   67: getfield 26	com/locationDao:rs	Ljava/sql/ResultSet;
    //   70: ldc_w 388
    //   73: invokeinterface 72 2 0
    //   78: invokevirtual 390	com/locationBean:setCmd_id	(I)V
    //   81: aload_2
    //   82: aload_0
    //   83: getfield 26	com/locationDao:rs	Ljava/sql/ResultSet;
    //   86: ldc_w 393
    //   89: invokeinterface 84 2 0
    //   94: invokevirtual 395	com/locationBean:setCmd	(Ljava/lang/String;)V
    //   97: aload_2
    //   98: aload_0
    //   99: getfield 26	com/locationDao:rs	Ljava/sql/ResultSet;
    //   102: ldc_w 398
    //   105: invokeinterface 84 2 0
    //   110: invokevirtual 400	com/locationBean:setCmd_desc	(Ljava/lang/String;)V
    //   113: aload_1
    //   114: aload_2
    //   115: invokeinterface 92 2 0
    //   120: pop
    //   121: aload_0
    //   122: getfield 26	com/locationDao:rs	Ljava/sql/ResultSet;
    //   125: invokeinterface 98 1 0
    //   130: ifne -73 -> 57
    //   133: aload_0
    //   134: getfield 26	com/locationDao:rs	Ljava/sql/ResultSet;
    //   137: invokeinterface 102 1 0
    //   142: goto +68 -> 210
    //   145: astore_3
    //   146: aload_3
    //   147: invokevirtual 105	java/sql/SQLException:printStackTrace	()V
    //   150: aload_0
    //   151: getfield 30	com/locationDao:stmt	Ljava/sql/Statement;
    //   154: ifnull +82 -> 236
    //   157: aload_0
    //   158: getfield 30	com/locationDao:stmt	Ljava/sql/Statement;
    //   161: invokeinterface 110 1 0
    //   166: goto +70 -> 236
    //   169: astore 5
    //   171: aload 5
    //   173: invokevirtual 105	java/sql/SQLException:printStackTrace	()V
    //   176: goto +60 -> 236
    //   179: astore 4
    //   181: aload_0
    //   182: getfield 30	com/locationDao:stmt	Ljava/sql/Statement;
    //   185: ifnull +22 -> 207
    //   188: aload_0
    //   189: getfield 30	com/locationDao:stmt	Ljava/sql/Statement;
    //   192: invokeinterface 110 1 0
    //   197: goto +10 -> 207
    //   200: astore 5
    //   202: aload 5
    //   204: invokevirtual 105	java/sql/SQLException:printStackTrace	()V
    //   207: aload 4
    //   209: athrow
    //   210: aload_0
    //   211: getfield 30	com/locationDao:stmt	Ljava/sql/Statement;
    //   214: ifnull +22 -> 236
    //   217: aload_0
    //   218: getfield 30	com/locationDao:stmt	Ljava/sql/Statement;
    //   221: invokeinterface 110 1 0
    //   226: goto +10 -> 236
    //   229: astore 5
    //   231: aload 5
    //   233: invokevirtual 105	java/sql/SQLException:printStackTrace	()V
    //   236: aload_1
    //   237: areturn
    // Line number table:
    //   Java source line #407	-> byte code offset #0
    //   Java source line #408	-> byte code offset #7
    //   Java source line #409	-> byte code offset #15
    //   Java source line #411	-> byte code offset #17
    //   Java source line #412	-> byte code offset #24
    //   Java source line #413	-> byte code offset #37
    //   Java source line #414	-> byte code offset #54
    //   Java source line #415	-> byte code offset #57
    //   Java source line #416	-> byte code offset #65
    //   Java source line #417	-> byte code offset #81
    //   Java source line #418	-> byte code offset #97
    //   Java source line #419	-> byte code offset #113
    //   Java source line #414	-> byte code offset #121
    //   Java source line #421	-> byte code offset #133
    //   Java source line #423	-> byte code offset #142
    //   Java source line #425	-> byte code offset #150
    //   Java source line #426	-> byte code offset #157
    //   Java source line #424	-> byte code offset #179
    //   Java source line #425	-> byte code offset #181
    //   Java source line #426	-> byte code offset #188
    //   Java source line #427	-> byte code offset #207
    //   Java source line #425	-> byte code offset #210
    //   Java source line #426	-> byte code offset #217
    //   Java source line #428	-> byte code offset #236
    // Local variable table:
    //   start	length	slot	name	signature
    //   0	238	0	this	locationDao
    //   14	223	1	list	java.util.List<locationBean>
    //   16	99	2	location	locationBean
    //   145	2	3	e	java.sql.SQLException
    //   179	29	4	localObject	Object
    //   169	3	5	e	java.sql.SQLException
    //   200	3	5	e	java.sql.SQLException
    //   229	3	5	e	java.sql.SQLException
    // Exception table:
    //   from	to	target	type
    //   17	142	145	java/sql/SQLException
    //   150	166	169	java/sql/SQLException
    //   17	150	179	finally
    //   181	197	200	java/sql/SQLException
    //   210	226	229	java/sql/SQLException
  }
  
  /* Error */
  public void SendMaintCmd(int stationid, int cid)
  {
    // Byte code:
    //   0: aload_0
    //   1: ldc_w 404
    //   4: putfield 34	com/locationDao:query	Ljava/lang/String;
    //   7: aload_0
    //   8: invokestatic 49	com/ConnectionProvider:getCon	()Ljava/sql/Connection;
    //   11: putfield 22	com/locationDao:connection	Ljava/sql/Connection;
    //   14: aload_0
    //   15: aload_0
    //   16: getfield 22	com/locationDao:connection	Ljava/sql/Connection;
    //   19: aload_0
    //   20: getfield 34	com/locationDao:query	Ljava/lang/String;
    //   23: invokeinterface 127 2 0
    //   28: putfield 24	com/locationDao:ptmt	Ljava/sql/PreparedStatement;
    //   31: aload_0
    //   32: getfield 24	com/locationDao:ptmt	Ljava/sql/PreparedStatement;
    //   35: iconst_1
    //   36: iload_2
    //   37: invokeinterface 131 3 0
    //   42: aload_0
    //   43: getfield 24	com/locationDao:ptmt	Ljava/sql/PreparedStatement;
    //   46: iconst_2
    //   47: iload_1
    //   48: invokeinterface 131 3 0
    //   53: aload_0
    //   54: getfield 24	com/locationDao:ptmt	Ljava/sql/PreparedStatement;
    //   57: invokeinterface 205 1 0
    //   62: pop
    //   63: goto +88 -> 151
    //   66: astore_3
    //   67: aload_3
    //   68: invokevirtual 105	java/sql/SQLException:printStackTrace	()V
    //   71: aload_0
    //   72: getfield 24	com/locationDao:ptmt	Ljava/sql/PreparedStatement;
    //   75: ifnull +112 -> 187
    //   78: aload_0
    //   79: getfield 24	com/locationDao:ptmt	Ljava/sql/PreparedStatement;
    //   82: invokeinterface 209 1 0
    //   87: goto +100 -> 187
    //   90: astore 5
    //   92: aload 5
    //   94: invokevirtual 105	java/sql/SQLException:printStackTrace	()V
    //   97: goto +90 -> 187
    //   100: astore 5
    //   102: aload 5
    //   104: invokevirtual 210	java/lang/Exception:printStackTrace	()V
    //   107: goto +80 -> 187
    //   110: astore 4
    //   112: aload_0
    //   113: getfield 24	com/locationDao:ptmt	Ljava/sql/PreparedStatement;
    //   116: ifnull +32 -> 148
    //   119: aload_0
    //   120: getfield 24	com/locationDao:ptmt	Ljava/sql/PreparedStatement;
    //   123: invokeinterface 209 1 0
    //   128: goto +20 -> 148
    //   131: astore 5
    //   133: aload 5
    //   135: invokevirtual 105	java/sql/SQLException:printStackTrace	()V
    //   138: goto +10 -> 148
    //   141: astore 5
    //   143: aload 5
    //   145: invokevirtual 210	java/lang/Exception:printStackTrace	()V
    //   148: aload 4
    //   150: athrow
    //   151: aload_0
    //   152: getfield 24	com/locationDao:ptmt	Ljava/sql/PreparedStatement;
    //   155: ifnull +32 -> 187
    //   158: aload_0
    //   159: getfield 24	com/locationDao:ptmt	Ljava/sql/PreparedStatement;
    //   162: invokeinterface 209 1 0
    //   167: goto +20 -> 187
    //   170: astore 5
    //   172: aload 5
    //   174: invokevirtual 105	java/sql/SQLException:printStackTrace	()V
    //   177: goto +10 -> 187
    //   180: astore 5
    //   182: aload 5
    //   184: invokevirtual 210	java/lang/Exception:printStackTrace	()V
    //   187: return
    // Line number table:
    //   Java source line #436	-> byte code offset #0
    //   Java source line #439	-> byte code offset #7
    //   Java source line #440	-> byte code offset #14
    //   Java source line #441	-> byte code offset #31
    //   Java source line #442	-> byte code offset #42
    //   Java source line #443	-> byte code offset #53
    //   Java source line #444	-> byte code offset #63
    //   Java source line #445	-> byte code offset #67
    //   Java source line #448	-> byte code offset #71
    //   Java source line #449	-> byte code offset #78
    //   Java source line #450	-> byte code offset #87
    //   Java source line #451	-> byte code offset #92
    //   Java source line #452	-> byte code offset #100
    //   Java source line #453	-> byte code offset #102
    //   Java source line #446	-> byte code offset #110
    //   Java source line #448	-> byte code offset #112
    //   Java source line #449	-> byte code offset #119
    //   Java source line #450	-> byte code offset #128
    //   Java source line #451	-> byte code offset #133
    //   Java source line #452	-> byte code offset #141
    //   Java source line #453	-> byte code offset #143
    //   Java source line #456	-> byte code offset #148
    //   Java source line #448	-> byte code offset #151
    //   Java source line #449	-> byte code offset #158
    //   Java source line #450	-> byte code offset #167
    //   Java source line #451	-> byte code offset #172
    //   Java source line #452	-> byte code offset #180
    //   Java source line #453	-> byte code offset #182
    //   Java source line #458	-> byte code offset #187
    // Local variable table:
    //   start	length	slot	name	signature
    //   0	188	0	this	locationDao
    //   0	188	1	stationid	int
    //   0	188	2	cid	int
    //   66	2	3	e	java.sql.SQLException
    //   110	39	4	localObject	Object
    //   90	3	5	e	java.sql.SQLException
    //   100	3	5	e	Exception
    //   131	3	5	e	java.sql.SQLException
    //   141	3	5	e	Exception
    //   170	3	5	e	java.sql.SQLException
    //   180	3	5	e	Exception
    // Exception table:
    //   from	to	target	type
    //   0	63	66	java/sql/SQLException
    //   71	87	90	java/sql/SQLException
    //   71	87	100	java/lang/Exception
    //   0	71	110	finally
    //   112	128	131	java/sql/SQLException
    //   112	128	141	java/lang/Exception
    //   151	167	170	java/sql/SQLException
    //   151	167	180	java/lang/Exception
  }
  
  /* Error */
  public java.util.List<locationBean> listOperator()
  {
	  return null;
    // Byte code:
    //   0: aload_0
    //   1: ldc_w 409
    //   4: putfield 34	com/locationDao:query	Ljava/lang/String;
    //   7: new 46	java/util/ArrayList
    //   10: dup
    //   11: invokespecial 48	java/util/ArrayList:<init>	()V
    //   14: astore_1
    //   15: aconst_null
    //   16: astore_2
    //   17: aload_0
    //   18: invokestatic 49	com/ConnectionProvider:getCon	()Ljava/sql/Connection;
    //   21: putfield 22	com/locationDao:connection	Ljava/sql/Connection;
    //   24: aload_0
    //   25: aload_0
    //   26: getfield 22	com/locationDao:connection	Ljava/sql/Connection;
    //   29: invokeinterface 55 1 0
    //   34: putfield 30	com/locationDao:stmt	Ljava/sql/Statement;
    //   37: aload_0
    //   38: aload_0
    //   39: getfield 30	com/locationDao:stmt	Ljava/sql/Statement;
    //   42: aload_0
    //   43: getfield 34	com/locationDao:query	Ljava/lang/String;
    //   46: invokeinterface 61 2 0
    //   51: putfield 26	com/locationDao:rs	Ljava/sql/ResultSet;
    //   54: goto +35 -> 89
    //   57: new 67	com/locationBean
    //   60: dup
    //   61: invokespecial 69	com/locationBean:<init>	()V
    //   64: astore_2
    //   65: aload_2
    //   66: aload_0
    //   67: getfield 26	com/locationDao:rs	Ljava/sql/ResultSet;
    //   70: ldc_w 411
    //   73: invokeinterface 84 2 0
    //   78: invokevirtual 295	com/locationBean:setOperator	(Ljava/lang/String;)V
    //   81: aload_1
    //   82: aload_2
    //   83: invokeinterface 92 2 0
    //   88: pop
    //   89: aload_0
    //   90: getfield 26	com/locationDao:rs	Ljava/sql/ResultSet;
    //   93: invokeinterface 98 1 0
    //   98: ifne -41 -> 57
    //   101: aload_0
    //   102: getfield 26	com/locationDao:rs	Ljava/sql/ResultSet;
    //   105: invokeinterface 102 1 0
    //   110: goto +68 -> 178
    //   113: astore_3
    //   114: aload_3
    //   115: invokevirtual 105	java/sql/SQLException:printStackTrace	()V
    //   118: aload_0
    //   119: getfield 30	com/locationDao:stmt	Ljava/sql/Statement;
    //   122: ifnull +82 -> 204
    //   125: aload_0
    //   126: getfield 30	com/locationDao:stmt	Ljava/sql/Statement;
    //   129: invokeinterface 110 1 0
    //   134: goto +70 -> 204
    //   137: astore 5
    //   139: aload 5
    //   141: invokevirtual 105	java/sql/SQLException:printStackTrace	()V
    //   144: goto +60 -> 204
    //   147: astore 4
    //   149: aload_0
    //   150: getfield 30	com/locationDao:stmt	Ljava/sql/Statement;
    //   153: ifnull +22 -> 175
    //   156: aload_0
    //   157: getfield 30	com/locationDao:stmt	Ljava/sql/Statement;
    //   160: invokeinterface 110 1 0
    //   165: goto +10 -> 175
    //   168: astore 5
    //   170: aload 5
    //   172: invokevirtual 105	java/sql/SQLException:printStackTrace	()V
    //   175: aload 4
    //   177: athrow
    //   178: aload_0
    //   179: getfield 30	com/locationDao:stmt	Ljava/sql/Statement;
    //   182: ifnull +22 -> 204
    //   185: aload_0
    //   186: getfield 30	com/locationDao:stmt	Ljava/sql/Statement;
    //   189: invokeinterface 110 1 0
    //   194: goto +10 -> 204
    //   197: astore 5
    //   199: aload 5
    //   201: invokevirtual 105	java/sql/SQLException:printStackTrace	()V
    //   204: aload_1
    //   205: areturn
    // Line number table:
    //   Java source line #461	-> byte code offset #0
    //   Java source line #462	-> byte code offset #7
    //   Java source line #463	-> byte code offset #15
    //   Java source line #465	-> byte code offset #17
    //   Java source line #466	-> byte code offset #24
    //   Java source line #467	-> byte code offset #37
    //   Java source line #468	-> byte code offset #54
    //   Java source line #469	-> byte code offset #57
    //   Java source line #470	-> byte code offset #65
    //   Java source line #471	-> byte code offset #81
    //   Java source line #468	-> byte code offset #89
    //   Java source line #473	-> byte code offset #101
    //   Java source line #475	-> byte code offset #110
    //   Java source line #477	-> byte code offset #118
    //   Java source line #478	-> byte code offset #125
    //   Java source line #476	-> byte code offset #147
    //   Java source line #477	-> byte code offset #149
    //   Java source line #478	-> byte code offset #156
    //   Java source line #479	-> byte code offset #175
    //   Java source line #477	-> byte code offset #178
    //   Java source line #478	-> byte code offset #185
    //   Java source line #480	-> byte code offset #204
    // Local variable table:
    //   start	length	slot	name	signature
    //   0	206	0	this	locationDao
    //   14	191	1	list	java.util.List<locationBean>
    //   16	67	2	op	locationBean
    //   113	2	3	e	java.sql.SQLException
    //   147	29	4	localObject	Object
    //   137	3	5	e	java.sql.SQLException
    //   168	3	5	e	java.sql.SQLException
    //   197	3	5	e	java.sql.SQLException
    // Exception table:
    //   from	to	target	type
    //   17	110	113	java/sql/SQLException
    //   118	134	137	java/sql/SQLException
    //   17	118	147	finally
    //   149	165	168	java/sql/SQLException
    //   178	194	197	java/sql/SQLException
  }
}
