package com;

import java.io.PrintStream;
import java.sql.Connection;
import java.sql.PreparedStatement;
import java.sql.ResultSet;
import java.sql.Statement;
import java.sql.Timestamp;
import java.util.Date;

public class LoginDao
{
  Connection con = null;
  PreparedStatement ptmt = null;
  ResultSet rs = null;
  boolean status = false;
  Statement stmt = null;
  String query = null;
  Date date = new Date();
  
  public void login(LoginBean bean)
  {
    try
    {
      this.con = ConnectionProvider.getCon();
      this.ptmt = this.con.prepareStatement("select * from users where login_name=?");
      this.ptmt.setString(1, bean.getUname());
      this.rs = this.ptmt.executeQuery();
      this.status = this.rs.next();
      if (!this.status)
      {
        System.out.println(bean.getUname() + "- Login Failure -" + new Timestamp(this.date.getTime()));
        bean.setStatus(false);
      }
      else if (this.status)
      {
        String Pswd = this.rs.getString("user_password");
        bean.setUsername(this.rs.getString("user_name"));
        bean.setRole(this.rs.getInt("user_role"));
        bean.setUid(this.rs.getInt("user_id"));
        bean.setOrg_id(this.rs.getInt("org_id"));
        if (Pswd.equals(bean.getPass()))
        {
          bean.setStatus(true);
          System.out.println(bean.getUname() + "- Login Sucess -" + new Timestamp(this.date.getTime()));
        }
        else
        {
          bean.setStatus(false);
        }
      }
    }
    catch (Exception e)
    {
      System.out.println("Log In failed: An Exception has occurred! " + e);
    }
  }
  
  /* Error */
  public java.util.List<LoginBean> listRoles(int oid)
  {
	  return null;
    // Byte code:
    //   0: aload_0
    //   1: ldc -72
    //   3: putfield 34	com/LoginDao:query	Ljava/lang/String;
    //   6: new 186	java/util/ArrayList
    //   9: dup
    //   10: invokespecial 188	java/util/ArrayList:<init>	()V
    //   13: astore_2
    //   14: aconst_null
    //   15: astore_3
    //   16: aload_0
    //   17: invokestatic 47	com/ConnectionProvider:getCon	()Ljava/sql/Connection;
    //   20: putfield 24	com/LoginDao:con	Ljava/sql/Connection;
    //   23: aload_0
    //   24: aload_0
    //   25: getfield 24	com/LoginDao:con	Ljava/sql/Connection;
    //   28: aload_0
    //   29: getfield 34	com/LoginDao:query	Ljava/lang/String;
    //   32: invokeinterface 55 2 0
    //   37: putfield 26	com/LoginDao:ptmt	Ljava/sql/PreparedStatement;
    //   40: aload_0
    //   41: getfield 26	com/LoginDao:ptmt	Ljava/sql/PreparedStatement;
    //   44: iconst_1
    //   45: iload_1
    //   46: invokeinterface 189 3 0
    //   51: aload_0
    //   52: aload_0
    //   53: getfield 26	com/LoginDao:ptmt	Ljava/sql/PreparedStatement;
    //   56: invokeinterface 73 1 0
    //   61: putfield 28	com/LoginDao:rs	Ljava/sql/ResultSet;
    //   64: goto +49 -> 113
    //   67: new 62	com/LoginBean
    //   70: dup
    //   71: invokespecial 193	com/LoginBean:<init>	()V
    //   74: astore_3
    //   75: aload_3
    //   76: aload_0
    //   77: getfield 28	com/LoginDao:rs	Ljava/sql/ResultSet;
    //   80: ldc -62
    //   82: invokeinterface 132 2 0
    //   87: invokevirtual 196	com/LoginBean:setRole_id	(Ljava/lang/String;)V
    //   90: aload_3
    //   91: aload_0
    //   92: getfield 28	com/LoginDao:rs	Ljava/sql/ResultSet;
    //   95: ldc -57
    //   97: invokeinterface 132 2 0
    //   102: invokevirtual 201	com/LoginBean:setRole_desc	(Ljava/lang/String;)V
    //   105: aload_2
    //   106: aload_3
    //   107: invokeinterface 204 2 0
    //   112: pop
    //   113: aload_0
    //   114: getfield 28	com/LoginDao:rs	Ljava/sql/ResultSet;
    //   117: invokeinterface 77 1 0
    //   122: ifne -55 -> 67
    //   125: aload_0
    //   126: getfield 28	com/LoginDao:rs	Ljava/sql/ResultSet;
    //   129: invokeinterface 209 1 0
    //   134: goto +70 -> 204
    //   137: astore 4
    //   139: aload 4
    //   141: invokevirtual 212	java/sql/SQLException:printStackTrace	()V
    //   144: aload_0
    //   145: getfield 26	com/LoginDao:ptmt	Ljava/sql/PreparedStatement;
    //   148: ifnull +82 -> 230
    //   151: aload_0
    //   152: getfield 26	com/LoginDao:ptmt	Ljava/sql/PreparedStatement;
    //   155: invokeinterface 217 1 0
    //   160: goto +70 -> 230
    //   163: astore 6
    //   165: aload 6
    //   167: invokevirtual 212	java/sql/SQLException:printStackTrace	()V
    //   170: goto +60 -> 230
    //   173: astore 5
    //   175: aload_0
    //   176: getfield 26	com/LoginDao:ptmt	Ljava/sql/PreparedStatement;
    //   179: ifnull +22 -> 201
    //   182: aload_0
    //   183: getfield 26	com/LoginDao:ptmt	Ljava/sql/PreparedStatement;
    //   186: invokeinterface 217 1 0
    //   191: goto +10 -> 201
    //   194: astore 6
    //   196: aload 6
    //   198: invokevirtual 212	java/sql/SQLException:printStackTrace	()V
    //   201: aload 5
    //   203: athrow
    //   204: aload_0
    //   205: getfield 26	com/LoginDao:ptmt	Ljava/sql/PreparedStatement;
    //   208: ifnull +22 -> 230
    //   211: aload_0
    //   212: getfield 26	com/LoginDao:ptmt	Ljava/sql/PreparedStatement;
    //   215: invokeinterface 217 1 0
    //   220: goto +10 -> 230
    //   223: astore 6
    //   225: aload 6
    //   227: invokevirtual 212	java/sql/SQLException:printStackTrace	()V
    //   230: aload_2
    //   231: areturn
    // Line number table:
    //   Java source line #65	-> byte code offset #0
    //   Java source line #66	-> byte code offset #6
    //   Java source line #68	-> byte code offset #14
    //   Java source line #70	-> byte code offset #16
    //   Java source line #71	-> byte code offset #23
    //   Java source line #72	-> byte code offset #40
    //   Java source line #74	-> byte code offset #51
    //   Java source line #76	-> byte code offset #64
    //   Java source line #77	-> byte code offset #67
    //   Java source line #78	-> byte code offset #75
    //   Java source line #79	-> byte code offset #90
    //   Java source line #80	-> byte code offset #105
    //   Java source line #76	-> byte code offset #113
    //   Java source line #82	-> byte code offset #125
    //   Java source line #84	-> byte code offset #134
    //   Java source line #88	-> byte code offset #144
    //   Java source line #89	-> byte code offset #151
    //   Java source line #90	-> byte code offset #160
    //   Java source line #91	-> byte code offset #165
    //   Java source line #86	-> byte code offset #173
    //   Java source line #88	-> byte code offset #175
    //   Java source line #89	-> byte code offset #182
    //   Java source line #90	-> byte code offset #191
    //   Java source line #91	-> byte code offset #196
    //   Java source line #93	-> byte code offset #201
    //   Java source line #88	-> byte code offset #204
    //   Java source line #89	-> byte code offset #211
    //   Java source line #90	-> byte code offset #220
    //   Java source line #91	-> byte code offset #225
    //   Java source line #94	-> byte code offset #230
    // Local variable table:
    //   start	length	slot	name	signature
    //   0	232	0	this	LoginDao
    //   0	232	1	oid	int
    //   13	218	2	list	java.util.List<LoginBean>
    //   15	92	3	login	LoginBean
    //   137	3	4	e	java.sql.SQLException
    //   173	29	5	localObject	Object
    //   163	3	6	e	java.sql.SQLException
    //   194	3	6	e	java.sql.SQLException
    //   223	3	6	e	java.sql.SQLException
    // Exception table:
    //   from	to	target	type
    //   16	134	137	java/sql/SQLException
    //   144	160	163	java/sql/SQLException
    //   16	144	173	finally
    //   175	191	194	java/sql/SQLException
    //   204	220	223	java/sql/SQLException
  }
 
  
  /* Error */
  public java.util.List<LoginBean> listModules(int oid)
  {
	  return null;
    // Byte code:
    //   0: aload_0
    //   1: ldc -28
    //   3: putfield 34	com/LoginDao:query	Ljava/lang/String;
    //   6: new 186	java/util/ArrayList
    //   9: dup
    //   10: invokespecial 188	java/util/ArrayList:<init>	()V
    //   13: astore_2
    //   14: aconst_null
    //   15: astore_3
    //   16: aload_0
    //   17: invokestatic 47	com/ConnectionProvider:getCon	()Ljava/sql/Connection;
    //   20: putfield 24	com/LoginDao:con	Ljava/sql/Connection;
    //   23: aload_0
    //   24: aload_0
    //   25: getfield 24	com/LoginDao:con	Ljava/sql/Connection;
    //   28: aload_0
    //   29: getfield 34	com/LoginDao:query	Ljava/lang/String;
    //   32: invokeinterface 55 2 0
    //   37: putfield 26	com/LoginDao:ptmt	Ljava/sql/PreparedStatement;
    //   40: aload_0
    //   41: getfield 26	com/LoginDao:ptmt	Ljava/sql/PreparedStatement;
    //   44: iconst_1
    //   45: iload_1
    //   46: invokeinterface 189 3 0
    //   51: aload_0
    //   52: aload_0
    //   53: getfield 26	com/LoginDao:ptmt	Ljava/sql/PreparedStatement;
    //   56: invokeinterface 73 1 0
    //   61: putfield 28	com/LoginDao:rs	Ljava/sql/ResultSet;
    //   64: goto +49 -> 113
    //   67: new 62	com/LoginBean
    //   70: dup
    //   71: invokespecial 193	com/LoginBean:<init>	()V
    //   74: astore_3
    //   75: aload_3
    //   76: aload_0
    //   77: getfield 28	com/LoginDao:rs	Ljava/sql/ResultSet;
    //   80: ldc -26
    //   82: invokeinterface 143 2 0
    //   87: invokevirtual 232	com/LoginBean:setModule_id	(I)V
    //   90: aload_3
    //   91: aload_0
    //   92: getfield 28	com/LoginDao:rs	Ljava/sql/ResultSet;
    //   95: ldc -21
    //   97: invokeinterface 132 2 0
    //   102: invokevirtual 237	com/LoginBean:setModule	(Ljava/lang/String;)V
    //   105: aload_2
    //   106: aload_3
    //   107: invokeinterface 204 2 0
    //   112: pop
    //   113: aload_0
    //   114: getfield 28	com/LoginDao:rs	Ljava/sql/ResultSet;
    //   117: invokeinterface 77 1 0
    //   122: ifne -55 -> 67
    //   125: aload_0
    //   126: getfield 28	com/LoginDao:rs	Ljava/sql/ResultSet;
    //   129: invokeinterface 209 1 0
    //   134: goto +70 -> 204
    //   137: astore 4
    //   139: aload 4
    //   141: invokevirtual 212	java/sql/SQLException:printStackTrace	()V
    //   144: aload_0
    //   145: getfield 26	com/LoginDao:ptmt	Ljava/sql/PreparedStatement;
    //   148: ifnull +82 -> 230
    //   151: aload_0
    //   152: getfield 26	com/LoginDao:ptmt	Ljava/sql/PreparedStatement;
    //   155: invokeinterface 217 1 0
    //   160: goto +70 -> 230
    //   163: astore 6
    //   165: aload 6
    //   167: invokevirtual 212	java/sql/SQLException:printStackTrace	()V
    //   170: goto +60 -> 230
    //   173: astore 5
    //   175: aload_0
    //   176: getfield 26	com/LoginDao:ptmt	Ljava/sql/PreparedStatement;
    //   179: ifnull +22 -> 201
    //   182: aload_0
    //   183: getfield 26	com/LoginDao:ptmt	Ljava/sql/PreparedStatement;
    //   186: invokeinterface 217 1 0
    //   191: goto +10 -> 201
    //   194: astore 6
    //   196: aload 6
    //   198: invokevirtual 212	java/sql/SQLException:printStackTrace	()V
    //   201: aload 5
    //   203: athrow
    //   204: aload_0
    //   205: getfield 26	com/LoginDao:ptmt	Ljava/sql/PreparedStatement;
    //   208: ifnull +22 -> 230
    //   211: aload_0
    //   212: getfield 26	com/LoginDao:ptmt	Ljava/sql/PreparedStatement;
    //   215: invokeinterface 217 1 0
    //   220: goto +10 -> 230
    //   223: astore 6
    //   225: aload 6
    //   227: invokevirtual 212	java/sql/SQLException:printStackTrace	()V
    //   230: aload_2
      // 231: return
    // Line number table:
    //   Java source line #98	-> byte code offset #0
    //   Java source line #99	-> byte code offset #6
    //   Java source line #100	-> byte code offset #14
    //   Java source line #102	-> byte code offset #16
    //   Java source line #103	-> byte code offset #23
    //   Java source line #104	-> byte code offset #40
    //   Java source line #106	-> byte code offset #51
    //   Java source line #108	-> byte code offset #64
    //   Java source line #109	-> byte code offset #67
    //   Java source line #110	-> byte code offset #75
    //   Java source line #111	-> byte code offset #90
    //   Java source line #112	-> byte code offset #105
    //   Java source line #108	-> byte code offset #113
    //   Java source line #114	-> byte code offset #125
    //   Java source line #116	-> byte code offset #134
    //   Java source line #120	-> byte code offset #144
    //   Java source line #121	-> byte code offset #151
    //   Java source line #122	-> byte code offset #160
    //   Java source line #123	-> byte code offset #165
    //   Java source line #118	-> byte code offset #173
    //   Java source line #120	-> byte code offset #175
    //   Java source line #121	-> byte code offset #182
    //   Java source line #122	-> byte code offset #191
    //   Java source line #123	-> byte code offset #196
    //   Java source line #125	-> byte code offset #201
    //   Java source line #120	-> byte code offset #204
    //   Java source line #121	-> byte code offset #211
    //   Java source line #122	-> byte code offset #220
    //   Java source line #123	-> byte code offset #225
    //   Java source line #126	-> byte code offset #230
    // Local variable table:
    //   start	length	slot	name	signature
    //   0	232	0	this	LoginDao
    //   0	232	1	oid	int
    //   13	218	2	list	java.util.List<LoginBean>
    //   15	92	3	login	LoginBean
    //   137	3	4	e	java.sql.SQLException
    //   173	29	5	localObject	Object
    //   163	3	6	e	java.sql.SQLException
    //   194	3	6	e	java.sql.SQLException
    //   223	3	6	e	java.sql.SQLException
    // Exception table:
    //   from	to	target	type
    //   16	134	137	java/sql/SQLException
    //   144	160	163	java/sql/SQLException
    //   16	144	173	finally
    //   175	191	194	java/sql/SQLException
    //   204	220	223	java/sql/SQLException
  }
  
  /* Error */
  public java.util.List<LoginBean> listMenu(int Roleid)
  {
	   return null;
    // Byte code:
    //   0: aload_0
    //   1: ldc -15
    //   3: putfield 34	com/LoginDao:query	Ljava/lang/String;
    //   6: new 186	java/util/ArrayList
    //   9: dup
    //   10: invokespecial 188	java/util/ArrayList:<init>	()V
    //   13: astore_2
    //   14: aconst_null
    //   15: astore_3
    //   16: aload_0
    //   17: invokestatic 47	com/ConnectionProvider:getCon	()Ljava/sql/Connection;
    //   20: putfield 24	com/LoginDao:con	Ljava/sql/Connection;
    //   23: aload_0
    //   24: aload_0
    //   25: getfield 24	com/LoginDao:con	Ljava/sql/Connection;
    //   28: aload_0
    //   29: getfield 34	com/LoginDao:query	Ljava/lang/String;
    //   32: invokeinterface 55 2 0
    //   37: putfield 26	com/LoginDao:ptmt	Ljava/sql/PreparedStatement;
    //   40: aload_0
    //   41: getfield 26	com/LoginDao:ptmt	Ljava/sql/PreparedStatement;
    //   44: iconst_1
    //   45: iload_1
    //   46: invokeinterface 189 3 0
    //   51: aload_0
    //   52: aload_0
    //   53: getfield 26	com/LoginDao:ptmt	Ljava/sql/PreparedStatement;
    //   56: invokeinterface 73 1 0
    //   61: putfield 28	com/LoginDao:rs	Ljava/sql/ResultSet;
    //   64: goto +64 -> 128
    //   67: new 62	com/LoginBean
    //   70: dup
    //   71: invokespecial 193	com/LoginBean:<init>	()V
    //   74: astore_3
    //   75: aload_3
    //   76: aload_0
    //   77: getfield 28	com/LoginDao:rs	Ljava/sql/ResultSet;
    //   80: ldc -26
    //   82: invokeinterface 143 2 0
    //   87: invokevirtual 232	com/LoginBean:setModule_id	(I)V
    //   90: aload_3
    //   91: aload_0
    //   92: getfield 28	com/LoginDao:rs	Ljava/sql/ResultSet;
    //   95: ldc -21
    //   97: invokeinterface 132 2 0
    //   102: invokevirtual 237	com/LoginBean:setModule	(Ljava/lang/String;)V
    //   105: aload_3
    //   106: aload_0
    //   107: getfield 28	com/LoginDao:rs	Ljava/sql/ResultSet;
    //   110: ldc -13
    //   112: invokeinterface 132 2 0
    //   117: invokevirtual 245	com/LoginBean:setMenu_url	(Ljava/lang/String;)V
    //   120: aload_2
    //   121: aload_3
    //   122: invokeinterface 204 2 0
    //   127: pop
    //   128: aload_0
    //   129: getfield 28	com/LoginDao:rs	Ljava/sql/ResultSet;
    //   132: invokeinterface 77 1 0
    //   137: ifne -70 -> 67
    //   140: aload_0
    //   141: getfield 28	com/LoginDao:rs	Ljava/sql/ResultSet;
    //   144: invokeinterface 209 1 0
    //   149: goto +70 -> 219
    //   152: astore 4
    //   154: aload 4
    //   156: invokevirtual 212	java/sql/SQLException:printStackTrace	()V
    //   159: aload_0
    //   160: getfield 26	com/LoginDao:ptmt	Ljava/sql/PreparedStatement;
    //   163: ifnull +82 -> 245
    //   166: aload_0
    //   167: getfield 26	com/LoginDao:ptmt	Ljava/sql/PreparedStatement;
    //   170: invokeinterface 217 1 0
    //   175: goto +70 -> 245
    //   178: astore 6
    //   180: aload 6
    //   182: invokevirtual 212	java/sql/SQLException:printStackTrace	()V
    //   185: goto +60 -> 245
    //   188: astore 5
    //   190: aload_0
    //   191: getfield 26	com/LoginDao:ptmt	Ljava/sql/PreparedStatement;
    //   194: ifnull +22 -> 216
    //   197: aload_0
    //   198: getfield 26	com/LoginDao:ptmt	Ljava/sql/PreparedStatement;
    //   201: invokeinterface 217 1 0
    //   206: goto +10 -> 216
    //   209: astore 6
    //   211: aload 6
    //   213: invokevirtual 212	java/sql/SQLException:printStackTrace	()V
    //   216: aload 5
    //   218: athrow
    //   219: aload_0
    //   220: getfield 26	com/LoginDao:ptmt	Ljava/sql/PreparedStatement;
    //   223: ifnull +22 -> 245
    //   226: aload_0
    //   227: getfield 26	com/LoginDao:ptmt	Ljava/sql/PreparedStatement;
    //   230: invokeinterface 217 1 0
    //   235: goto +10 -> 245
    //   238: astore 6
    //   240: aload 6
    //   242: invokevirtual 212	java/sql/SQLException:printStackTrace	()V
    //   245: aload_2
    //   246: areturn
    // Line number table:
    //   Java source line #133	-> byte code offset #0
    //   Java source line #135	-> byte code offset #6
    //   Java source line #137	-> byte code offset #14
    //   Java source line #139	-> byte code offset #16
    //   Java source line #140	-> byte code offset #23
    //   Java source line #141	-> byte code offset #40
    //   Java source line #144	-> byte code offset #51
    //   Java source line #146	-> byte code offset #64
    //   Java source line #147	-> byte code offset #67
    //   Java source line #148	-> byte code offset #75
    //   Java source line #149	-> byte code offset #90
    //   Java source line #150	-> byte code offset #105
    //   Java source line #151	-> byte code offset #120
    //   Java source line #146	-> byte code offset #128
    //   Java source line #153	-> byte code offset #140
    //   Java source line #155	-> byte code offset #149
    //   Java source line #159	-> byte code offset #159
    //   Java source line #160	-> byte code offset #166
    //   Java source line #161	-> byte code offset #175
    //   Java source line #162	-> byte code offset #180
    //   Java source line #157	-> byte code offset #188
    //   Java source line #159	-> byte code offset #190
    //   Java source line #160	-> byte code offset #197
    //   Java source line #161	-> byte code offset #206
    //   Java source line #162	-> byte code offset #211
    //   Java source line #164	-> byte code offset #216
    //   Java source line #159	-> byte code offset #219
    //   Java source line #160	-> byte code offset #226
    //   Java source line #161	-> byte code offset #235
    //   Java source line #162	-> byte code offset #240
    //   Java source line #165	-> byte code offset #245
    // Local variable table:
    //   start	length	slot	name	signature
    //   0	247	0	this	LoginDao
    //   0	247	1	Roleid	int
    //   13	233	2	list	java.util.List<LoginBean>
    //   15	107	3	menu	LoginBean
    //   152	3	4	e	java.sql.SQLException
    //   188	29	5	localObject	Object
    //   178	3	6	e	java.sql.SQLException
    //   209	3	6	e	java.sql.SQLException
    //   238	3	6	e	java.sql.SQLException
    // Exception table:
    //   from	to	target	type
    //   16	149	152	java/sql/SQLException
    //   159	175	178	java/sql/SQLException
    //   16	159	188	finally
    //   190	206	209	java/sql/SQLException
    //   219	235	238	java/sql/SQLException
  }
  
  /* Error */
  public java.util.List<LoginBean> listMenus(int vModuleid)
  {
	   return null;
    // Byte code:
    //   0: aload_0
    //   1: ldc -5
    //   3: putfield 34	com/LoginDao:query	Ljava/lang/String;
    //   6: new 186	java/util/ArrayList
    //   9: dup
    //   10: invokespecial 188	java/util/ArrayList:<init>	()V
    //   13: astore_2
    //   14: aconst_null
    //   15: astore_3
    //   16: aload_0
    //   17: invokestatic 47	com/ConnectionProvider:getCon	()Ljava/sql/Connection;
    //   20: putfield 24	com/LoginDao:con	Ljava/sql/Connection;
    //   23: aload_0
    //   24: aload_0
    //   25: getfield 24	com/LoginDao:con	Ljava/sql/Connection;
    //   28: aload_0
    //   29: getfield 34	com/LoginDao:query	Ljava/lang/String;
    //   32: invokeinterface 55 2 0
    //   37: putfield 26	com/LoginDao:ptmt	Ljava/sql/PreparedStatement;
    //   40: aload_0
    //   41: getfield 26	com/LoginDao:ptmt	Ljava/sql/PreparedStatement;
    //   44: iconst_1
    //   45: iload_1
    //   46: invokeinterface 189 3 0
    //   51: aload_0
    //   52: aload_0
    //   53: getfield 26	com/LoginDao:ptmt	Ljava/sql/PreparedStatement;
    //   56: invokeinterface 73 1 0
    //   61: putfield 28	com/LoginDao:rs	Ljava/sql/ResultSet;
    //   64: goto +65 -> 129
    //   67: new 62	com/LoginBean
    //   70: dup
    //   71: invokespecial 193	com/LoginBean:<init>	()V
    //   74: astore_3
    //   75: aload_3
    //   76: aload_0
    //   77: getfield 28	com/LoginDao:rs	Ljava/sql/ResultSet;
    //   80: ldc -3
    //   82: invokeinterface 143 2 0
    //   87: invokevirtual 232	com/LoginBean:setModule_id	(I)V
    //   90: aload_3
    //   91: aload_0
    //   92: getfield 28	com/LoginDao:rs	Ljava/sql/ResultSet;
    //   95: ldc -1
    //   97: invokeinterface 132 2 0
    //   102: invokevirtual 237	com/LoginBean:setModule	(Ljava/lang/String;)V
    //   105: aload_3
    //   106: aload_0
    //   107: getfield 28	com/LoginDao:rs	Ljava/sql/ResultSet;
    //   110: ldc_w 257
    //   113: invokeinterface 132 2 0
    //   118: invokevirtual 245	com/LoginBean:setMenu_url	(Ljava/lang/String;)V
    //   121: aload_2
    //   122: aload_3
    //   123: invokeinterface 204 2 0
    //   128: pop
    //   129: aload_0
    //   130: getfield 28	com/LoginDao:rs	Ljava/sql/ResultSet;
    //   133: invokeinterface 77 1 0
    //   138: ifne -71 -> 67
    //   141: aload_0
    //   142: getfield 28	com/LoginDao:rs	Ljava/sql/ResultSet;
    //   145: invokeinterface 209 1 0
    //   150: goto +70 -> 220
    //   153: astore 4
    //   155: aload 4
    //   157: invokevirtual 212	java/sql/SQLException:printStackTrace	()V
    //   160: aload_0
    //   161: getfield 26	com/LoginDao:ptmt	Ljava/sql/PreparedStatement;
    //   164: ifnull +82 -> 246
    //   167: aload_0
    //   168: getfield 26	com/LoginDao:ptmt	Ljava/sql/PreparedStatement;
    //   171: invokeinterface 217 1 0
    //   176: goto +70 -> 246
    //   179: astore 6
    //   181: aload 6
    //   183: invokevirtual 212	java/sql/SQLException:printStackTrace	()V
    //   186: goto +60 -> 246
    //   189: astore 5
    //   191: aload_0
    //   192: getfield 26	com/LoginDao:ptmt	Ljava/sql/PreparedStatement;
    //   195: ifnull +22 -> 217
    //   198: aload_0
    //   199: getfield 26	com/LoginDao:ptmt	Ljava/sql/PreparedStatement;
    //   202: invokeinterface 217 1 0
    //   207: goto +10 -> 217
    //   210: astore 6
    //   212: aload 6
    //   214: invokevirtual 212	java/sql/SQLException:printStackTrace	()V
    //   217: aload 5
    //   219: athrow
    //   220: aload_0
    //   221: getfield 26	com/LoginDao:ptmt	Ljava/sql/PreparedStatement;
    //   224: ifnull +22 -> 246
    //   227: aload_0
    //   228: getfield 26	com/LoginDao:ptmt	Ljava/sql/PreparedStatement;
    //   231: invokeinterface 217 1 0
    //   236: goto +10 -> 246
    //   239: astore 6
    //   241: aload 6
    //   243: invokevirtual 212	java/sql/SQLException:printStackTrace	()V
    //   246: aload_2
    //   247: areturn
    // Line number table:
    //   Java source line #171	-> byte code offset #0
    //   Java source line #173	-> byte code offset #6
    //   Java source line #175	-> byte code offset #14
    //   Java source line #177	-> byte code offset #16
    //   Java source line #178	-> byte code offset #23
    //   Java source line #179	-> byte code offset #40
    //   Java source line #180	-> byte code offset #51
    //   Java source line #182	-> byte code offset #64
    //   Java source line #183	-> byte code offset #67
    //   Java source line #184	-> byte code offset #75
    //   Java source line #185	-> byte code offset #90
    //   Java source line #186	-> byte code offset #105
    //   Java source line #187	-> byte code offset #121
    //   Java source line #182	-> byte code offset #129
    //   Java source line #189	-> byte code offset #141
    //   Java source line #190	-> byte code offset #150
    //   Java source line #194	-> byte code offset #160
    //   Java source line #195	-> byte code offset #167
    //   Java source line #196	-> byte code offset #176
    //   Java source line #197	-> byte code offset #181
    //   Java source line #192	-> byte code offset #189
    //   Java source line #194	-> byte code offset #191
    //   Java source line #195	-> byte code offset #198
    //   Java source line #196	-> byte code offset #207
    //   Java source line #197	-> byte code offset #212
    //   Java source line #199	-> byte code offset #217
    //   Java source line #194	-> byte code offset #220
    //   Java source line #195	-> byte code offset #227
    //   Java source line #196	-> byte code offset #236
    //   Java source line #197	-> byte code offset #241
    //   Java source line #200	-> byte code offset #246
    // Local variable table:
    //   start	length	slot	name	signature
    //   0	248	0	this	LoginDao
    //   0	248	1	vModuleid	int
    //   13	234	2	list	java.util.List<LoginBean>
    //   15	108	3	menu	LoginBean
    //   153	3	4	e	java.sql.SQLException
    //   189	29	5	localObject	Object
    //   179	3	6	e	java.sql.SQLException
    //   210	3	6	e	java.sql.SQLException
    //   239	3	6	e	java.sql.SQLException
    // Exception table:
    //   from	to	target	type
    //   16	150	153	java/sql/SQLException
    //   160	176	179	java/sql/SQLException
    //   16	160	189	finally
    //   191	207	210	java/sql/SQLException
    //   220	236	239	java/sql/SQLException
  }
  
  /* Error */
  public java.util.List<LoginBean> listCreports()
  {
	   return null;
    // Byte code:
    //   0: aload_0
    //   1: ldc_w 263
    //   4: putfield 34	com/LoginDao:query	Ljava/lang/String;
    //   7: new 186	java/util/ArrayList
    //   10: dup
    //   11: invokespecial 188	java/util/ArrayList:<init>	()V
    //   14: astore_1
    //   15: aconst_null
    //   16: astore_2
    //   17: aload_0
    //   18: invokestatic 47	com/ConnectionProvider:getCon	()Ljava/sql/Connection;
    //   21: putfield 24	com/LoginDao:con	Ljava/sql/Connection;
    //   24: aload_0
    //   25: aload_0
    //   26: getfield 24	com/LoginDao:con	Ljava/sql/Connection;
    //   29: aload_0
    //   30: getfield 34	com/LoginDao:query	Ljava/lang/String;
    //   33: invokeinterface 55 2 0
    //   38: putfield 26	com/LoginDao:ptmt	Ljava/sql/PreparedStatement;
    //   41: aload_0
    //   42: aload_0
    //   43: getfield 26	com/LoginDao:ptmt	Ljava/sql/PreparedStatement;
    //   46: invokeinterface 73 1 0
    //   51: putfield 28	com/LoginDao:rs	Ljava/sql/ResultSet;
    //   54: goto +67 -> 121
    //   57: new 62	com/LoginBean
    //   60: dup
    //   61: invokespecial 193	com/LoginBean:<init>	()V
    //   64: astore_2
    //   65: aload_2
    //   66: aload_0
    //   67: getfield 28	com/LoginDao:rs	Ljava/sql/ResultSet;
    //   70: ldc_w 265
    //   73: invokeinterface 143 2 0
    //   78: invokevirtual 232	com/LoginBean:setModule_id	(I)V
    //   81: aload_2
    //   82: aload_0
    //   83: getfield 28	com/LoginDao:rs	Ljava/sql/ResultSet;
    //   86: ldc_w 267
    //   89: invokeinterface 132 2 0
    //   94: invokevirtual 237	com/LoginBean:setModule	(Ljava/lang/String;)V
    //   97: aload_2
    //   98: aload_0
    //   99: getfield 28	com/LoginDao:rs	Ljava/sql/ResultSet;
    //   102: ldc_w 269
    //   105: invokeinterface 132 2 0
    //   110: invokevirtual 245	com/LoginBean:setMenu_url	(Ljava/lang/String;)V
    //   113: aload_1
    //   114: aload_2
    //   115: invokeinterface 204 2 0
    //   120: pop
    //   121: aload_0
    //   122: getfield 28	com/LoginDao:rs	Ljava/sql/ResultSet;
    //   125: invokeinterface 77 1 0
    //   130: ifne -73 -> 57
    //   133: aload_0
    //   134: getfield 28	com/LoginDao:rs	Ljava/sql/ResultSet;
    //   137: invokeinterface 209 1 0
    //   142: goto +68 -> 210
    //   145: astore_3
    //   146: aload_3
    //   147: invokevirtual 212	java/sql/SQLException:printStackTrace	()V
    //   150: aload_0
    //   151: getfield 26	com/LoginDao:ptmt	Ljava/sql/PreparedStatement;
    //   154: ifnull +82 -> 236
    //   157: aload_0
    //   158: getfield 26	com/LoginDao:ptmt	Ljava/sql/PreparedStatement;
    //   161: invokeinterface 217 1 0
    //   166: goto +70 -> 236
    //   169: astore 5
    //   171: aload 5
    //   173: invokevirtual 212	java/sql/SQLException:printStackTrace	()V
    //   176: goto +60 -> 236
    //   179: astore 4
    //   181: aload_0
    //   182: getfield 26	com/LoginDao:ptmt	Ljava/sql/PreparedStatement;
    //   185: ifnull +22 -> 207
    //   188: aload_0
    //   189: getfield 26	com/LoginDao:ptmt	Ljava/sql/PreparedStatement;
    //   192: invokeinterface 217 1 0
    //   197: goto +10 -> 207
    //   200: astore 5
    //   202: aload 5
    //   204: invokevirtual 212	java/sql/SQLException:printStackTrace	()V
    //   207: aload 4
    //   209: athrow
    //   210: aload_0
    //   211: getfield 26	com/LoginDao:ptmt	Ljava/sql/PreparedStatement;
    //   214: ifnull +22 -> 236
    //   217: aload_0
    //   218: getfield 26	com/LoginDao:ptmt	Ljava/sql/PreparedStatement;
    //   221: invokeinterface 217 1 0
    //   226: goto +10 -> 236
    //   229: astore 5
    //   231: aload 5
    //   233: invokevirtual 212	java/sql/SQLException:printStackTrace	()V
    //   236: aload_1
    //   237: areturn
    // Line number table:
    //   Java source line #207	-> byte code offset #0
    //   Java source line #209	-> byte code offset #7
    //   Java source line #211	-> byte code offset #15
    //   Java source line #213	-> byte code offset #17
    //   Java source line #214	-> byte code offset #24
    //   Java source line #215	-> byte code offset #41
    //   Java source line #217	-> byte code offset #54
    //   Java source line #218	-> byte code offset #57
    //   Java source line #219	-> byte code offset #65
    //   Java source line #220	-> byte code offset #81
    //   Java source line #221	-> byte code offset #97
    //   Java source line #222	-> byte code offset #113
    //   Java source line #217	-> byte code offset #121
    //   Java source line #224	-> byte code offset #133
    //   Java source line #225	-> byte code offset #142
    //   Java source line #229	-> byte code offset #150
    //   Java source line #230	-> byte code offset #157
    //   Java source line #231	-> byte code offset #166
    //   Java source line #232	-> byte code offset #171
    //   Java source line #227	-> byte code offset #179
    //   Java source line #229	-> byte code offset #181
    //   Java source line #230	-> byte code offset #188
    //   Java source line #231	-> byte code offset #197
    //   Java source line #232	-> byte code offset #202
    //   Java source line #234	-> byte code offset #207
    //   Java source line #229	-> byte code offset #210
    //   Java source line #230	-> byte code offset #217
    //   Java source line #231	-> byte code offset #226
    //   Java source line #232	-> byte code offset #231
    //   Java source line #235	-> byte code offset #236
    // Local variable table:
    //   start	length	slot	name	signature
    //   0	238	0	this	LoginDao
    //   14	223	1	list	java.util.List<LoginBean>
    //   16	99	2	menu	LoginBean
    //   145	2	3	e	java.sql.SQLException
    //   179	29	4	localObject	Object
    //   169	3	5	e	java.sql.SQLException
    //   200	3	5	e	java.sql.SQLException
    //   229	3	5	e	java.sql.SQLException
    // Exception table:
    //   from	to	target	type
    //   17	142	145	java/sql/SQLException
    //   150	166	169	java/sql/SQLException
    //   17	150	179	finally
    //   181	197	200	java/sql/SQLException
    //   210	226	229	java/sql/SQLException
  }
  
  /* Error */
  public void findRole(LoginBean Lbean)
  {
	   
    // Byte code:
    //   0: aload_0
    //   1: invokestatic 47	com/ConnectionProvider:getCon	()Ljava/sql/Connection;
    //   4: putfield 24	com/LoginDao:con	Ljava/sql/Connection;
    //   7: aload_0
    //   8: ldc_w 272
    //   11: putfield 34	com/LoginDao:query	Ljava/lang/String;
    //   14: aload_0
    //   15: aload_0
    //   16: getfield 24	com/LoginDao:con	Ljava/sql/Connection;
    //   19: aload_0
    //   20: getfield 34	com/LoginDao:query	Ljava/lang/String;
    //   23: invokeinterface 55 2 0
    //   28: putfield 26	com/LoginDao:ptmt	Ljava/sql/PreparedStatement;
    //   31: aload_0
    //   32: getfield 26	com/LoginDao:ptmt	Ljava/sql/PreparedStatement;
    //   35: iconst_1
    //   36: aload_1
    //   37: invokevirtual 274	com/LoginBean:getRole_id	()Ljava/lang/String;
    //   40: invokeinterface 67 3 0
    //   45: aload_0
    //   46: aload_0
    //   47: getfield 26	com/LoginDao:ptmt	Ljava/sql/PreparedStatement;
    //   50: invokeinterface 73 1 0
    //   55: putfield 28	com/LoginDao:rs	Ljava/sql/ResultSet;
    //   58: goto +33 -> 91
    //   61: aload_1
    //   62: aload_0
    //   63: getfield 28	com/LoginDao:rs	Ljava/sql/ResultSet;
    //   66: ldc -62
    //   68: invokeinterface 132 2 0
    //   73: invokevirtual 196	com/LoginBean:setRole_id	(Ljava/lang/String;)V
    //   76: aload_1
    //   77: aload_0
    //   78: getfield 28	com/LoginDao:rs	Ljava/sql/ResultSet;
    //   81: ldc -57
    //   83: invokeinterface 132 2 0
    //   88: invokevirtual 201	com/LoginBean:setRole_desc	(Ljava/lang/String;)V
    //   91: aload_0
    //   92: getfield 28	com/LoginDao:rs	Ljava/sql/ResultSet;
    //   95: invokeinterface 77 1 0
    //   100: ifne -39 -> 61
    //   103: goto +86 -> 189
    //   106: astore_2
    //   107: aload_2
    //   108: invokevirtual 212	java/sql/SQLException:printStackTrace	()V
    //   111: aload_0
    //   112: getfield 26	com/LoginDao:ptmt	Ljava/sql/PreparedStatement;
    //   115: ifnull +110 -> 225
    //   118: aload_0
    //   119: getfield 26	com/LoginDao:ptmt	Ljava/sql/PreparedStatement;
    //   122: invokeinterface 217 1 0
    //   127: goto +98 -> 225
    //   130: astore 4
    //   132: aload 4
    //   134: invokevirtual 212	java/sql/SQLException:printStackTrace	()V
    //   137: goto +88 -> 225
    //   140: astore 4
    //   142: aload 4
    //   144: invokevirtual 277	java/lang/Exception:printStackTrace	()V
    //   147: goto +78 -> 225
    //   150: astore_3
    //   151: aload_0
    //   152: getfield 26	com/LoginDao:ptmt	Ljava/sql/PreparedStatement;
    //   155: ifnull +32 -> 187
    //   158: aload_0
    //   159: getfield 26	com/LoginDao:ptmt	Ljava/sql/PreparedStatement;
    //   162: invokeinterface 217 1 0
    //   167: goto +20 -> 187
    //   170: astore 4
    //   172: aload 4
    //   174: invokevirtual 212	java/sql/SQLException:printStackTrace	()V
    //   177: goto +10 -> 187
    //   180: astore 4
    //   182: aload 4
    //   184: invokevirtual 277	java/lang/Exception:printStackTrace	()V
    //   187: aload_3
    //   188: athrow
    //   189: aload_0
    //   190: getfield 26	com/LoginDao:ptmt	Ljava/sql/PreparedStatement;
    //   193: ifnull +32 -> 225
    //   196: aload_0
    //   197: getfield 26	com/LoginDao:ptmt	Ljava/sql/PreparedStatement;
    //   200: invokeinterface 217 1 0
    //   205: goto +20 -> 225
    //   208: astore 4
    //   210: aload 4
    //   212: invokevirtual 212	java/sql/SQLException:printStackTrace	()V
    //   215: goto +10 -> 225
    //   218: astore 4
    //   220: aload 4
    //   222: invokevirtual 277	java/lang/Exception:printStackTrace	()V
    //   225: return
    // Line number table:
    //   Java source line #240	-> byte code offset #0
    //   Java source line #241	-> byte code offset #7
    //   Java source line #242	-> byte code offset #14
    //   Java source line #243	-> byte code offset #31
    //   Java source line #244	-> byte code offset #45
    //   Java source line #245	-> byte code offset #58
    //   Java source line #246	-> byte code offset #61
    //   Java source line #247	-> byte code offset #76
    //   Java source line #245	-> byte code offset #91
    //   Java source line #250	-> byte code offset #103
    //   Java source line #251	-> byte code offset #107
    //   Java source line #253	-> byte code offset #111
    //   Java source line #254	-> byte code offset #118
    //   Java source line #255	-> byte code offset #127
    //   Java source line #256	-> byte code offset #140
    //   Java source line #257	-> byte code offset #142
    //   Java source line #252	-> byte code offset #150
    //   Java source line #253	-> byte code offset #151
    //   Java source line #254	-> byte code offset #158
    //   Java source line #255	-> byte code offset #167
    //   Java source line #256	-> byte code offset #180
    //   Java source line #257	-> byte code offset #182
    //   Java source line #259	-> byte code offset #187
    //   Java source line #253	-> byte code offset #189
    //   Java source line #254	-> byte code offset #196
    //   Java source line #255	-> byte code offset #205
    //   Java source line #256	-> byte code offset #218
    //   Java source line #257	-> byte code offset #220
    //   Java source line #260	-> byte code offset #225
    // Local variable table:
    //   start	length	slot	name	signature
    //   0	226	0	this	LoginDao
    //   0	226	1	Lbean	LoginBean
    //   106	2	2	e	java.sql.SQLException
    //   150	38	3	localObject	Object
    //   130	3	4	e	java.sql.SQLException
    //   140	3	4	e	Exception
    //   170	3	4	e	java.sql.SQLException
    //   180	3	4	e	Exception
    //   208	3	4	e	java.sql.SQLException
    //   218	3	4	e	Exception
    // Exception table:
    //   from	to	target	type
    //   0	103	106	java/sql/SQLException
    //   111	127	130	java/sql/SQLException
    //   111	127	140	java/lang/Exception
    //   0	111	150	finally
    //   151	167	170	java/sql/SQLException
    //   151	167	180	java/lang/Exception
    //   189	205	208	java/sql/SQLException
    //   189	205	218	java/lang/Exception
  }
  
  /* Error */
  public java.util.List<LoginBean> listRoleMenu(int Roleid)
  {
	   return null;
    // Byte code:
    //   0: aload_0
    //   1: ldc_w 280
    //   4: putfield 34	com/LoginDao:query	Ljava/lang/String;
    //   7: new 186	java/util/ArrayList
    //   10: dup
    //   11: invokespecial 188	java/util/ArrayList:<init>	()V
    //   14: astore_2
    //   15: aconst_null
    //   16: astore_3
    //   17: aload_0
    //   18: invokestatic 47	com/ConnectionProvider:getCon	()Ljava/sql/Connection;
    //   21: putfield 24	com/LoginDao:con	Ljava/sql/Connection;
    //   24: aload_0
    //   25: aload_0
    //   26: getfield 24	com/LoginDao:con	Ljava/sql/Connection;
    //   29: aload_0
    //   30: getfield 34	com/LoginDao:query	Ljava/lang/String;
    //   33: invokeinterface 55 2 0
    //   38: putfield 26	com/LoginDao:ptmt	Ljava/sql/PreparedStatement;
    //   41: aload_0
    //   42: getfield 26	com/LoginDao:ptmt	Ljava/sql/PreparedStatement;
    //   45: iconst_1
    //   46: iload_1
    //   47: invokeinterface 189 3 0
    //   52: aload_0
    //   53: aload_0
    //   54: getfield 26	com/LoginDao:ptmt	Ljava/sql/PreparedStatement;
    //   57: invokeinterface 73 1 0
    //   62: putfield 28	com/LoginDao:rs	Ljava/sql/ResultSet;
    //   65: goto +65 -> 130
    //   68: new 62	com/LoginBean
    //   71: dup
    //   72: invokespecial 193	com/LoginBean:<init>	()V
    //   75: astore_3
    //   76: aload_3
    //   77: aload_0
    //   78: getfield 28	com/LoginDao:rs	Ljava/sql/ResultSet;
    //   81: ldc -26
    //   83: invokeinterface 143 2 0
    //   88: invokevirtual 232	com/LoginBean:setModule_id	(I)V
    //   91: aload_3
    //   92: aload_0
    //   93: getfield 28	com/LoginDao:rs	Ljava/sql/ResultSet;
    //   96: ldc -21
    //   98: invokeinterface 132 2 0
    //   103: invokevirtual 237	com/LoginBean:setModule	(Ljava/lang/String;)V
    //   106: aload_3
    //   107: aload_0
    //   108: getfield 28	com/LoginDao:rs	Ljava/sql/ResultSet;
    //   111: ldc_w 282
    //   114: invokeinterface 132 2 0
    //   119: invokevirtual 245	com/LoginBean:setMenu_url	(Ljava/lang/String;)V
    //   122: aload_2
    //   123: aload_3
    //   124: invokeinterface 204 2 0
    //   129: pop
    //   130: aload_0
    //   131: getfield 28	com/LoginDao:rs	Ljava/sql/ResultSet;
    //   134: invokeinterface 77 1 0
    //   139: ifne -71 -> 68
    //   142: aload_0
    //   143: getfield 28	com/LoginDao:rs	Ljava/sql/ResultSet;
    //   146: invokeinterface 209 1 0
    //   151: goto +70 -> 221
    //   154: astore 4
    //   156: aload 4
    //   158: invokevirtual 212	java/sql/SQLException:printStackTrace	()V
    //   161: aload_0
    //   162: getfield 26	com/LoginDao:ptmt	Ljava/sql/PreparedStatement;
    //   165: ifnull +82 -> 247
    //   168: aload_0
    //   169: getfield 26	com/LoginDao:ptmt	Ljava/sql/PreparedStatement;
    //   172: invokeinterface 217 1 0
    //   177: goto +70 -> 247
    //   180: astore 6
    //   182: aload 6
    //   184: invokevirtual 212	java/sql/SQLException:printStackTrace	()V
    //   187: goto +60 -> 247
    //   190: astore 5
    //   192: aload_0
    //   193: getfield 26	com/LoginDao:ptmt	Ljava/sql/PreparedStatement;
    //   196: ifnull +22 -> 218
    //   199: aload_0
    //   200: getfield 26	com/LoginDao:ptmt	Ljava/sql/PreparedStatement;
    //   203: invokeinterface 217 1 0
    //   208: goto +10 -> 218
    //   211: astore 6
    //   213: aload 6
    //   215: invokevirtual 212	java/sql/SQLException:printStackTrace	()V
    //   218: aload 5
    //   220: athrow
    //   221: aload_0
    //   222: getfield 26	com/LoginDao:ptmt	Ljava/sql/PreparedStatement;
    //   225: ifnull +22 -> 247
    //   228: aload_0
    //   229: getfield 26	com/LoginDao:ptmt	Ljava/sql/PreparedStatement;
    //   232: invokeinterface 217 1 0
    //   237: goto +10 -> 247
    //   240: astore 6
    //   242: aload 6
    //   244: invokevirtual 212	java/sql/SQLException:printStackTrace	()V
    //   247: aload_2
    //   248: areturn
    // Line number table:
    //   Java source line #267	-> byte code offset #0
    //   Java source line #269	-> byte code offset #7
    //   Java source line #270	-> byte code offset #15
    //   Java source line #272	-> byte code offset #17
    //   Java source line #273	-> byte code offset #24
    //   Java source line #274	-> byte code offset #41
    //   Java source line #275	-> byte code offset #52
    //   Java source line #277	-> byte code offset #65
    //   Java source line #278	-> byte code offset #68
    //   Java source line #279	-> byte code offset #76
    //   Java source line #280	-> byte code offset #91
    //   Java source line #281	-> byte code offset #106
    //   Java source line #282	-> byte code offset #122
    //   Java source line #277	-> byte code offset #130
    //   Java source line #284	-> byte code offset #142
    //   Java source line #285	-> byte code offset #151
    //   Java source line #289	-> byte code offset #161
    //   Java source line #290	-> byte code offset #168
    //   Java source line #291	-> byte code offset #177
    //   Java source line #292	-> byte code offset #182
    //   Java source line #287	-> byte code offset #190
    //   Java source line #289	-> byte code offset #192
    //   Java source line #290	-> byte code offset #199
    //   Java source line #291	-> byte code offset #208
    //   Java source line #292	-> byte code offset #213
    //   Java source line #294	-> byte code offset #218
    //   Java source line #289	-> byte code offset #221
    //   Java source line #290	-> byte code offset #228
    //   Java source line #291	-> byte code offset #237
    //   Java source line #292	-> byte code offset #242
    //   Java source line #295	-> byte code offset #247
    // Local variable table:
    //   start	length	slot	name	signature
    //   0	249	0	this	LoginDao
    //   0	249	1	Roleid	int
    //   14	234	2	list	java.util.List<LoginBean>
    //   16	108	3	menu	LoginBean
    //   154	3	4	e	java.sql.SQLException
    //   190	29	5	localObject	Object
    //   180	3	6	e	java.sql.SQLException
    //   211	3	6	e	java.sql.SQLException
    //   240	3	6	e	java.sql.SQLException
    // Exception table:
    //   from	to	target	type
    //   17	151	154	java/sql/SQLException
    //   161	177	180	java/sql/SQLException
    //   17	161	190	finally
    //   192	208	211	java/sql/SQLException
    //   221	237	240	java/sql/SQLException
  }
  
  /* Error */
  public void addRole(int oid, String name, String[] module)
  {
	   
    // Byte code:
    //   0: ldc_w 286
    //   3: astore 4
    //   5: aload_0
    //   6: invokestatic 47	com/ConnectionProvider:getCon	()Ljava/sql/Connection;
    //   9: putfield 24	com/LoginDao:con	Ljava/sql/Connection;
    //   12: aload_0
    //   13: ldc_w 288
    //   16: putfield 34	com/LoginDao:query	Ljava/lang/String;
    //   19: aload_0
    //   20: aload_0
    //   21: getfield 24	com/LoginDao:con	Ljava/sql/Connection;
    //   24: invokeinterface 290 1 0
    //   29: putfield 32	com/LoginDao:stmt	Ljava/sql/Statement;
    //   32: getstatic 83	java/lang/System:out	Ljava/io/PrintStream;
    //   35: aload_0
    //   36: getfield 34	com/LoginDao:query	Ljava/lang/String;
    //   39: invokevirtual 121	java/io/PrintStream:println	(Ljava/lang/String;)V
    //   42: aload_0
    //   43: aload_0
    //   44: getfield 32	com/LoginDao:stmt	Ljava/sql/Statement;
    //   47: aload_0
    //   48: getfield 34	com/LoginDao:query	Ljava/lang/String;
    //   51: invokeinterface 294 2 0
    //   56: putfield 28	com/LoginDao:rs	Ljava/sql/ResultSet;
    //   59: goto +16 -> 75
    //   62: aload_0
    //   63: getfield 28	com/LoginDao:rs	Ljava/sql/ResultSet;
    //   66: ldc -62
    //   68: invokeinterface 132 2 0
    //   73: astore 4
    //   75: aload_0
    //   76: getfield 28	com/LoginDao:rs	Ljava/sql/ResultSet;
    //   79: invokeinterface 77 1 0
    //   84: ifne -22 -> 62
    //   87: aload_0
    //   88: ldc_w 299
    //   91: putfield 34	com/LoginDao:query	Ljava/lang/String;
    //   94: aload_0
    //   95: aload_0
    //   96: getfield 24	com/LoginDao:con	Ljava/sql/Connection;
    //   99: aload_0
    //   100: getfield 34	com/LoginDao:query	Ljava/lang/String;
    //   103: invokeinterface 55 2 0
    //   108: putfield 26	com/LoginDao:ptmt	Ljava/sql/PreparedStatement;
    //   111: aload_0
    //   112: getfield 26	com/LoginDao:ptmt	Ljava/sql/PreparedStatement;
    //   115: iconst_1
    //   116: aload 4
    //   118: invokeinterface 67 3 0
    //   123: aload_0
    //   124: getfield 26	com/LoginDao:ptmt	Ljava/sql/PreparedStatement;
    //   127: iconst_2
    //   128: aload_2
    //   129: invokeinterface 67 3 0
    //   134: aload_0
    //   135: getfield 26	com/LoginDao:ptmt	Ljava/sql/PreparedStatement;
    //   138: iconst_3
    //   139: iload_1
    //   140: invokeinterface 189 3 0
    //   145: aload_0
    //   146: getfield 26	com/LoginDao:ptmt	Ljava/sql/PreparedStatement;
    //   149: invokeinterface 301 1 0
    //   154: pop
    //   155: aload_3
    //   156: ifnull +185 -> 341
    //   159: iconst_0
    //   160: istore 5
    //   162: goto +82 -> 244
    //   165: aload_0
    //   166: ldc_w 305
    //   169: putfield 34	com/LoginDao:query	Ljava/lang/String;
    //   172: aload_0
    //   173: aload_0
    //   174: getfield 24	com/LoginDao:con	Ljava/sql/Connection;
    //   177: aload_0
    //   178: getfield 34	com/LoginDao:query	Ljava/lang/String;
    //   181: invokeinterface 55 2 0
    //   186: putfield 26	com/LoginDao:ptmt	Ljava/sql/PreparedStatement;
    //   189: aload_0
    //   190: getfield 26	com/LoginDao:ptmt	Ljava/sql/PreparedStatement;
    //   193: iconst_1
    //   194: aload 4
    //   196: invokestatic 307	java/lang/Integer:parseInt	(Ljava/lang/String;)I
    //   199: invokeinterface 189 3 0
    //   204: aload_0
    //   205: getfield 26	com/LoginDao:ptmt	Ljava/sql/PreparedStatement;
    //   208: iconst_2
    //   209: aload_3
    //   210: iload 5
    //   212: aaload
    //   213: invokestatic 307	java/lang/Integer:parseInt	(Ljava/lang/String;)I
    //   216: invokeinterface 189 3 0
    //   221: aload_0
    //   222: getfield 26	com/LoginDao:ptmt	Ljava/sql/PreparedStatement;
    //   225: invokeinterface 301 1 0
    //   230: pop
    //   231: getstatic 83	java/lang/System:out	Ljava/io/PrintStream;
    //   234: aload_3
    //   235: iload 5
    //   237: aaload
    //   238: invokevirtual 121	java/io/PrintStream:println	(Ljava/lang/String;)V
    //   241: iinc 5 1
    //   244: iload 5
    //   246: aload_3
    //   247: arraylength
    //   248: if_icmplt -83 -> 165
    //   251: goto +90 -> 341
    //   254: astore 5
    //   256: aload 5
    //   258: invokevirtual 212	java/sql/SQLException:printStackTrace	()V
    //   261: aload_0
    //   262: getfield 32	com/LoginDao:stmt	Ljava/sql/Statement;
    //   265: ifnull +112 -> 377
    //   268: aload_0
    //   269: getfield 32	com/LoginDao:stmt	Ljava/sql/Statement;
    //   272: invokeinterface 312 1 0
    //   277: goto +100 -> 377
    //   280: astore 7
    //   282: aload 7
    //   284: invokevirtual 212	java/sql/SQLException:printStackTrace	()V
    //   287: goto +90 -> 377
    //   290: astore 7
    //   292: aload 7
    //   294: invokevirtual 277	java/lang/Exception:printStackTrace	()V
    //   297: goto +80 -> 377
    //   300: astore 6
    //   302: aload_0
    //   303: getfield 32	com/LoginDao:stmt	Ljava/sql/Statement;
    //   306: ifnull +32 -> 338
    //   309: aload_0
    //   310: getfield 32	com/LoginDao:stmt	Ljava/sql/Statement;
    //   313: invokeinterface 312 1 0
    //   318: goto +20 -> 338
    //   321: astore 7
    //   323: aload 7
    //   325: invokevirtual 212	java/sql/SQLException:printStackTrace	()V
    //   328: goto +10 -> 338
    //   331: astore 7
    //   333: aload 7
    //   335: invokevirtual 277	java/lang/Exception:printStackTrace	()V
    //   338: aload 6
    //   340: athrow
    //   341: aload_0
    //   342: getfield 32	com/LoginDao:stmt	Ljava/sql/Statement;
    //   345: ifnull +32 -> 377
    //   348: aload_0
    //   349: getfield 32	com/LoginDao:stmt	Ljava/sql/Statement;
    //   352: invokeinterface 312 1 0
    //   357: goto +20 -> 377
    //   360: astore 7
    //   362: aload 7
    //   364: invokevirtual 212	java/sql/SQLException:printStackTrace	()V
    //   367: goto +10 -> 377
    //   370: astore 7
    //   372: aload 7
    //   374: invokevirtual 277	java/lang/Exception:printStackTrace	()V
    //   377: return
    // Line number table:
    //   Java source line #299	-> byte code offset #0
    //   Java source line #301	-> byte code offset #5
    //   Java source line #302	-> byte code offset #12
    //   Java source line #303	-> byte code offset #19
    //   Java source line #304	-> byte code offset #32
    //   Java source line #305	-> byte code offset #42
    //   Java source line #306	-> byte code offset #59
    //   Java source line #307	-> byte code offset #62
    //   Java source line #306	-> byte code offset #75
    //   Java source line #310	-> byte code offset #87
    //   Java source line #312	-> byte code offset #94
    //   Java source line #313	-> byte code offset #111
    //   Java source line #314	-> byte code offset #123
    //   Java source line #315	-> byte code offset #134
    //   Java source line #317	-> byte code offset #145
    //   Java source line #319	-> byte code offset #155
    //   Java source line #320	-> byte code offset #159
    //   Java source line #321	-> byte code offset #165
    //   Java source line #322	-> byte code offset #172
    //   Java source line #323	-> byte code offset #189
    //   Java source line #324	-> byte code offset #204
    //   Java source line #326	-> byte code offset #221
    //   Java source line #327	-> byte code offset #231
    //   Java source line #320	-> byte code offset #241
    //   Java source line #330	-> byte code offset #251
    //   Java source line #331	-> byte code offset #256
    //   Java source line #334	-> byte code offset #261
    //   Java source line #335	-> byte code offset #268
    //   Java source line #336	-> byte code offset #277
    //   Java source line #337	-> byte code offset #282
    //   Java source line #338	-> byte code offset #290
    //   Java source line #339	-> byte code offset #292
    //   Java source line #332	-> byte code offset #300
    //   Java source line #334	-> byte code offset #302
    //   Java source line #335	-> byte code offset #309
    //   Java source line #336	-> byte code offset #318
    //   Java source line #337	-> byte code offset #323
    //   Java source line #338	-> byte code offset #331
    //   Java source line #339	-> byte code offset #333
    //   Java source line #342	-> byte code offset #338
    //   Java source line #334	-> byte code offset #341
    //   Java source line #335	-> byte code offset #348
    //   Java source line #336	-> byte code offset #357
    //   Java source line #337	-> byte code offset #362
    //   Java source line #338	-> byte code offset #370
    //   Java source line #339	-> byte code offset #372
    //   Java source line #344	-> byte code offset #377
    // Local variable table:
    //   start	length	slot	name	signature
    //   0	378	0	this	LoginDao
    //   0	378	1	oid	int
    //   0	378	2	name	String
    //   0	378	3	module	String[]
    //   3	192	4	vroleid	String
    //   160	85	5	i	int
    //   254	3	5	e	java.sql.SQLException
    //   300	39	6	localObject	Object
    //   280	3	7	e	java.sql.SQLException
    //   290	3	7	e	Exception
    //   321	3	7	e	java.sql.SQLException
    //   331	3	7	e	Exception
    //   360	3	7	e	java.sql.SQLException
    //   370	3	7	e	Exception
    // Exception table:
    //   from	to	target	type
    //   5	251	254	java/sql/SQLException
    //   261	277	280	java/sql/SQLException
    //   261	277	290	java/lang/Exception
    //   5	261	300	finally
    //   302	318	321	java/sql/SQLException
    //   302	318	331	java/lang/Exception
    //   341	357	360	java/sql/SQLException
    //   341	357	370	java/lang/Exception
  }
  
  /* Error */
  public void updateRole(int roleid, String name, String[] module)
  {
	
    // Byte code:
    //   0: aload_0
    //   1: invokestatic 47	com/ConnectionProvider:getCon	()Ljava/sql/Connection;
    //   4: putfield 24	com/LoginDao:con	Ljava/sql/Connection;
    //   7: aload_0
    //   8: ldc_w 320
    //   11: putfield 34	com/LoginDao:query	Ljava/lang/String;
    //   14: aload_0
    //   15: aload_0
    //   16: getfield 24	com/LoginDao:con	Ljava/sql/Connection;
    //   19: aload_0
    //   20: getfield 34	com/LoginDao:query	Ljava/lang/String;
    //   23: invokeinterface 55 2 0
    //   28: putfield 26	com/LoginDao:ptmt	Ljava/sql/PreparedStatement;
    //   31: aload_0
    //   32: getfield 26	com/LoginDao:ptmt	Ljava/sql/PreparedStatement;
    //   35: iconst_1
    //   36: aload_2
    //   37: invokeinterface 67 3 0
    //   42: aload_0
    //   43: getfield 26	com/LoginDao:ptmt	Ljava/sql/PreparedStatement;
    //   46: iconst_2
    //   47: iload_1
    //   48: invokestatic 322	java/lang/String:valueOf	(I)Ljava/lang/String;
    //   51: invokeinterface 67 3 0
    //   56: aload_0
    //   57: getfield 26	com/LoginDao:ptmt	Ljava/sql/PreparedStatement;
    //   60: invokeinterface 301 1 0
    //   65: pop
    //   66: aload_0
    //   67: ldc_w 325
    //   70: putfield 34	com/LoginDao:query	Ljava/lang/String;
    //   73: aload_0
    //   74: aload_0
    //   75: getfield 24	com/LoginDao:con	Ljava/sql/Connection;
    //   78: aload_0
    //   79: getfield 34	com/LoginDao:query	Ljava/lang/String;
    //   82: invokeinterface 55 2 0
    //   87: putfield 26	com/LoginDao:ptmt	Ljava/sql/PreparedStatement;
    //   90: aload_0
    //   91: getfield 26	com/LoginDao:ptmt	Ljava/sql/PreparedStatement;
    //   94: iconst_1
    //   95: iload_1
    //   96: invokeinterface 189 3 0
    //   101: aload_0
    //   102: getfield 26	com/LoginDao:ptmt	Ljava/sql/PreparedStatement;
    //   105: invokeinterface 301 1 0
    //   110: pop
    //   111: aload_3
    //   112: ifnull +171 -> 283
    //   115: iconst_0
    //   116: istore 4
    //   118: goto +68 -> 186
    //   121: aload_0
    //   122: ldc_w 305
    //   125: putfield 34	com/LoginDao:query	Ljava/lang/String;
    //   128: aload_0
    //   129: aload_0
    //   130: getfield 24	com/LoginDao:con	Ljava/sql/Connection;
    //   133: aload_0
    //   134: getfield 34	com/LoginDao:query	Ljava/lang/String;
    //   137: invokeinterface 55 2 0
    //   142: putfield 26	com/LoginDao:ptmt	Ljava/sql/PreparedStatement;
    //   145: aload_0
    //   146: getfield 26	com/LoginDao:ptmt	Ljava/sql/PreparedStatement;
    //   149: iconst_1
    //   150: iload_1
    //   151: invokeinterface 189 3 0
    //   156: aload_0
    //   157: getfield 26	com/LoginDao:ptmt	Ljava/sql/PreparedStatement;
    //   160: iconst_2
    //   161: aload_3
    //   162: iload 4
    //   164: aaload
    //   165: invokestatic 307	java/lang/Integer:parseInt	(Ljava/lang/String;)I
    //   168: invokeinterface 189 3 0
    //   173: aload_0
    //   174: getfield 26	com/LoginDao:ptmt	Ljava/sql/PreparedStatement;
    //   177: invokeinterface 301 1 0
    //   182: pop
    //   183: iinc 4 1
    //   186: iload 4
    //   188: aload_3
    //   189: arraylength
    //   190: if_icmplt -69 -> 121
    //   193: goto +90 -> 283
    //   196: astore 4
    //   198: aload 4
    //   200: invokevirtual 212	java/sql/SQLException:printStackTrace	()V
    //   203: aload_0
    //   204: getfield 32	com/LoginDao:stmt	Ljava/sql/Statement;
    //   207: ifnull +112 -> 319
    //   210: aload_0
    //   211: getfield 32	com/LoginDao:stmt	Ljava/sql/Statement;
    //   214: invokeinterface 312 1 0
    //   219: goto +100 -> 319
    //   222: astore 6
    //   224: aload 6
    //   226: invokevirtual 212	java/sql/SQLException:printStackTrace	()V
    //   229: goto +90 -> 319
    //   232: astore 6
    //   234: aload 6
    //   236: invokevirtual 277	java/lang/Exception:printStackTrace	()V
    //   239: goto +80 -> 319
    //   242: astore 5
    //   244: aload_0
    //   245: getfield 32	com/LoginDao:stmt	Ljava/sql/Statement;
    //   248: ifnull +32 -> 280
    //   251: aload_0
    //   252: getfield 32	com/LoginDao:stmt	Ljava/sql/Statement;
    //   255: invokeinterface 312 1 0
    //   260: goto +20 -> 280
    //   263: astore 6
    //   265: aload 6
    //   267: invokevirtual 212	java/sql/SQLException:printStackTrace	()V
    //   270: goto +10 -> 280
    //   273: astore 6
    //   275: aload 6
    //   277: invokevirtual 277	java/lang/Exception:printStackTrace	()V
    //   280: aload 5
    //   282: athrow
    //   283: aload_0
    //   284: getfield 32	com/LoginDao:stmt	Ljava/sql/Statement;
    //   287: ifnull +32 -> 319
    //   290: aload_0
    //   291: getfield 32	com/LoginDao:stmt	Ljava/sql/Statement;
    //   294: invokeinterface 312 1 0
    //   299: goto +20 -> 319
    //   302: astore 6
    //   304: aload 6
    //   306: invokevirtual 212	java/sql/SQLException:printStackTrace	()V
    //   309: goto +10 -> 319
    //   312: astore 6
    //   314: aload 6
    //   316: invokevirtual 277	java/lang/Exception:printStackTrace	()V
    //   319: return
    // Line number table:
    //   Java source line #348	-> byte code offset #0
    //   Java source line #349	-> byte code offset #7
    //   Java source line #350	-> byte code offset #14
    //   Java source line #351	-> byte code offset #31
    //   Java source line #352	-> byte code offset #42
    //   Java source line #353	-> byte code offset #56
    //   Java source line #354	-> byte code offset #66
    //   Java source line #355	-> byte code offset #73
    //   Java source line #356	-> byte code offset #90
    //   Java source line #357	-> byte code offset #101
    //   Java source line #358	-> byte code offset #111
    //   Java source line #359	-> byte code offset #115
    //   Java source line #360	-> byte code offset #121
    //   Java source line #361	-> byte code offset #128
    //   Java source line #362	-> byte code offset #145
    //   Java source line #363	-> byte code offset #156
    //   Java source line #364	-> byte code offset #173
    //   Java source line #359	-> byte code offset #183
    //   Java source line #367	-> byte code offset #193
    //   Java source line #368	-> byte code offset #198
    //   Java source line #371	-> byte code offset #203
    //   Java source line #372	-> byte code offset #210
    //   Java source line #373	-> byte code offset #219
    //   Java source line #374	-> byte code offset #224
    //   Java source line #375	-> byte code offset #232
    //   Java source line #376	-> byte code offset #234
    //   Java source line #369	-> byte code offset #242
    //   Java source line #371	-> byte code offset #244
    //   Java source line #372	-> byte code offset #251
    //   Java source line #373	-> byte code offset #260
    //   Java source line #374	-> byte code offset #265
    //   Java source line #375	-> byte code offset #273
    //   Java source line #376	-> byte code offset #275
    //   Java source line #379	-> byte code offset #280
    //   Java source line #371	-> byte code offset #283
    //   Java source line #372	-> byte code offset #290
    //   Java source line #373	-> byte code offset #299
    //   Java source line #374	-> byte code offset #304
    //   Java source line #375	-> byte code offset #312
    //   Java source line #376	-> byte code offset #314
    //   Java source line #380	-> byte code offset #319
    // Local variable table:
    //   start	length	slot	name	signature
    //   0	320	0	this	LoginDao
    //   0	320	1	roleid	int
    //   0	320	2	name	String
    //   0	320	3	module	String[]
    //   116	71	4	i	int
    //   196	3	4	e	java.sql.SQLException
    //   242	39	5	localObject	Object
    //   222	3	6	e	java.sql.SQLException
    //   232	3	6	e	Exception
    //   263	3	6	e	java.sql.SQLException
    //   273	3	6	e	Exception
    //   302	3	6	e	java.sql.SQLException
    //   312	3	6	e	Exception
    // Exception table:
    //   from	to	target	type
    //   0	193	196	java/sql/SQLException
    //   203	219	222	java/sql/SQLException
    //   203	219	232	java/lang/Exception
    //   0	203	242	finally
    //   244	260	263	java/sql/SQLException
    //   244	260	273	java/lang/Exception
    //   283	299	302	java/sql/SQLException
    //   283	299	312	java/lang/Exception
  }
  
  /* Error */
  public void delRole(int rid)
  {
    // Byte code:
    //   0: iconst_0
    //   1: istore_2
    //   2: aload_0
    //   3: invokestatic 47	com/ConnectionProvider:getCon	()Ljava/sql/Connection;
    //   6: putfield 24	com/LoginDao:con	Ljava/sql/Connection;
    //   9: aload_0
    //   10: ldc_w 329
    //   13: putfield 34	com/LoginDao:query	Ljava/lang/String;
    //   16: aload_0
    //   17: aload_0
    //   18: getfield 24	com/LoginDao:con	Ljava/sql/Connection;
    //   21: aload_0
    //   22: getfield 34	com/LoginDao:query	Ljava/lang/String;
    //   25: invokeinterface 55 2 0
    //   30: putfield 26	com/LoginDao:ptmt	Ljava/sql/PreparedStatement;
    //   33: aload_0
    //   34: getfield 26	com/LoginDao:ptmt	Ljava/sql/PreparedStatement;
    //   37: iconst_1
    //   38: iload_1
    //   39: invokeinterface 189 3 0
    //   44: aload_0
    //   45: aload_0
    //   46: getfield 26	com/LoginDao:ptmt	Ljava/sql/PreparedStatement;
    //   49: invokeinterface 73 1 0
    //   54: putfield 28	com/LoginDao:rs	Ljava/sql/ResultSet;
    //   57: goto +16 -> 73
    //   60: aload_0
    //   61: getfield 28	com/LoginDao:rs	Ljava/sql/ResultSet;
    //   64: ldc_w 331
    //   67: invokeinterface 143 2 0
    //   72: istore_2
    //   73: aload_0
    //   74: getfield 28	com/LoginDao:rs	Ljava/sql/ResultSet;
    //   77: invokeinterface 77 1 0
    //   82: ifne -22 -> 60
    //   85: iload_2
    //   86: ifne +182 -> 268
    //   89: aload_0
    //   90: ldc_w 333
    //   93: putfield 34	com/LoginDao:query	Ljava/lang/String;
    //   96: aload_0
    //   97: aload_0
    //   98: getfield 24	com/LoginDao:con	Ljava/sql/Connection;
    //   101: aload_0
    //   102: getfield 34	com/LoginDao:query	Ljava/lang/String;
    //   105: invokeinterface 55 2 0
    //   110: putfield 26	com/LoginDao:ptmt	Ljava/sql/PreparedStatement;
    //   113: aload_0
    //   114: getfield 26	com/LoginDao:ptmt	Ljava/sql/PreparedStatement;
    //   117: iconst_1
    //   118: iload_1
    //   119: invokeinterface 189 3 0
    //   124: aload_0
    //   125: getfield 26	com/LoginDao:ptmt	Ljava/sql/PreparedStatement;
    //   128: invokeinterface 301 1 0
    //   133: pop
    //   134: aload_0
    //   135: ldc_w 335
    //   138: putfield 34	com/LoginDao:query	Ljava/lang/String;
    //   141: aload_0
    //   142: aload_0
    //   143: getfield 24	com/LoginDao:con	Ljava/sql/Connection;
    //   146: aload_0
    //   147: getfield 34	com/LoginDao:query	Ljava/lang/String;
    //   150: invokeinterface 55 2 0
    //   155: putfield 26	com/LoginDao:ptmt	Ljava/sql/PreparedStatement;
    //   158: aload_0
    //   159: getfield 26	com/LoginDao:ptmt	Ljava/sql/PreparedStatement;
    //   162: iconst_1
    //   163: iload_1
    //   164: invokestatic 322	java/lang/String:valueOf	(I)Ljava/lang/String;
    //   167: invokeinterface 67 3 0
    //   172: aload_0
    //   173: getfield 26	com/LoginDao:ptmt	Ljava/sql/PreparedStatement;
    //   176: invokeinterface 301 1 0
    //   181: pop
    //   182: goto +86 -> 268
    //   185: astore_2
    //   186: aload_2
    //   187: invokevirtual 212	java/sql/SQLException:printStackTrace	()V
    //   190: aload_0
    //   191: getfield 26	com/LoginDao:ptmt	Ljava/sql/PreparedStatement;
    //   194: ifnull +110 -> 304
    //   197: aload_0
    //   198: getfield 26	com/LoginDao:ptmt	Ljava/sql/PreparedStatement;
    //   201: invokeinterface 217 1 0
    //   206: goto +98 -> 304
    //   209: astore 4
    //   211: aload 4
    //   213: invokevirtual 212	java/sql/SQLException:printStackTrace	()V
    //   216: goto +88 -> 304
    //   219: astore 4
    //   221: aload 4
    //   223: invokevirtual 277	java/lang/Exception:printStackTrace	()V
    //   226: goto +78 -> 304
    //   229: astore_3
    //   230: aload_0
    //   231: getfield 26	com/LoginDao:ptmt	Ljava/sql/PreparedStatement;
    //   234: ifnull +32 -> 266
    //   237: aload_0
    //   238: getfield 26	com/LoginDao:ptmt	Ljava/sql/PreparedStatement;
    //   241: invokeinterface 217 1 0
    //   246: goto +20 -> 266
    //   249: astore 4
    //   251: aload 4
    //   253: invokevirtual 212	java/sql/SQLException:printStackTrace	()V
    //   256: goto +10 -> 266
    //   259: astore 4
    //   261: aload 4
    //   263: invokevirtual 277	java/lang/Exception:printStackTrace	()V
    //   266: aload_3
    //   267: athrow
    //   268: aload_0
    //   269: getfield 26	com/LoginDao:ptmt	Ljava/sql/PreparedStatement;
    //   272: ifnull +32 -> 304
    //   275: aload_0
    //   276: getfield 26	com/LoginDao:ptmt	Ljava/sql/PreparedStatement;
    //   279: invokeinterface 217 1 0
    //   284: goto +20 -> 304
    //   287: astore 4
    //   289: aload 4
    //   291: invokevirtual 212	java/sql/SQLException:printStackTrace	()V
    //   294: goto +10 -> 304
    //   297: astore 4
    //   299: aload 4
    //   301: invokevirtual 277	java/lang/Exception:printStackTrace	()V
    //   304: return
    // Line number table:
    //   Java source line #385	-> byte code offset #0
    //   Java source line #386	-> byte code offset #2
    //   Java source line #388	-> byte code offset #9
    //   Java source line #389	-> byte code offset #16
    //   Java source line #390	-> byte code offset #33
    //   Java source line #391	-> byte code offset #44
    //   Java source line #392	-> byte code offset #57
    //   Java source line #393	-> byte code offset #60
    //   Java source line #392	-> byte code offset #73
    //   Java source line #395	-> byte code offset #85
    //   Java source line #396	-> byte code offset #89
    //   Java source line #397	-> byte code offset #96
    //   Java source line #398	-> byte code offset #113
    //   Java source line #399	-> byte code offset #124
    //   Java source line #401	-> byte code offset #134
    //   Java source line #402	-> byte code offset #141
    //   Java source line #403	-> byte code offset #158
    //   Java source line #404	-> byte code offset #172
    //   Java source line #406	-> byte code offset #182
    //   Java source line #407	-> byte code offset #186
    //   Java source line #410	-> byte code offset #190
    //   Java source line #411	-> byte code offset #197
    //   Java source line #412	-> byte code offset #206
    //   Java source line #413	-> byte code offset #211
    //   Java source line #414	-> byte code offset #219
    //   Java source line #415	-> byte code offset #221
    //   Java source line #408	-> byte code offset #229
    //   Java source line #410	-> byte code offset #230
    //   Java source line #411	-> byte code offset #237
    //   Java source line #412	-> byte code offset #246
    //   Java source line #413	-> byte code offset #251
    //   Java source line #414	-> byte code offset #259
    //   Java source line #415	-> byte code offset #261
    //   Java source line #418	-> byte code offset #266
    //   Java source line #410	-> byte code offset #268
    //   Java source line #411	-> byte code offset #275
    //   Java source line #412	-> byte code offset #284
    //   Java source line #413	-> byte code offset #289
    //   Java source line #414	-> byte code offset #297
    //   Java source line #415	-> byte code offset #299
    //   Java source line #420	-> byte code offset #304
    // Local variable table:
    //   start	length	slot	name	signature
    //   0	305	0	this	LoginDao
    //   0	305	1	rid	int
    //   1	85	2	vusers	int
    //   185	2	2	e	java.sql.SQLException
    //   229	38	3	localObject	Object
    //   209	3	4	e	java.sql.SQLException
    //   219	3	4	e	Exception
    //   249	3	4	e	java.sql.SQLException
    //   259	3	4	e	Exception
    //   287	3	4	e	java.sql.SQLException
    //   297	3	4	e	Exception
    // Exception table:
    //   from	to	target	type
    //   0	182	185	java/sql/SQLException
    //   190	206	209	java/sql/SQLException
    //   190	206	219	java/lang/Exception
    //   0	190	229	finally
    //   230	246	249	java/sql/SQLException
    //   230	246	259	java/lang/Exception
    //   268	284	287	java/sql/SQLException
    //   268	284	297	java/lang/Exception
  }
  
  /* Error */
  public void addRoleModule(int rid, int mid)
  {
    // Byte code:
    //   0: aload_0
    //   1: ldc_w 305
    //   4: putfield 34	com/LoginDao:query	Ljava/lang/String;
    //   7: aload_0
    //   8: invokestatic 47	com/ConnectionProvider:getCon	()Ljava/sql/Connection;
    //   11: putfield 24	com/LoginDao:con	Ljava/sql/Connection;
    //   14: aload_0
    //   15: aload_0
    //   16: getfield 24	com/LoginDao:con	Ljava/sql/Connection;
    //   19: aload_0
    //   20: getfield 34	com/LoginDao:query	Ljava/lang/String;
    //   23: invokeinterface 55 2 0
    //   28: putfield 26	com/LoginDao:ptmt	Ljava/sql/PreparedStatement;
    //   31: aload_0
    //   32: getfield 26	com/LoginDao:ptmt	Ljava/sql/PreparedStatement;
    //   35: iconst_1
    //   36: iload_1
    //   37: invokeinterface 189 3 0
    //   42: aload_0
    //   43: getfield 26	com/LoginDao:ptmt	Ljava/sql/PreparedStatement;
    //   46: iconst_2
    //   47: iload_2
    //   48: invokeinterface 189 3 0
    //   53: aload_0
    //   54: getfield 26	com/LoginDao:ptmt	Ljava/sql/PreparedStatement;
    //   57: invokeinterface 301 1 0
    //   62: pop
    //   63: goto +88 -> 151
    //   66: astore_3
    //   67: aload_3
    //   68: invokevirtual 212	java/sql/SQLException:printStackTrace	()V
    //   71: aload_0
    //   72: getfield 26	com/LoginDao:ptmt	Ljava/sql/PreparedStatement;
    //   75: ifnull +112 -> 187
    //   78: aload_0
    //   79: getfield 26	com/LoginDao:ptmt	Ljava/sql/PreparedStatement;
    //   82: invokeinterface 217 1 0
    //   87: goto +100 -> 187
    //   90: astore 5
    //   92: aload 5
    //   94: invokevirtual 212	java/sql/SQLException:printStackTrace	()V
    //   97: goto +90 -> 187
    //   100: astore 5
    //   102: aload 5
    //   104: invokevirtual 277	java/lang/Exception:printStackTrace	()V
    //   107: goto +80 -> 187
    //   110: astore 4
    //   112: aload_0
    //   113: getfield 26	com/LoginDao:ptmt	Ljava/sql/PreparedStatement;
    //   116: ifnull +32 -> 148
    //   119: aload_0
    //   120: getfield 26	com/LoginDao:ptmt	Ljava/sql/PreparedStatement;
    //   123: invokeinterface 217 1 0
    //   128: goto +20 -> 148
    //   131: astore 5
    //   133: aload 5
    //   135: invokevirtual 212	java/sql/SQLException:printStackTrace	()V
    //   138: goto +10 -> 148
    //   141: astore 5
    //   143: aload 5
    //   145: invokevirtual 277	java/lang/Exception:printStackTrace	()V
    //   148: aload 4
    //   150: athrow
    //   151: aload_0
    //   152: getfield 26	com/LoginDao:ptmt	Ljava/sql/PreparedStatement;
    //   155: ifnull +32 -> 187
    //   158: aload_0
    //   159: getfield 26	com/LoginDao:ptmt	Ljava/sql/PreparedStatement;
    //   162: invokeinterface 217 1 0
    //   167: goto +20 -> 187
    //   170: astore 5
    //   172: aload 5
    //   174: invokevirtual 212	java/sql/SQLException:printStackTrace	()V
    //   177: goto +10 -> 187
    //   180: astore 5
    //   182: aload 5
    //   184: invokevirtual 277	java/lang/Exception:printStackTrace	()V
    //   187: return
    // Line number table:
    //   Java source line #426	-> byte code offset #0
    //   Java source line #428	-> byte code offset #7
    //   Java source line #429	-> byte code offset #14
    //   Java source line #430	-> byte code offset #31
    //   Java source line #431	-> byte code offset #42
    //   Java source line #432	-> byte code offset #53
    //   Java source line #433	-> byte code offset #63
    //   Java source line #434	-> byte code offset #67
    //   Java source line #437	-> byte code offset #71
    //   Java source line #438	-> byte code offset #78
    //   Java source line #439	-> byte code offset #87
    //   Java source line #440	-> byte code offset #92
    //   Java source line #441	-> byte code offset #100
    //   Java source line #442	-> byte code offset #102
    //   Java source line #435	-> byte code offset #110
    //   Java source line #437	-> byte code offset #112
    //   Java source line #438	-> byte code offset #119
    //   Java source line #439	-> byte code offset #128
    //   Java source line #440	-> byte code offset #133
    //   Java source line #441	-> byte code offset #141
    //   Java source line #442	-> byte code offset #143
    //   Java source line #445	-> byte code offset #148
    //   Java source line #437	-> byte code offset #151
    //   Java source line #438	-> byte code offset #158
    //   Java source line #439	-> byte code offset #167
    //   Java source line #440	-> byte code offset #172
    //   Java source line #441	-> byte code offset #180
    //   Java source line #442	-> byte code offset #182
    //   Java source line #447	-> byte code offset #187
    // Local variable table:
    //   start	length	slot	name	signature
    //   0	188	0	this	LoginDao
    //   0	188	1	rid	int
    //   0	188	2	mid	int
    //   66	2	3	e	java.sql.SQLException
    //   110	39	4	localObject	Object
    //   90	3	5	e	java.sql.SQLException
    //   100	3	5	e	Exception
    //   131	3	5	e	java.sql.SQLException
    //   141	3	5	e	Exception
    //   170	3	5	e	java.sql.SQLException
    //   180	3	5	e	Exception
    // Exception table:
    //   from	to	target	type
    //   0	63	66	java/sql/SQLException
    //   71	87	90	java/sql/SQLException
    //   71	87	100	java/lang/Exception
    //   0	71	110	finally
    //   112	128	131	java/sql/SQLException
    //   112	128	141	java/lang/Exception
    //   151	167	170	java/sql/SQLException
    //   151	167	180	java/lang/Exception
  }
}
