package com;

import java.sql.Connection;
import java.sql.PreparedStatement;
import java.sql.ResultSet;
import java.sql.Statement;

public class usersDao
{
  Connection connection = null;
  PreparedStatement ptmt = null;
  ResultSet rs = null;
  Statement stmt = null;
  String query = "";
  
  /* Error */
  public java.util.List<usersBean> viewAllUsers(int oid)
  {
	  return null;
    // Byte code:
    //   0: ldc 40
    //   2: astore_2
    //   3: new 42	java/util/ArrayList
    //   6: dup
    //   7: invokespecial 44	java/util/ArrayList:<init>	()V
    //   10: astore_3
    //   11: aconst_null
    //   12: astore 4
    //   14: aload_0
    //   15: invokestatic 45	com/ConnectionProvider:getCon	()Ljava/sql/Connection;
    //   18: putfield 20	com/usersDao:connection	Ljava/sql/Connection;
    //   21: aload_0
    //   22: aload_0
    //   23: getfield 20	com/usersDao:connection	Ljava/sql/Connection;
    //   26: aload_2
    //   27: invokeinterface 51 2 0
    //   32: putfield 22	com/usersDao:ptmt	Ljava/sql/PreparedStatement;
    //   35: aload_0
    //   36: getfield 22	com/usersDao:ptmt	Ljava/sql/PreparedStatement;
    //   39: iconst_1
    //   40: iload_1
    //   41: invokeinterface 57 3 0
    //   46: aload_0
    //   47: aload_0
    //   48: getfield 22	com/usersDao:ptmt	Ljava/sql/PreparedStatement;
    //   51: invokeinterface 63 1 0
    //   56: putfield 24	com/usersDao:rs	Ljava/sql/ResultSet;
    //   59: goto +165 -> 224
    //   62: new 67	com/usersBean
    //   65: dup
    //   66: invokespecial 69	com/usersBean:<init>	()V
    //   69: astore 4
    //   71: aload 4
    //   73: aload_0
    //   74: getfield 24	com/usersDao:rs	Ljava/sql/ResultSet;
    //   77: ldc 70
    //   79: invokeinterface 72 2 0
    //   84: invokevirtual 78	com/usersBean:setUser_id	(I)V
    //   87: aload 4
    //   89: aload_0
    //   90: getfield 24	com/usersDao:rs	Ljava/sql/ResultSet;
    //   93: ldc 82
    //   95: invokeinterface 72 2 0
    //   100: invokevirtual 84	com/usersBean:setUser_role	(I)V
    //   103: aload 4
    //   105: aload_0
    //   106: getfield 24	com/usersDao:rs	Ljava/sql/ResultSet;
    //   109: ldc 87
    //   111: invokeinterface 89 2 0
    //   116: invokevirtual 93	com/usersBean:setUser_name	(Ljava/lang/String;)V
    //   119: aload 4
    //   121: aload_0
    //   122: getfield 24	com/usersDao:rs	Ljava/sql/ResultSet;
    //   125: ldc 97
    //   127: invokeinterface 89 2 0
    //   132: invokevirtual 99	com/usersBean:setDesignation	(Ljava/lang/String;)V
    //   135: aload 4
    //   137: aload_0
    //   138: getfield 24	com/usersDao:rs	Ljava/sql/ResultSet;
    //   141: ldc 102
    //   143: invokeinterface 89 2 0
    //   148: invokevirtual 104	com/usersBean:setLogin_name	(Ljava/lang/String;)V
    //   151: aload 4
    //   153: aload_0
    //   154: getfield 24	com/usersDao:rs	Ljava/sql/ResultSet;
    //   157: ldc 107
    //   159: invokeinterface 89 2 0
    //   164: invokevirtual 109	com/usersBean:setUser_password	(Ljava/lang/String;)V
    //   167: aload 4
    //   169: aload_0
    //   170: getfield 24	com/usersDao:rs	Ljava/sql/ResultSet;
    //   173: ldc 112
    //   175: invokeinterface 89 2 0
    //   180: invokevirtual 114	com/usersBean:setContact_phone	(Ljava/lang/String;)V
    //   183: aload 4
    //   185: aload_0
    //   186: getfield 24	com/usersDao:rs	Ljava/sql/ResultSet;
    //   189: ldc 117
    //   191: invokeinterface 89 2 0
    //   196: invokevirtual 119	com/usersBean:setEmail	(Ljava/lang/String;)V
    //   199: aload 4
    //   201: aload_0
    //   202: getfield 24	com/usersDao:rs	Ljava/sql/ResultSet;
    //   205: ldc 122
    //   207: invokeinterface 89 2 0
    //   212: invokevirtual 124	com/usersBean:setRole	(Ljava/lang/String;)V
    //   215: aload_3
    //   216: aload 4
    //   218: invokeinterface 127 2 0
    //   223: pop
    //   224: aload_0
    //   225: getfield 24	com/usersDao:rs	Ljava/sql/ResultSet;
    //   228: invokeinterface 133 1 0
    //   233: ifne -171 -> 62
    //   236: aload_0
    //   237: getfield 24	com/usersDao:rs	Ljava/sql/ResultSet;
    //   240: invokeinterface 137 1 0
    //   245: goto +70 -> 315
    //   248: astore 5
    //   250: aload 5
    //   252: invokevirtual 140	java/sql/SQLException:printStackTrace	()V
    //   255: aload_0
    //   256: getfield 26	com/usersDao:stmt	Ljava/sql/Statement;
    //   259: ifnull +82 -> 341
    //   262: aload_0
    //   263: getfield 26	com/usersDao:stmt	Ljava/sql/Statement;
    //   266: invokeinterface 145 1 0
    //   271: goto +70 -> 341
    //   274: astore 7
    //   276: aload 7
    //   278: invokevirtual 140	java/sql/SQLException:printStackTrace	()V
    //   281: goto +60 -> 341
    //   284: astore 6
    //   286: aload_0
    //   287: getfield 26	com/usersDao:stmt	Ljava/sql/Statement;
    //   290: ifnull +22 -> 312
    //   293: aload_0
    //   294: getfield 26	com/usersDao:stmt	Ljava/sql/Statement;
    //   297: invokeinterface 145 1 0
    //   302: goto +10 -> 312
    //   305: astore 7
    //   307: aload 7
    //   309: invokevirtual 140	java/sql/SQLException:printStackTrace	()V
    //   312: aload 6
    //   314: athrow
    //   315: aload_0
    //   316: getfield 26	com/usersDao:stmt	Ljava/sql/Statement;
    //   319: ifnull +22 -> 341
    //   322: aload_0
    //   323: getfield 26	com/usersDao:stmt	Ljava/sql/Statement;
    //   326: invokeinterface 145 1 0
    //   331: goto +10 -> 341
    //   334: astore 7
    //   336: aload 7
    //   338: invokevirtual 140	java/sql/SQLException:printStackTrace	()V
    //   341: aload_3
    //   342: areturn
    // Line number table:
    //   Java source line #28	-> byte code offset #0
    //   Java source line #29	-> byte code offset #3
    //   Java source line #30	-> byte code offset #11
    //   Java source line #32	-> byte code offset #14
    //   Java source line #33	-> byte code offset #21
    //   Java source line #34	-> byte code offset #35
    //   Java source line #36	-> byte code offset #46
    //   Java source line #37	-> byte code offset #59
    //   Java source line #38	-> byte code offset #62
    //   Java source line #39	-> byte code offset #71
    //   Java source line #40	-> byte code offset #87
    //   Java source line #41	-> byte code offset #103
    //   Java source line #42	-> byte code offset #119
    //   Java source line #43	-> byte code offset #135
    //   Java source line #44	-> byte code offset #151
    //   Java source line #45	-> byte code offset #167
    //   Java source line #46	-> byte code offset #183
    //   Java source line #47	-> byte code offset #199
    //   Java source line #48	-> byte code offset #215
    //   Java source line #37	-> byte code offset #224
    //   Java source line #50	-> byte code offset #236
    //   Java source line #52	-> byte code offset #245
    //   Java source line #56	-> byte code offset #255
    //   Java source line #57	-> byte code offset #262
    //   Java source line #58	-> byte code offset #271
    //   Java source line #59	-> byte code offset #276
    //   Java source line #54	-> byte code offset #284
    //   Java source line #56	-> byte code offset #286
    //   Java source line #57	-> byte code offset #293
    //   Java source line #58	-> byte code offset #302
    //   Java source line #59	-> byte code offset #307
    //   Java source line #61	-> byte code offset #312
    //   Java source line #56	-> byte code offset #315
    //   Java source line #57	-> byte code offset #322
    //   Java source line #58	-> byte code offset #331
    //   Java source line #59	-> byte code offset #336
    //   Java source line #62	-> byte code offset #341
    // Local variable table:
    //   start	length	slot	name	signature
    //   0	343	0	this	usersDao
    //   0	343	1	oid	int
    //   2	25	2	query	String
    //   10	332	3	list	java.util.List<usersBean>
    //   12	205	4	user	usersBean
    //   248	3	5	e	java.sql.SQLException
    //   284	29	6	localObject	Object
    //   274	3	7	e	java.sql.SQLException
    //   305	3	7	e	java.sql.SQLException
    //   334	3	7	e	java.sql.SQLException
    // Exception table:
    //   from	to	target	type
    //   14	245	248	java/sql/SQLException
    //   255	271	274	java/sql/SQLException
    //   14	255	284	finally
    //   286	302	305	java/sql/SQLException
    //   315	331	334	java/sql/SQLException
  }
  
  /* Error */
  public void addUser(usersBean user)
  {
    // Byte code:
    //   0: aload_0
    //   1: ldc -91
    //   3: putfield 30	com/usersDao:query	Ljava/lang/String;
    //   6: aload_0
    //   7: invokestatic 45	com/ConnectionProvider:getCon	()Ljava/sql/Connection;
    //   10: putfield 20	com/usersDao:connection	Ljava/sql/Connection;
    //   13: aload_0
    //   14: aload_0
    //   15: getfield 20	com/usersDao:connection	Ljava/sql/Connection;
    //   18: aload_0
    //   19: getfield 30	com/usersDao:query	Ljava/lang/String;
    //   22: invokeinterface 51 2 0
    //   27: putfield 22	com/usersDao:ptmt	Ljava/sql/PreparedStatement;
    //   30: aload_0
    //   31: getfield 22	com/usersDao:ptmt	Ljava/sql/PreparedStatement;
    //   34: iconst_1
    //   35: aload_1
    //   36: invokevirtual 167	com/usersBean:getDesignation	()Ljava/lang/String;
    //   39: invokeinterface 171 3 0
    //   44: aload_0
    //   45: getfield 22	com/usersDao:ptmt	Ljava/sql/PreparedStatement;
    //   48: iconst_2
    //   49: aload_1
    //   50: invokevirtual 175	com/usersBean:getUser_name	()Ljava/lang/String;
    //   53: invokeinterface 171 3 0
    //   58: aload_0
    //   59: getfield 22	com/usersDao:ptmt	Ljava/sql/PreparedStatement;
    //   62: iconst_3
    //   63: aload_1
    //   64: invokevirtual 178	com/usersBean:getLogin_name	()Ljava/lang/String;
    //   67: invokeinterface 171 3 0
    //   72: aload_0
    //   73: getfield 22	com/usersDao:ptmt	Ljava/sql/PreparedStatement;
    //   76: iconst_4
    //   77: aload_1
    //   78: invokevirtual 181	com/usersBean:getUser_password	()Ljava/lang/String;
    //   81: invokeinterface 171 3 0
    //   86: aload_0
    //   87: getfield 22	com/usersDao:ptmt	Ljava/sql/PreparedStatement;
    //   90: iconst_5
    //   91: aload_1
    //   92: invokevirtual 184	com/usersBean:getContact_phone	()Ljava/lang/String;
    //   95: invokestatic 187	java/lang/Long:parseLong	(Ljava/lang/String;)J
    //   98: invokeinterface 193 4 0
    //   103: aload_0
    //   104: getfield 22	com/usersDao:ptmt	Ljava/sql/PreparedStatement;
    //   107: bipush 6
    //   109: aload_1
    //   110: invokevirtual 197	com/usersBean:getEmail	()Ljava/lang/String;
    //   113: invokeinterface 171 3 0
    //   118: aload_0
    //   119: getfield 22	com/usersDao:ptmt	Ljava/sql/PreparedStatement;
    //   122: bipush 7
    //   124: aload_1
    //   125: invokevirtual 200	com/usersBean:getUser_role	()I
    //   128: invokeinterface 57 3 0
    //   133: aload_0
    //   134: getfield 22	com/usersDao:ptmt	Ljava/sql/PreparedStatement;
    //   137: bipush 8
    //   139: aload_1
    //   140: invokevirtual 204	com/usersBean:getOid	()I
    //   143: invokeinterface 57 3 0
    //   148: aload_0
    //   149: getfield 22	com/usersDao:ptmt	Ljava/sql/PreparedStatement;
    //   152: invokeinterface 207 1 0
    //   157: pop
    //   158: goto +86 -> 244
    //   161: astore_2
    //   162: aload_2
    //   163: invokevirtual 140	java/sql/SQLException:printStackTrace	()V
    //   166: aload_0
    //   167: getfield 22	com/usersDao:ptmt	Ljava/sql/PreparedStatement;
    //   170: ifnull +110 -> 280
    //   173: aload_0
    //   174: getfield 22	com/usersDao:ptmt	Ljava/sql/PreparedStatement;
    //   177: invokeinterface 210 1 0
    //   182: goto +98 -> 280
    //   185: astore 4
    //   187: aload 4
    //   189: invokevirtual 140	java/sql/SQLException:printStackTrace	()V
    //   192: goto +88 -> 280
    //   195: astore 4
    //   197: aload 4
    //   199: invokevirtual 211	java/lang/Exception:printStackTrace	()V
    //   202: goto +78 -> 280
    //   205: astore_3
    //   206: aload_0
    //   207: getfield 22	com/usersDao:ptmt	Ljava/sql/PreparedStatement;
    //   210: ifnull +32 -> 242
    //   213: aload_0
    //   214: getfield 22	com/usersDao:ptmt	Ljava/sql/PreparedStatement;
    //   217: invokeinterface 210 1 0
    //   222: goto +20 -> 242
    //   225: astore 4
    //   227: aload 4
    //   229: invokevirtual 140	java/sql/SQLException:printStackTrace	()V
    //   232: goto +10 -> 242
    //   235: astore 4
    //   237: aload 4
    //   239: invokevirtual 211	java/lang/Exception:printStackTrace	()V
    //   242: aload_3
    //   243: athrow
    //   244: aload_0
    //   245: getfield 22	com/usersDao:ptmt	Ljava/sql/PreparedStatement;
    //   248: ifnull +32 -> 280
    //   251: aload_0
    //   252: getfield 22	com/usersDao:ptmt	Ljava/sql/PreparedStatement;
    //   255: invokeinterface 210 1 0
    //   260: goto +20 -> 280
    //   263: astore 4
    //   265: aload 4
    //   267: invokevirtual 140	java/sql/SQLException:printStackTrace	()V
    //   270: goto +10 -> 280
    //   273: astore 4
    //   275: aload 4
    //   277: invokevirtual 211	java/lang/Exception:printStackTrace	()V
    //   280: return
    // Line number table:
    //   Java source line #67	-> byte code offset #0
    //   Java source line #69	-> byte code offset #6
    //   Java source line #70	-> byte code offset #13
    //   Java source line #71	-> byte code offset #30
    //   Java source line #72	-> byte code offset #44
    //   Java source line #73	-> byte code offset #58
    //   Java source line #74	-> byte code offset #72
    //   Java source line #75	-> byte code offset #86
    //   Java source line #76	-> byte code offset #103
    //   Java source line #77	-> byte code offset #118
    //   Java source line #78	-> byte code offset #133
    //   Java source line #79	-> byte code offset #148
    //   Java source line #80	-> byte code offset #158
    //   Java source line #81	-> byte code offset #162
    //   Java source line #84	-> byte code offset #166
    //   Java source line #85	-> byte code offset #173
    //   Java source line #86	-> byte code offset #182
    //   Java source line #87	-> byte code offset #187
    //   Java source line #88	-> byte code offset #195
    //   Java source line #89	-> byte code offset #197
    //   Java source line #82	-> byte code offset #205
    //   Java source line #84	-> byte code offset #206
    //   Java source line #85	-> byte code offset #213
    //   Java source line #86	-> byte code offset #222
    //   Java source line #87	-> byte code offset #227
    //   Java source line #88	-> byte code offset #235
    //   Java source line #89	-> byte code offset #237
    //   Java source line #92	-> byte code offset #242
    //   Java source line #84	-> byte code offset #244
    //   Java source line #85	-> byte code offset #251
    //   Java source line #86	-> byte code offset #260
    //   Java source line #87	-> byte code offset #265
    //   Java source line #88	-> byte code offset #273
    //   Java source line #89	-> byte code offset #275
    //   Java source line #94	-> byte code offset #280
    // Local variable table:
    //   start	length	slot	name	signature
    //   0	281	0	this	usersDao
    //   0	281	1	user	usersBean
    //   161	2	2	e	java.sql.SQLException
    //   205	38	3	localObject	Object
    //   185	3	4	e	java.sql.SQLException
    //   195	3	4	e	Exception
    //   225	3	4	e	java.sql.SQLException
    //   235	3	4	e	Exception
    //   263	3	4	e	java.sql.SQLException
    //   273	3	4	e	Exception
    // Exception table:
    //   from	to	target	type
    //   0	158	161	java/sql/SQLException
    //   166	182	185	java/sql/SQLException
    //   166	182	195	java/lang/Exception
    //   0	166	205	finally
    //   206	222	225	java/sql/SQLException
    //   206	222	235	java/lang/Exception
    //   244	260	263	java/sql/SQLException
    //   244	260	273	java/lang/Exception
  }
  
  /* Error */
  public void updateUser(usersBean user)
  {
    // Byte code:
    //   0: aload_0
    //   1: ldc -40
    //   3: putfield 30	com/usersDao:query	Ljava/lang/String;
    //   6: aload_0
    //   7: invokestatic 45	com/ConnectionProvider:getCon	()Ljava/sql/Connection;
    //   10: putfield 20	com/usersDao:connection	Ljava/sql/Connection;
    //   13: aload_0
    //   14: aload_0
    //   15: getfield 20	com/usersDao:connection	Ljava/sql/Connection;
    //   18: aload_0
    //   19: getfield 30	com/usersDao:query	Ljava/lang/String;
    //   22: invokeinterface 51 2 0
    //   27: putfield 22	com/usersDao:ptmt	Ljava/sql/PreparedStatement;
    //   30: aload_0
    //   31: getfield 22	com/usersDao:ptmt	Ljava/sql/PreparedStatement;
    //   34: iconst_1
    //   35: aload_1
    //   36: invokevirtual 167	com/usersBean:getDesignation	()Ljava/lang/String;
    //   39: invokeinterface 171 3 0
    //   44: aload_0
    //   45: getfield 22	com/usersDao:ptmt	Ljava/sql/PreparedStatement;
    //   48: iconst_2
    //   49: aload_1
    //   50: invokevirtual 175	com/usersBean:getUser_name	()Ljava/lang/String;
    //   53: invokeinterface 171 3 0
    //   58: aload_0
    //   59: getfield 22	com/usersDao:ptmt	Ljava/sql/PreparedStatement;
    //   62: iconst_3
    //   63: aload_1
    //   64: invokevirtual 178	com/usersBean:getLogin_name	()Ljava/lang/String;
    //   67: invokeinterface 171 3 0
    //   72: aload_0
    //   73: getfield 22	com/usersDao:ptmt	Ljava/sql/PreparedStatement;
    //   76: iconst_4
    //   77: aload_1
    //   78: invokevirtual 181	com/usersBean:getUser_password	()Ljava/lang/String;
    //   81: invokeinterface 171 3 0
    //   86: aload_0
    //   87: getfield 22	com/usersDao:ptmt	Ljava/sql/PreparedStatement;
    //   90: iconst_5
    //   91: aload_1
    //   92: invokevirtual 184	com/usersBean:getContact_phone	()Ljava/lang/String;
    //   95: invokestatic 187	java/lang/Long:parseLong	(Ljava/lang/String;)J
    //   98: invokeinterface 193 4 0
    //   103: aload_0
    //   104: getfield 22	com/usersDao:ptmt	Ljava/sql/PreparedStatement;
    //   107: bipush 6
    //   109: aload_1
    //   110: invokevirtual 197	com/usersBean:getEmail	()Ljava/lang/String;
    //   113: invokeinterface 171 3 0
    //   118: aload_0
    //   119: getfield 22	com/usersDao:ptmt	Ljava/sql/PreparedStatement;
    //   122: bipush 7
    //   124: aload_1
    //   125: invokevirtual 200	com/usersBean:getUser_role	()I
    //   128: invokeinterface 57 3 0
    //   133: aload_0
    //   134: getfield 22	com/usersDao:ptmt	Ljava/sql/PreparedStatement;
    //   137: bipush 8
    //   139: aload_1
    //   140: invokevirtual 218	com/usersBean:getUser_id	()I
    //   143: invokeinterface 57 3 0
    //   148: aload_0
    //   149: getfield 22	com/usersDao:ptmt	Ljava/sql/PreparedStatement;
    //   152: invokeinterface 207 1 0
    //   157: pop
    //   158: goto +86 -> 244
    //   161: astore_2
    //   162: aload_2
    //   163: invokevirtual 140	java/sql/SQLException:printStackTrace	()V
    //   166: aload_0
    //   167: getfield 22	com/usersDao:ptmt	Ljava/sql/PreparedStatement;
    //   170: ifnull +110 -> 280
    //   173: aload_0
    //   174: getfield 22	com/usersDao:ptmt	Ljava/sql/PreparedStatement;
    //   177: invokeinterface 210 1 0
    //   182: goto +98 -> 280
    //   185: astore 4
    //   187: aload 4
    //   189: invokevirtual 140	java/sql/SQLException:printStackTrace	()V
    //   192: goto +88 -> 280
    //   195: astore 4
    //   197: aload 4
    //   199: invokevirtual 211	java/lang/Exception:printStackTrace	()V
    //   202: goto +78 -> 280
    //   205: astore_3
    //   206: aload_0
    //   207: getfield 22	com/usersDao:ptmt	Ljava/sql/PreparedStatement;
    //   210: ifnull +32 -> 242
    //   213: aload_0
    //   214: getfield 22	com/usersDao:ptmt	Ljava/sql/PreparedStatement;
    //   217: invokeinterface 210 1 0
    //   222: goto +20 -> 242
    //   225: astore 4
    //   227: aload 4
    //   229: invokevirtual 140	java/sql/SQLException:printStackTrace	()V
    //   232: goto +10 -> 242
    //   235: astore 4
    //   237: aload 4
    //   239: invokevirtual 211	java/lang/Exception:printStackTrace	()V
    //   242: aload_3
    //   243: athrow
    //   244: aload_0
    //   245: getfield 22	com/usersDao:ptmt	Ljava/sql/PreparedStatement;
    //   248: ifnull +32 -> 280
    //   251: aload_0
    //   252: getfield 22	com/usersDao:ptmt	Ljava/sql/PreparedStatement;
    //   255: invokeinterface 210 1 0
    //   260: goto +20 -> 280
    //   263: astore 4
    //   265: aload 4
    //   267: invokevirtual 140	java/sql/SQLException:printStackTrace	()V
    //   270: goto +10 -> 280
    //   273: astore 4
    //   275: aload 4
    //   277: invokevirtual 211	java/lang/Exception:printStackTrace	()V
    //   280: return
    // Line number table:
    //   Java source line #99	-> byte code offset #0
    //   Java source line #101	-> byte code offset #6
    //   Java source line #102	-> byte code offset #13
    //   Java source line #103	-> byte code offset #30
    //   Java source line #104	-> byte code offset #44
    //   Java source line #105	-> byte code offset #58
    //   Java source line #106	-> byte code offset #72
    //   Java source line #107	-> byte code offset #86
    //   Java source line #108	-> byte code offset #103
    //   Java source line #109	-> byte code offset #118
    //   Java source line #110	-> byte code offset #133
    //   Java source line #111	-> byte code offset #148
    //   Java source line #112	-> byte code offset #158
    //   Java source line #113	-> byte code offset #162
    //   Java source line #116	-> byte code offset #166
    //   Java source line #117	-> byte code offset #173
    //   Java source line #118	-> byte code offset #182
    //   Java source line #119	-> byte code offset #187
    //   Java source line #120	-> byte code offset #195
    //   Java source line #121	-> byte code offset #197
    //   Java source line #114	-> byte code offset #205
    //   Java source line #116	-> byte code offset #206
    //   Java source line #117	-> byte code offset #213
    //   Java source line #118	-> byte code offset #222
    //   Java source line #119	-> byte code offset #227
    //   Java source line #120	-> byte code offset #235
    //   Java source line #121	-> byte code offset #237
    //   Java source line #124	-> byte code offset #242
    //   Java source line #116	-> byte code offset #244
    //   Java source line #117	-> byte code offset #251
    //   Java source line #118	-> byte code offset #260
    //   Java source line #119	-> byte code offset #265
    //   Java source line #120	-> byte code offset #273
    //   Java source line #121	-> byte code offset #275
    //   Java source line #126	-> byte code offset #280
    // Local variable table:
    //   start	length	slot	name	signature
    //   0	281	0	this	usersDao
    //   0	281	1	user	usersBean
    //   161	2	2	e	java.sql.SQLException
    //   205	38	3	localObject	Object
    //   185	3	4	e	java.sql.SQLException
    //   195	3	4	e	Exception
    //   225	3	4	e	java.sql.SQLException
    //   235	3	4	e	Exception
    //   263	3	4	e	java.sql.SQLException
    //   273	3	4	e	Exception
    // Exception table:
    //   from	to	target	type
    //   0	158	161	java/sql/SQLException
    //   166	182	185	java/sql/SQLException
    //   166	182	195	java/lang/Exception
    //   0	166	205	finally
    //   206	222	225	java/sql/SQLException
    //   206	222	235	java/lang/Exception
    //   244	260	263	java/sql/SQLException
    //   244	260	273	java/lang/Exception
  }
  
  /* Error */
  public void searchUser(usersBean user)
  {
    // Byte code:
    //   0: aload_0
    //   1: ldc -34
    //   3: putfield 30	com/usersDao:query	Ljava/lang/String;
    //   6: aload_0
    //   7: invokestatic 45	com/ConnectionProvider:getCon	()Ljava/sql/Connection;
    //   10: putfield 20	com/usersDao:connection	Ljava/sql/Connection;
    //   13: aload_0
    //   14: aload_0
    //   15: getfield 20	com/usersDao:connection	Ljava/sql/Connection;
    //   18: aload_0
    //   19: getfield 30	com/usersDao:query	Ljava/lang/String;
    //   22: invokeinterface 51 2 0
    //   27: putfield 22	com/usersDao:ptmt	Ljava/sql/PreparedStatement;
    //   30: aload_0
    //   31: getfield 22	com/usersDao:ptmt	Ljava/sql/PreparedStatement;
    //   34: iconst_1
    //   35: aload_1
    //   36: invokevirtual 218	com/usersBean:getUser_id	()I
    //   39: invokeinterface 57 3 0
    //   44: aload_0
    //   45: aload_0
    //   46: getfield 22	com/usersDao:ptmt	Ljava/sql/PreparedStatement;
    //   49: invokeinterface 63 1 0
    //   54: putfield 24	com/usersDao:rs	Ljava/sql/ResultSet;
    //   57: aload_0
    //   58: getfield 24	com/usersDao:rs	Ljava/sql/ResultSet;
    //   61: invokeinterface 133 1 0
    //   66: pop
    //   67: aload_1
    //   68: aload_0
    //   69: getfield 24	com/usersDao:rs	Ljava/sql/ResultSet;
    //   72: ldc 70
    //   74: invokeinterface 72 2 0
    //   79: invokevirtual 78	com/usersBean:setUser_id	(I)V
    //   82: aload_1
    //   83: aload_0
    //   84: getfield 24	com/usersDao:rs	Ljava/sql/ResultSet;
    //   87: ldc 82
    //   89: invokeinterface 72 2 0
    //   94: invokevirtual 84	com/usersBean:setUser_role	(I)V
    //   97: aload_1
    //   98: aload_0
    //   99: getfield 24	com/usersDao:rs	Ljava/sql/ResultSet;
    //   102: ldc 87
    //   104: invokeinterface 89 2 0
    //   109: invokevirtual 93	com/usersBean:setUser_name	(Ljava/lang/String;)V
    //   112: aload_1
    //   113: aload_0
    //   114: getfield 24	com/usersDao:rs	Ljava/sql/ResultSet;
    //   117: ldc 97
    //   119: invokeinterface 89 2 0
    //   124: invokevirtual 99	com/usersBean:setDesignation	(Ljava/lang/String;)V
    //   127: aload_1
    //   128: aload_0
    //   129: getfield 24	com/usersDao:rs	Ljava/sql/ResultSet;
    //   132: ldc 102
    //   134: invokeinterface 89 2 0
    //   139: invokevirtual 104	com/usersBean:setLogin_name	(Ljava/lang/String;)V
    //   142: aload_1
    //   143: aload_0
    //   144: getfield 24	com/usersDao:rs	Ljava/sql/ResultSet;
    //   147: ldc 107
    //   149: invokeinterface 89 2 0
    //   154: invokevirtual 109	com/usersBean:setUser_password	(Ljava/lang/String;)V
    //   157: aload_1
    //   158: aload_0
    //   159: getfield 24	com/usersDao:rs	Ljava/sql/ResultSet;
    //   162: ldc 112
    //   164: invokeinterface 89 2 0
    //   169: invokevirtual 114	com/usersBean:setContact_phone	(Ljava/lang/String;)V
    //   172: aload_1
    //   173: aload_0
    //   174: getfield 24	com/usersDao:rs	Ljava/sql/ResultSet;
    //   177: ldc 117
    //   179: invokeinterface 89 2 0
    //   184: invokevirtual 119	com/usersBean:setEmail	(Ljava/lang/String;)V
    //   187: aload_1
    //   188: aload_0
    //   189: getfield 24	com/usersDao:rs	Ljava/sql/ResultSet;
    //   192: ldc 122
    //   194: invokeinterface 89 2 0
    //   199: invokevirtual 124	com/usersBean:setRole	(Ljava/lang/String;)V
    //   202: goto +118 -> 320
    //   205: astore_2
    //   206: aload_2
    //   207: invokevirtual 140	java/sql/SQLException:printStackTrace	()V
    //   210: aload_0
    //   211: getfield 24	com/usersDao:rs	Ljava/sql/ResultSet;
    //   214: ifnull +12 -> 226
    //   217: aload_0
    //   218: getfield 24	com/usersDao:rs	Ljava/sql/ResultSet;
    //   221: invokeinterface 137 1 0
    //   226: aload_0
    //   227: getfield 22	com/usersDao:ptmt	Ljava/sql/PreparedStatement;
    //   230: ifnull +142 -> 372
    //   233: aload_0
    //   234: getfield 22	com/usersDao:ptmt	Ljava/sql/PreparedStatement;
    //   237: invokeinterface 210 1 0
    //   242: goto +130 -> 372
    //   245: astore 4
    //   247: aload 4
    //   249: invokevirtual 140	java/sql/SQLException:printStackTrace	()V
    //   252: goto +120 -> 372
    //   255: astore 4
    //   257: aload 4
    //   259: invokevirtual 211	java/lang/Exception:printStackTrace	()V
    //   262: goto +110 -> 372
    //   265: astore_3
    //   266: aload_0
    //   267: getfield 24	com/usersDao:rs	Ljava/sql/ResultSet;
    //   270: ifnull +12 -> 282
    //   273: aload_0
    //   274: getfield 24	com/usersDao:rs	Ljava/sql/ResultSet;
    //   277: invokeinterface 137 1 0
    //   282: aload_0
    //   283: getfield 22	com/usersDao:ptmt	Ljava/sql/PreparedStatement;
    //   286: ifnull +32 -> 318
    //   289: aload_0
    //   290: getfield 22	com/usersDao:ptmt	Ljava/sql/PreparedStatement;
    //   293: invokeinterface 210 1 0
    //   298: goto +20 -> 318
    //   301: astore 4
    //   303: aload 4
    //   305: invokevirtual 140	java/sql/SQLException:printStackTrace	()V
    //   308: goto +10 -> 318
    //   311: astore 4
    //   313: aload 4
    //   315: invokevirtual 211	java/lang/Exception:printStackTrace	()V
    //   318: aload_3
    //   319: athrow
    //   320: aload_0
    //   321: getfield 24	com/usersDao:rs	Ljava/sql/ResultSet;
    //   324: ifnull +12 -> 336
    //   327: aload_0
    //   328: getfield 24	com/usersDao:rs	Ljava/sql/ResultSet;
    //   331: invokeinterface 137 1 0
    //   336: aload_0
    //   337: getfield 22	com/usersDao:ptmt	Ljava/sql/PreparedStatement;
    //   340: ifnull +32 -> 372
    //   343: aload_0
    //   344: getfield 22	com/usersDao:ptmt	Ljava/sql/PreparedStatement;
    //   347: invokeinterface 210 1 0
    //   352: goto +20 -> 372
    //   355: astore 4
    //   357: aload 4
    //   359: invokevirtual 140	java/sql/SQLException:printStackTrace	()V
    //   362: goto +10 -> 372
    //   365: astore 4
    //   367: aload 4
    //   369: invokevirtual 211	java/lang/Exception:printStackTrace	()V
    //   372: return
    // Line number table:
    //   Java source line #131	-> byte code offset #0
    //   Java source line #133	-> byte code offset #6
    //   Java source line #134	-> byte code offset #13
    //   Java source line #135	-> byte code offset #30
    //   Java source line #138	-> byte code offset #44
    //   Java source line #139	-> byte code offset #57
    //   Java source line #140	-> byte code offset #67
    //   Java source line #141	-> byte code offset #82
    //   Java source line #142	-> byte code offset #97
    //   Java source line #143	-> byte code offset #112
    //   Java source line #144	-> byte code offset #127
    //   Java source line #145	-> byte code offset #142
    //   Java source line #146	-> byte code offset #157
    //   Java source line #147	-> byte code offset #172
    //   Java source line #148	-> byte code offset #187
    //   Java source line #149	-> byte code offset #202
    //   Java source line #150	-> byte code offset #206
    //   Java source line #153	-> byte code offset #210
    //   Java source line #154	-> byte code offset #217
    //   Java source line #155	-> byte code offset #226
    //   Java source line #156	-> byte code offset #233
    //   Java source line #157	-> byte code offset #242
    //   Java source line #158	-> byte code offset #247
    //   Java source line #159	-> byte code offset #255
    //   Java source line #160	-> byte code offset #257
    //   Java source line #151	-> byte code offset #265
    //   Java source line #153	-> byte code offset #266
    //   Java source line #154	-> byte code offset #273
    //   Java source line #155	-> byte code offset #282
    //   Java source line #156	-> byte code offset #289
    //   Java source line #157	-> byte code offset #298
    //   Java source line #158	-> byte code offset #303
    //   Java source line #159	-> byte code offset #311
    //   Java source line #160	-> byte code offset #313
    //   Java source line #163	-> byte code offset #318
    //   Java source line #153	-> byte code offset #320
    //   Java source line #154	-> byte code offset #327
    //   Java source line #155	-> byte code offset #336
    //   Java source line #156	-> byte code offset #343
    //   Java source line #157	-> byte code offset #352
    //   Java source line #158	-> byte code offset #357
    //   Java source line #159	-> byte code offset #365
    //   Java source line #160	-> byte code offset #367
    //   Java source line #164	-> byte code offset #372
    // Local variable table:
    //   start	length	slot	name	signature
    //   0	373	0	this	usersDao
    //   0	373	1	user	usersBean
    //   205	2	2	e	java.sql.SQLException
    //   265	54	3	localObject	Object
    //   245	3	4	e	java.sql.SQLException
    //   255	3	4	e	Exception
    //   301	3	4	e	java.sql.SQLException
    //   311	3	4	e	Exception
    //   355	3	4	e	java.sql.SQLException
    //   365	3	4	e	Exception
    // Exception table:
    //   from	to	target	type
    //   0	202	205	java/sql/SQLException
    //   210	242	245	java/sql/SQLException
    //   210	242	255	java/lang/Exception
    //   0	210	265	finally
    //   266	298	301	java/sql/SQLException
    //   266	298	311	java/lang/Exception
    //   320	352	355	java/sql/SQLException
    //   320	352	365	java/lang/Exception
  }
  
  /* Error */
  public void delete(int userid)
  {
    // Byte code:
    //   0: aload_0
    //   1: invokestatic 45	com/ConnectionProvider:getCon	()Ljava/sql/Connection;
    //   4: putfield 20	com/usersDao:connection	Ljava/sql/Connection;
    //   7: aload_0
    //   8: ldc -31
    //   10: putfield 30	com/usersDao:query	Ljava/lang/String;
    //   13: aload_0
    //   14: aload_0
    //   15: getfield 20	com/usersDao:connection	Ljava/sql/Connection;
    //   18: aload_0
    //   19: getfield 30	com/usersDao:query	Ljava/lang/String;
    //   22: invokeinterface 51 2 0
    //   27: putfield 22	com/usersDao:ptmt	Ljava/sql/PreparedStatement;
    //   30: aload_0
    //   31: getfield 22	com/usersDao:ptmt	Ljava/sql/PreparedStatement;
    //   34: iconst_1
    //   35: iload_1
    //   36: invokeinterface 57 3 0
    //   41: aload_0
    //   42: getfield 22	com/usersDao:ptmt	Ljava/sql/PreparedStatement;
    //   45: invokeinterface 207 1 0
    //   50: pop
    //   51: goto +86 -> 137
    //   54: astore_2
    //   55: aload_2
    //   56: invokevirtual 140	java/sql/SQLException:printStackTrace	()V
    //   59: aload_0
    //   60: getfield 22	com/usersDao:ptmt	Ljava/sql/PreparedStatement;
    //   63: ifnull +110 -> 173
    //   66: aload_0
    //   67: getfield 22	com/usersDao:ptmt	Ljava/sql/PreparedStatement;
    //   70: invokeinterface 210 1 0
    //   75: goto +98 -> 173
    //   78: astore 4
    //   80: aload 4
    //   82: invokevirtual 140	java/sql/SQLException:printStackTrace	()V
    //   85: goto +88 -> 173
    //   88: astore 4
    //   90: aload 4
    //   92: invokevirtual 211	java/lang/Exception:printStackTrace	()V
    //   95: goto +78 -> 173
    //   98: astore_3
    //   99: aload_0
    //   100: getfield 22	com/usersDao:ptmt	Ljava/sql/PreparedStatement;
    //   103: ifnull +32 -> 135
    //   106: aload_0
    //   107: getfield 22	com/usersDao:ptmt	Ljava/sql/PreparedStatement;
    //   110: invokeinterface 210 1 0
    //   115: goto +20 -> 135
    //   118: astore 4
    //   120: aload 4
    //   122: invokevirtual 140	java/sql/SQLException:printStackTrace	()V
    //   125: goto +10 -> 135
    //   128: astore 4
    //   130: aload 4
    //   132: invokevirtual 211	java/lang/Exception:printStackTrace	()V
    //   135: aload_3
    //   136: athrow
    //   137: aload_0
    //   138: getfield 22	com/usersDao:ptmt	Ljava/sql/PreparedStatement;
    //   141: ifnull +32 -> 173
    //   144: aload_0
    //   145: getfield 22	com/usersDao:ptmt	Ljava/sql/PreparedStatement;
    //   148: invokeinterface 210 1 0
    //   153: goto +20 -> 173
    //   156: astore 4
    //   158: aload 4
    //   160: invokevirtual 140	java/sql/SQLException:printStackTrace	()V
    //   163: goto +10 -> 173
    //   166: astore 4
    //   168: aload 4
    //   170: invokevirtual 211	java/lang/Exception:printStackTrace	()V
    //   173: return
    // Line number table:
    //   Java source line #172	-> byte code offset #0
    //   Java source line #173	-> byte code offset #7
    //   Java source line #174	-> byte code offset #13
    //   Java source line #175	-> byte code offset #30
    //   Java source line #176	-> byte code offset #41
    //   Java source line #179	-> byte code offset #51
    //   Java source line #180	-> byte code offset #55
    //   Java source line #183	-> byte code offset #59
    //   Java source line #184	-> byte code offset #66
    //   Java source line #185	-> byte code offset #75
    //   Java source line #186	-> byte code offset #80
    //   Java source line #187	-> byte code offset #88
    //   Java source line #188	-> byte code offset #90
    //   Java source line #181	-> byte code offset #98
    //   Java source line #183	-> byte code offset #99
    //   Java source line #184	-> byte code offset #106
    //   Java source line #185	-> byte code offset #115
    //   Java source line #186	-> byte code offset #120
    //   Java source line #187	-> byte code offset #128
    //   Java source line #188	-> byte code offset #130
    //   Java source line #191	-> byte code offset #135
    //   Java source line #183	-> byte code offset #137
    //   Java source line #184	-> byte code offset #144
    //   Java source line #185	-> byte code offset #153
    //   Java source line #186	-> byte code offset #158
    //   Java source line #187	-> byte code offset #166
    //   Java source line #188	-> byte code offset #168
    //   Java source line #193	-> byte code offset #173
    // Local variable table:
    //   start	length	slot	name	signature
    //   0	174	0	this	usersDao
    //   0	174	1	userid	int
    //   54	2	2	e	java.sql.SQLException
    //   98	38	3	localObject	Object
    //   78	3	4	e	java.sql.SQLException
    //   88	3	4	e	Exception
    //   118	3	4	e	java.sql.SQLException
    //   128	3	4	e	Exception
    //   156	3	4	e	java.sql.SQLException
    //   166	3	4	e	Exception
    // Exception table:
    //   from	to	target	type
    //   0	51	54	java/sql/SQLException
    //   59	75	78	java/sql/SQLException
    //   59	75	88	java/lang/Exception
    //   0	59	98	finally
    //   99	115	118	java/sql/SQLException
    //   99	115	128	java/lang/Exception
    //   137	153	156	java/sql/SQLException
    //   137	153	166	java/lang/Exception
  }
  
  /* Error */
  public java.util.List<usersBean> listRoles()
  {
	  return null;
    // Byte code:
    //   0: ldc -25
    //   2: astore_1
    //   3: new 42	java/util/ArrayList
    //   6: dup
    //   7: invokespecial 44	java/util/ArrayList:<init>	()V
    //   10: astore_2
    //   11: aconst_null
    //   12: astore_3
    //   13: aload_0
    //   14: invokestatic 45	com/ConnectionProvider:getCon	()Ljava/sql/Connection;
    //   17: putfield 20	com/usersDao:connection	Ljava/sql/Connection;
    //   20: aload_0
    //   21: aload_0
    //   22: getfield 20	com/usersDao:connection	Ljava/sql/Connection;
    //   25: aload_1
    //   26: invokeinterface 51 2 0
    //   31: putfield 22	com/usersDao:ptmt	Ljava/sql/PreparedStatement;
    //   34: aload_0
    //   35: aload_0
    //   36: getfield 22	com/usersDao:ptmt	Ljava/sql/PreparedStatement;
    //   39: invokeinterface 63 1 0
    //   44: putfield 24	com/usersDao:rs	Ljava/sql/ResultSet;
    //   47: goto +49 -> 96
    //   50: new 67	com/usersBean
    //   53: dup
    //   54: invokespecial 69	com/usersBean:<init>	()V
    //   57: astore_3
    //   58: aload_3
    //   59: aload_0
    //   60: getfield 24	com/usersDao:rs	Ljava/sql/ResultSet;
    //   63: ldc -23
    //   65: invokeinterface 72 2 0
    //   70: invokevirtual 84	com/usersBean:setUser_role	(I)V
    //   73: aload_3
    //   74: aload_0
    //   75: getfield 24	com/usersDao:rs	Ljava/sql/ResultSet;
    //   78: ldc 122
    //   80: invokeinterface 89 2 0
    //   85: invokevirtual 124	com/usersBean:setRole	(Ljava/lang/String;)V
    //   88: aload_2
    //   89: aload_3
    //   90: invokeinterface 127 2 0
    //   95: pop
    //   96: aload_0
    //   97: getfield 24	com/usersDao:rs	Ljava/sql/ResultSet;
    //   100: invokeinterface 133 1 0
    //   105: ifne -55 -> 50
    //   108: aload_0
    //   109: getfield 24	com/usersDao:rs	Ljava/sql/ResultSet;
    //   112: invokeinterface 137 1 0
    //   117: goto +70 -> 187
    //   120: astore 4
    //   122: aload 4
    //   124: invokevirtual 140	java/sql/SQLException:printStackTrace	()V
    //   127: aload_0
    //   128: getfield 26	com/usersDao:stmt	Ljava/sql/Statement;
    //   131: ifnull +82 -> 213
    //   134: aload_0
    //   135: getfield 26	com/usersDao:stmt	Ljava/sql/Statement;
    //   138: invokeinterface 145 1 0
    //   143: goto +70 -> 213
    //   146: astore 6
    //   148: aload 6
    //   150: invokevirtual 140	java/sql/SQLException:printStackTrace	()V
    //   153: goto +60 -> 213
    //   156: astore 5
    //   158: aload_0
    //   159: getfield 26	com/usersDao:stmt	Ljava/sql/Statement;
    //   162: ifnull +22 -> 184
    //   165: aload_0
    //   166: getfield 26	com/usersDao:stmt	Ljava/sql/Statement;
    //   169: invokeinterface 145 1 0
    //   174: goto +10 -> 184
    //   177: astore 6
    //   179: aload 6
    //   181: invokevirtual 140	java/sql/SQLException:printStackTrace	()V
    //   184: aload 5
    //   186: athrow
    //   187: aload_0
    //   188: getfield 26	com/usersDao:stmt	Ljava/sql/Statement;
    //   191: ifnull +22 -> 213
    //   194: aload_0
    //   195: getfield 26	com/usersDao:stmt	Ljava/sql/Statement;
    //   198: invokeinterface 145 1 0
    //   203: goto +10 -> 213
    //   206: astore 6
    //   208: aload 6
    //   210: invokevirtual 140	java/sql/SQLException:printStackTrace	()V
    //   213: aload_2
    //   214: areturn
    // Line number table:
    //   Java source line #198	-> byte code offset #0
    //   Java source line #199	-> byte code offset #3
    //   Java source line #201	-> byte code offset #11
    //   Java source line #203	-> byte code offset #13
    //   Java source line #204	-> byte code offset #20
    //   Java source line #205	-> byte code offset #34
    //   Java source line #207	-> byte code offset #47
    //   Java source line #208	-> byte code offset #50
    //   Java source line #209	-> byte code offset #58
    //   Java source line #210	-> byte code offset #73
    //   Java source line #211	-> byte code offset #88
    //   Java source line #207	-> byte code offset #96
    //   Java source line #213	-> byte code offset #108
    //   Java source line #215	-> byte code offset #117
    //   Java source line #219	-> byte code offset #127
    //   Java source line #220	-> byte code offset #134
    //   Java source line #221	-> byte code offset #143
    //   Java source line #222	-> byte code offset #148
    //   Java source line #217	-> byte code offset #156
    //   Java source line #219	-> byte code offset #158
    //   Java source line #220	-> byte code offset #165
    //   Java source line #221	-> byte code offset #174
    //   Java source line #222	-> byte code offset #179
    //   Java source line #224	-> byte code offset #184
    //   Java source line #219	-> byte code offset #187
    //   Java source line #220	-> byte code offset #194
    //   Java source line #221	-> byte code offset #203
    //   Java source line #222	-> byte code offset #208
    //   Java source line #225	-> byte code offset #213
    // Local variable table:
    //   start	length	slot	name	signature
    //   0	215	0	this	usersDao
    //   2	24	1	query	String
    //   10	204	2	list	java.util.List<usersBean>
    //   12	78	3	user	usersBean
    //   120	3	4	e	java.sql.SQLException
    //   156	29	5	localObject	Object
    //   146	3	6	e	java.sql.SQLException
    //   177	3	6	e	java.sql.SQLException
    //   206	3	6	e	java.sql.SQLException
    // Exception table:
    //   from	to	target	type
    //   13	117	120	java/sql/SQLException
    //   127	143	146	java/sql/SQLException
    //   13	127	156	finally
    //   158	174	177	java/sql/SQLException
    //   187	203	206	java/sql/SQLException
  }
}
